Workbook

Sheet INDEX
A7: APARTMENT CORP — COMPETITIVE RENT COMP ANALYSIS 2026
A8: LEGEND for Each sheet: 3 GREEN rows = Affordable/Low-Income comps (LIHTC/Section 8/HUD) | 6 BLUE rows = Market Rate comps (no income restrictions) Rents: Low (50% AMI) | Mid (60% AMI LIHTC ceiling) | FMR (HUD Fair Market Rent) | Actual (verified advertised rent)
A9: # | B9: Property Name | C9: City, State | D9: Year Built | E9: Units | F9: Program | G9: Sheet Name | H9: Bedroom Mix | I9: Comp Types
A10: 1 | B10: Boca Ciega | C10: St. Petersburg, FL | D10: 1974 | E10: 109 | F10: Layered HUD/LIHTC | G10: 21 - Boca Ciega | H10: 2BR / 3BR | I10: 3 Affordable (Green) + 6 Market Rate (Blue)
A11: 2 | B11: Jefferson Arms | C11: Monticello, FL | D11: 1971 | E11: 75 | F11: Section 8/HUD | G11: 13 - Jefferson | H11: 2BR / 3BR | I11: 3 Affordable (Green) + 6 Market Rate (Blue)
A12: 3 | B12: Opa Locka 135th St | C12: Opa Locka, FL | D12: 1968 | E12: 65 | F12: Section 8/HUD | G12: 18 - Opa Locka | H12: 1BR / 2BR / 3BR | I12: 3 Affordable (Green) + 6 Market Rate (Blue)
A13: 4 | B13: Macedonia Garden | C13: Panama City, FL | D13: 1969 | E13: 100 | F13: Section 8/HUD | G13: 14 - Macedonia | H13: 2BR / 3BR | I13: 3 Affordable (Green) + 6 Market Rate (Blue)
A14: 5 | B14: Coral Village | C14: Cape Coral, FL | D14: 1999 | E14: 72 | F14: Section 8/HUD | G14: 48 - Coral Village | H14: 1BR / 2BR | I14: 3 Affordable (Green) + 6 Market Rate (Blue)
A15: 6 | B15: Holiday Apts | C15: Natchez, MS | D15: 1951 | E15: 115 | F15: Section 8/HUD | G15: 15 - Holiday | H15: 2BR / 3BR / 4BR / 5BR | I15: 3 Affordable (Green) + 6 Market Rate (Blue)
A16: 7 | B16: Cumberland | C16: Crystal Springs, MS | D16: 1985 | E16: 68 | F16: Section 8/HUD | G16: 16 - Cumberland | H16: 1BR / 2BR / 3BR / 4BR | I16: 3 Affordable (Green) + 6 Market Rate (Blue)
A17: 8 | B17: Village Green | C17: Natchez, MS | D17: 1977 | E17: 80 | F17: Section 8/HUD | G17: 17 - Village Green | H17: 1BR / 2BR / 3BR | I17: 3 Affordable (Green) + 6 Market Rate (Blue)
A18: 9 | B18: Walnut Hill | C18: Natchez, MS | D18: 1975 | E18: 168 | F18: Section 8/HUD | G18: 59 - Walnut Hill | H18: 2BR / 3BR | I18: 3 Affordable (Green) + 6 Market Rate (Blue)
A19: 10 | B19: River Pointe | C19: Columbus, OH | D19: 1996 | E19: 160 | F19: Section 8/HUD | G19: 29 - River Pointe | H19: 1BR / 2BR | I19: 3 Affordable (Green) + 6 Market Rate (Blue)
A20: 11 | B20: Breckenridge Village | C20: Ennis, TX | D20: 1997 | E20: 66 | F20: LIHTC | G20: 12 - Breckenridge | H20: 2BR / 4BR | I20: 3 Affordable (Green) + 6 Market Rate (Blue)
A21: 12 | B21: Lexington Arms | C21: Waxahachie, TX | D21: 1997 | E21: 61 | F21: LIHTC | G21: 38 - Lexington | H21: 2BR / 4BR | I21: 3 Affordable (Green) + 6 Market Rate (Blue)
... A24: 15 | B24: La Promesa | C24: Odessa, TX | D24: 1978 | E24: 136 | F24: Layered HUD/LIHTC | G24: 60 - La Promesa | H24: 2BR / 3BR | I24: 3 Affordable (Green) + 6 Market Rate (Blue)
A25: 16 | B25: New Wilmington Arms | C25: Compton, CA | D25: 1973 | E25: N/A | F25: Section 8/HUD | G25: 3 - Wilmington | H25: 1BR / 2BR / 3BR / 4BR | I25: 3 Affordable (Green) + 6 Market Rate (Blue)
A26: 17 | B26: Gates on Manhattan | C26: Harvey, LA | D26: 1968 | E26: 276 | F26: Section 8/HUD | G26: 19 - Gates | H26: 1BR / 2BR / 3BR | I26: 3 Affordable (Green) + 6 Market Rate (Blue)
A27: 18 | B27: Ruby Diamond | C27: Marrero, LA | D27: 2000 | E27: 73 | F27: LIHTC | G27: 42 - Ruby | H27: 3BR / 4BR | I27: 3 Affordable (Green) + 6 Market Rate (Blue)
A28: 19 | B28: Star Homes | C28: Marrero, LA | D28: 2000 | E28: 48 | F28: LIHTC | G28: 39 - Star | H28: 2BR / 3BR / 4BR | I28: 3 Affordable (Green) + 6 Market Rate (Blue)
A29: 20 | B29: Colonial Estates (Thibodaux) | C29: Thibodaux, LA | D29: 1975 | E29: 107 | F29: Section 8/HUD | G29: 20 - Thibodaux | H29: 1BR / 2BR / 3BR | I29: 3 Affordable (Green) + 6 Market Rate (Blue)
A30: 21 | B30: Marrero 3 | C30: Harvey, LA | D30: 1968 | E30: 173 | F30: Section 8/HUD | G30: 40 - Marrero | H30: 3BR / 4BR | I30: 3 Affordable (Green) + 6 Market Rate (Blue)
A31: 22 | B31: Arbor Crest | C31: Quincy, FL | D31: 1995 | E31: 120 | F31: LIHTC | G31: 37 - Arbor Crest | H31: 1BR / 2BR / 3BR | I31: 3 Affordable (Green) + 6 Market Rate (Blue)
A32: 23 | B32: Windsor/Yorkshire | C32: Shreveport, LA | D32: 1998 | E32: 134 | F32: LIHTC | G32: 33 - Windsor-Yorkshire | H32: 1BR / 2BR / 4BR | I32: 3 Affordable (Green) + 6 Market Rate (Blue)
A33: 24 | B33: North Pointe | C33: Bossier City, LA | D33: 2000 | E33: 27 | F33: LIHTC | G33: 50 - North Pointe | H33: 2BR / 3BR / 4BR | I33: 3 Affordable (Green) + 6 Market Rate (Blue)
A34: 25 | B34: Granite Bayou | C34: Baton Rouge, LA | D34: 2000 | E34: 60 | F34: LIHTC | G34: 53 - Bayou Pointe | H34: 3BR / 4BR | I34: 3 Affordable (Green) + 6 Market Rate (Blue)
A35: 26 | B35: St. Charles Place | C35: Lake Charles, LA | D35: 1995 | E35: 121 | F35: Layered HUD/LIHTC | G35: 41 - St. Charles | H35: 2BR / 3BR | I35: 3 Affordable (Green) + 6 Market Rate (Blue)
A36: 27 | B36: Pelican Bay | C36: Baton Rouge, LA | D36: 2001 | E36: 152 | F36: Section 8/HUD | G36: 55 - Pelican Bay | H36: 1BR / 2BR / 3BR / 4BR | I36: 3 Affordable (Green) + 6 Market Rate (Blue)
A37: 28 | B37: Howell Place | C37: Baton Rouge, LA | D37: 2001 | E37: 48 | F37: Section 8/HUD | G37: 56 - Howell Place | H37: 1BR / 2BR / 3BR / 4BR | I37: 3 Affordable (Green) + 6 Market Rate (Blue)
... A50: 42 | B50: Thomasville Church Homes | C50: Thomasville, NC | D50: 1975 | E50: 100 | F50: Section 8/HUD | G50: 44 - Thomasville | H50: 1BR / 2BR / 3BR / 4BR | I50: 3 Affordable (Green) + 6 Market Rate (Blue)
A51: 43 | B51: Crossroadsof Lee Summit

Sheet Excel Sharepoints
A1: Building Name | B1: Excel Rent Roll - Sharepoint URL
A2: Boca Ciega | B2: Boca Ciega Rent Roll - 06-15-2026.xls | D2: — | E2: — | F2: 1736 | G2: 2376 | H2: — | I2: —
A3: Jefferson | B3: JeffersonRentRoll.xls | D3: — | E3: — | F3: 1020 | G3: 1150 | H3: — | I3: —
A4: Opa Locka | D4: — | E4: 1470 | F4: 1800 | G4: 2320 | H4: — | I4: —
A5: Macedonia | D5: — | E5: — | F5: 1451 | G5: 1613 | H5: — | I5: —
A6: Coral Village | B6: Coral Village - Rent Roll - 06-15-2026.xls | D6: — | E6: 1375 | F6: 1552 | G6: — | H6: — | I6: —
A7: Holiday | B7: Holiday Rent Roll 06-29-2026.xls | D7: — | E7: — | F7: 935 | G7: 1073 | H7: 1147
A8: Cumberland | B8: Cumberland Rent Roll 06-29-2026.xls | D8: — | E8: 1074 | F8: 1166 | G8: 1290 | H8: 1433 | I8: —
A9: Walnut Hill | B9: Walnut Hill Rent Roll 06-29-2026.xls | D9: — | E9: — | F9: 1346 | G9: 1465 | H9: — | I9: —
A10: River Pointe | B10: River Pointe Rent Roll 06-29-2026.xlsx | D10: — | F10: 1400 | G10: — | H10: — | I10: —
A11: Breckenridge | B11: Breckenridge Rent Roll 06-29-2026.xls | D11: — | E11: — | F11: 964 | G11: — | H11: 1221 | I11: —
A12: Lexington | B12: Lexington Rent Roll 06-29-2026.xls | D12: — | E12: — | F12: 964 | G12: — | H12: 1221 | I12: —
A13: Grace Townhomes | B13: Grace Townhomes Rent Roll 06-29-2026.xls | D13: — | E13: 1198 | F13: 1430 | G13: 1656 | H13: — | I13: —
A14: Grove Park | B14: Grove Park Rent Roll 06-29-2026.xls | D14: — | E14: 1210 | F14: 1450 | G14: 1700 | H14: — | I14: —
A15: La Promesa | B15: La Promesa Rent Roll 06-29-2026.xlsx | D15: — | E15: — | F15: 1402 | G15: 1679 | H15: — | I15: —
A16: New Wilmington Arms | B16: New Wilmington Arms Rent Roll 06-29-2026.xls | D16: — | E16: 1221 | F16: 1563 | G16: 1820 | H16: 2128 | I16: —
A17: Gates of Manhattan | B17: Gates of Manhattan Rent Roll 06-29-2026.xlsx | D17: — | E17: 1000 | F17: 1150 | G17: 1300 | H17: — | I17: —
A18: Ruby | B18: Ruby Diamond - Rent Roll 06-12-2026.xlsx | D18: — | E18: — | G18: 1223 | H18: 870 | I18: —
A19: Star | B19: Star - Rent Roll 06-12-2026.xlsx | D19: — | E19: — | F19: 894 | G19: 982 | H19: 1045 | I19: —
A20: Marrero | B20: Marrero - Rent Roll Detail 06-12-2026.xls | D20: — | E20: — | G20: 1401 | H20: 1563 | I20: —
A21: Arbor Crest | B21: Arbor Crest - Rent Roll - 06-15-2026.xls | D21: — | E21: 914 | F21: 1058 | G21: 1204 | H21: — | I21: —
A22: Windsor-Yorkshire | B22: Windsor - Thibodaux Rent Roll 06-29-2026.xls | C22: Yorkshire - Thibodaux Rent Roll 06-29-2026.xls | D22: — | E22: 777 | F22: 885 | G22: — | H22: 1140 | I22: —
A23: North Pointe | B23: North Pointe Rent Roll 06-29-2026.xls | D23: — | E23: — | F23: 575 | G23: 655 | H23: 695 | I23: —
A24: Bayou Pointe | B24: Bayou Pointe Rent Roll 06-29-2026.xls | D24: — | E24: — | F24: — | G24: 1053 | H24: 1152 | I24: —
A25: St. Charles | B25: St Charles Rent Roll 06-29-2026.xls | D25: — | E25: — | F25: 1154 | G25: 1484 | H25: — | I25: —
A26: Pelican Bay | B26: Pelican Bay Rent Roll 06-29-2026.xls | D26: — | E26: 874 | F26: 1039 | G26: 1194 | H26: 1321 | I26: —
A27: Howell Place | B27: Howell Place Rent Roll 06-29-2026.xls | D27: — | E27: 874 | F27: 1039 | G27: 1194 | H27: 1321 | I27: —
A28: Pirates Bend | B28: Pirates Bend Rent Roll 06-29-2026.xls | D28: — | E28: 874 | F28: 1039 | G28: 1194 | H28: 1321 | I28: —
A29: Anaheim Gardens | B29: Anaheim Gardens Rent Roll 06-29-2026.xls | D29: — | E29: 3374 | F29: 3979 | G29: 4973 | H29: — | I29: —
A30: Fairfax | B30: Fairfax - Rent Roll - 06-15-2026.xls | D30: — | E30: 2908 | F30: — | G30: — | H30: — | I30: —
A31: Urban | B31: Urban Rehab Rent Roll 06-29-2026.xls | D31: — | E31: — | F31: 1842 | G31: — | H31: — | I31: —
A32: Midtown | B32: Midtown Manor Rent Roll 06-29-2026.xls | D32: — | E32: 1612 | F32: — | G32: — | H32: — | I32: —
A33: Pacific Pointe | B33: Pacific Pointe Rent Roll 06-29-2026.xls | D33: — | E33: 1252 | F33: 1374 | G33: — | H33: — | I33: —
A34: Granite Ridge | B34: Granite Ridge Rent Roll 06-29-2026.xls | D34: — | E34: 1212 | F34: 1383 | G34: — | H34: — | I34: —
A35: Columbia | B35: Columbia Village Rent Roll 06-29-2026.xlsx | D35: — | E35: — | F35: 1364 | G35: 1577.5 | H35: 1731 | I35: —
A36: Forest View | B36: Forest View Rent Roll 06-29-2026.xlsx | D36: — | E36: 723.88 | F36: 855.17 | G36: — | H36: — | I36: —
A37: Oak Hills | B37: Oak Hills Rent Roll 06-29-2026.xlsx | D37: — | E37: — | F37: 1308 | G37: 1526.47 | H37: — | I37: —
A38: River Garden | B38: River Gardens Rent Roll 06-29-2026.xlsx | D38: — | E38: — | F38: 1140 | G38: 1317 | H38: 1470 | I38: 1784
A39: Silver Springs | B39: Silver Springs Rent Roll 06-29-2026.xls | D39: — | E39: 970 | F39: 1185 | G39: 1400 | H39: 1695 | I39: —
A40: Thomasville | B40: Thomasville Rent Roll 06-29-2026.xls | D40: — | E40: 946 | F40: 1054 | G40: 1328 | H40: 1425 | I40: —
A41: Crossroads of Lee Summit | B41: Crossroads Rent Roll 06-29-2026.xls | D41: — | E41: — | F41: 1388 | G41: 1592 | H41: — | I41: —

Sheet Current Rents
A8: As of June 2026 | Enter rents here — values flow automatically to each building sheet | K8: Property (Sheet Name) | L8: Bed Type | M8: Current Rent | O8: Property (Sheet Name) | P8: Bed Type | Q8: Current Rent | S8: Property (Sheet Name) | T8: Bed Type | U8: Current Rent
A9: As of June 2026 | All values are live formula links — update rent on the building sheet and it updates here automatically | K9: Same information that is in the table to the left.
A10: ID | B10: Property Name | C10: Studio (0BD) | D10: 1 Bed (1BD) | E10: 2 Bed (2BD) | F10: 3 Bed (3BD) | G10: 4 Bed (4BD) | H10: 5 Bed (5BD) | I10: Notes | K10: 21 - Boca Ciega | L10: 2BD | M10: 1736 | O10: 42 - Ruby | P10: 3BD | Q10: 1223 | S10: 25 - Columbia | T10: 2BD | U10: 1364
A11: 21 | B11: Boca Ciega | C11: — | D11: — | E11: 1736 | F11: 2376 | G11: — | H11: — | K11: 21 - Boca Ciega | L11: 3BD | M11: 2376 | O11: 42 - Ruby | P11: 4BD | Q11: 870 | S11: 25 - Columbia | T11: 3BD | U11: 1577.5
A12: 13 | B12: Jefferson | C12: — | D12: — | E12: 1020 | F12: 1150 | G12: — | H12: — | K12: 13 - Jefferson | L12: 2BD | M12: 1020 | O12: 39 - Star | P12: 2BD | Q12: 894 | S12: 25 - Columbia | T12: 4BD | U12: 1731
A13: 18 | B13: Opa Locka | C13: — | D13: 1470 | E13: 1800 | F13: 2320 | G13: — | H13: — | K13: 13 - Jefferson | L13: 3BD | M13: 1150 | O13: 39 - Star | P13: 3BD | Q13: 982 | S13: 26 - Forest View | T13: 1BD | U13: 723.88
A14: 14 | B14: Macedonia | C14: — | D14: — | E14: 1451 | F14: 1613 | G14: — | H14: — | K14: 18 - Opa Locka (135th Apartments) | L14: 1BD | M14: 1470 | O14: 39 - Star | P14: 4BD | Q14: 1045 | S14: 26 - Forest View | T14: 2BD | U14: 855.17
A15: 48 | B15: Coral Village | C15: — | D15: 1375 | E15: 1552 | F15: — | G15: — | H15: — | K15: 19 - Opa Locka (135th Apartments) | L15: 2BD | M15: 1800 | O15: 40 - Marrero | P15: 3BD | Q15: 1401 | S15: 24 - Oak Hills | T15: 2BD | U15: 1308
A16: 15 | B16: Holiday | C16: — | D16: — | E16: 935 | F16: 1073 | G16: 1147 | K16: 20 - Opa Locka (135th Apartments) | L16: 3BD | M16: 2320 | O16: 40 - Marrero | P16: 4BD | Q16: 1563 | S16: 24 - Oak Hills | T16: 3BD | U16: 1526.47
A17: 16 | B17: Cumberland | C17: — | D17: 1074 | E17: 1166 | F17: 1290 | G17: 1433 | H17: — | K17: 14 - Macedonia | L17: 2BD | M17: 1451 | O17: 37 - Arbor Crest | P17: 1BD | Q17: 914 | S17: 58 - River Garden | T17: 2BD | U17: 1140
A18: 59 | B18: Walnut Hill | C18: — | D18: — | E18: 1346 | F18: 1465 | G18: — | H18: — | K18: 14 - Macedonia | L18: 3BD | M18: 1613 | O18: 37 - Arbor Crest | P18: 2BD | Q18: 1058 | S18: 58 - River Garden | T18: 3BD | U18: 1317
A19: 29 | B19: River Pointe | C19: — | E19: 1400 | F19: — | G19: — | H19: — | K19: 48 - Coral Village | L19: 1BD | M19: 1375 | O19: 37 - Arbor Crest | P19: 3BD | Q19: 1204 | S19: 58 - River Garden | T19: 4BD | U19: 1470
A20: 12 | B20: Breckenridge | C20: — | D20: — | E20: 964 | F20: — | G20: 1221 | H20: — | K20: 48 - Coral Village | L20: 2BD | M20: 1552 | O20: 33 - Windsor-Yorkshire | P20: 1BD | Q20: 777 | S20: 58 - River Garden | T20: 5BD | U20: 1784
A21: 38 | B21: Lexington | C21: — | D21: — | E21: 964 | F21: — | G21: 1221 | H21: — | K21: 15 - Holiday | L21: 2BD | M21: 935 | O21: 33 - Windsor-Yorkshire | P21: 2BD | Q21: 885 | S21: 36 - Silver Springs | T21: 1BD | U21: 970
A22: 23 | B22: Grace Townhomes | C22: — | D22: 1198 | E22: 1430 | F22: 1656 | G22: — | H22: — | K22: 15 - Holiday | L22: 3BD | M22: 1073 | O22: 33 - Windsor-Yorkshire | P22: 4BD | Q22: 1140 | S22: 36 - Silver Springs | T22: 2BD | U22: 1185
A23: 46 | B23: Grove Park | C23: — | D23: 1210 | E23: 1450 | F23: 1700 | G23: — | H23: — | K23: 15 - Holiday | L23: 4BD | M23: 1147 | O23: 50 - North Pointe | P23: 2BD | Q23: 575 | S23: 36 - Silver Springs | T23: 3BD | U23: 1400
A24: 60 | B24: La Promesa | C24: — | D24: — | E24: 1402 | F24: 1679 | G24: — | H24: — | K24: 16 - Cumberland | L24: 1BD | M24: 1074 | O24: 50 - North Pointe | P24: 3BD | Q24: 655 | S24: 36 - Silver Springs | T24: 4BD | U24: 1695
A25: 3 | B25: Wilmington | C25: — | D25: 1221 | E25: 1563 | F25: 1820 | G25: 2128 | H25: — | K25: 16 - Cumberland | L25: 2BD | M25: 1166 | O25: 50 - North Pointe | P25: 4BD | Q25: 695 | S25: 36 - Silver Springs | T25: 5BD | U25: 970
A26: 19 | B26: Gates | C26: — | D26: 1000 | E26: 1150 | F26: 1300 | G26: — | H26: — | K26: 16 - Cumberland | L26: 3BD | M26: 1290 | O26: 53 - Bayou Pointe | P26: 3BD | Q26: 1053 | S26: 44 - Thomasville | T26: 1BD | U26: 946
A27: 42 | B27: Ruby | C27: — | D27: — | F27: 1223 | G27: 870 | H27: — | K27: 16 - Cumberland | L27: 4BD | M27: 1433 | O27: 53 - Bayou Pointe | P27: 4BD | Q27: 1152 | S27: 44 - Thomasville | T27: 2BD | U27: 1054
A28: 39 | B28: Star | C28: — | D28: — | E28: 894 | F28: 982 | G28: 1045 | H28: — | K28: 59 - Walnut Hill | L28: 2BD | M28: 1346 | O28: 41 - St. Charles | P28: 2BD | Q28: 1154 | S28: 44 - Thomasville | T28: 3BD | U28: 1328
A29: 20 | B29: See Windsor/Yorkshire | K29: 59 - Walnut Hill | L29: 3BD | M29: 1465 | O29: 41 - St. Charles | P29: 3BD | Q29: 1484 | S29: 44 - Thomasville | T29: 4BD | U29: 1425
A30: 40 | B30: Marrero | C30: — | D30: — | F30: 1401 | G30: 1563 | H30: — | K30: 29 - River Pointe | L30: 2BD | M30: 1400 | O30: 55 - Pelican Bay | P30: 1BD | Q30: 874 | S30: 44 - Thomasville | T30: 1BD | U30: 946
A31: 37 | B31: Arbor Crest | C31: — | D31: 914 | E31: 1058 | F31: 1204 | G31: — | H31: — | K31: 29 - River Pointe | L31: 3BD | M31: 1600 | O31: 55 - Pelican Bay | P31: 2BD | Q31: 1039 | S31: 44 - Thomasville | T31: 2BD | U31: 1054
A32: 33 | B32: Windsor-Yorkshire | C32: — | D32: 777 | E32: 885 | F32: — | G32: 1140 | H32: — | K32: 29 - River Pointe | L32: 4BD | M32: 1700 | O32: 55 - Pelican Bay | P32: 3BD | Q32: 1194 | S32: 44 - Thomasville | T32: 3BD | U32: 1328
A33: 50 | B33: North Pointe | C33: — | D33: — | E33: 575 | F33: 655 | G33: 695 | H33: — | K33: 12 - Breckenridge | L33: 2BD | M33: 964 | O33: 55 - Pelican Bay | P33: 4BD | Q33: 1321 | S33: 63 - Crossroads | T33: 2BD | U33: 1388
A34: 53 | B34: Bayou Pointe | C34: — | D34: — | E34: — | F34: 1053 | G34: 1152 | H34: — | K34: 12 - Breckenridge | L34: 4BD | M34: 1221 | O34: 56 - Howell Place | P34: 1BD | Q34: 874 | S34: 63 - Crossroads | T34: 3BD | U34: 1592
A35: 41 | B35: St. Charles | C35: — | D35: — | E35: 1154 | F35: 1484 | G35: — | H35: — | K35: 38 - Lexington | L35: 2BD | M35: 964 | O35: 56 - Howell Place | P35: 2BD
A36: 55 | B36: Pelican Bay | C36: — | D36: 874 | E36: 1039 | F36: 1194 | G36: 1321 | H36: — | K36: 38 - Lexington | L36: 4BD | M36: 1221 | O36: 56 - Howell Place | P36: 3BD
A37: 56 | B37: Howell Place | C37: — | D37: 874 | E37: 1039 | F37: 1194 | G37: 1321 | H37: — | K37: 23 - Grace Townhomes | L37: 1BD | M37: 1198 | O37: 56 - Howell Place | P37: 4BD
A38: 57 | B38: Pirates Bend | C38: — | D38: 874 | E38: 1039 | F38: 1194 | G38: 1321 | H38: — | K38: 23 - Grace Townhomes | L38: 2BD | M38: 1430 | O38: 57 - Pirates Bend | P38: 1BD
A39: 6 | B39: Anaheim Gardens | C39: — | D39: 3374 | E39: 3979 | F39: 4973 | G39: — | H39: — | K39: 23 - Grace Townhomes | L39: 3BD | M39: 1656 | O39: 57 - Pirates Bend | P39: 2BD
A40: 11 | B40: Fairfax | C40: — | D40: 2908 | E40: — | F40: — | G40: — | H40: — | K40: 46 - Grove Park | L40: 1BD | M40: 1210 | O40: 57 - Pirates Bend | P40: 3BD
A41: 31 | B41: Urban | C41: — | D41: — | E41: 1842 | F41: — | G41: — | H41: — | K41: 46 - Grove Park | L41: 2BD | M41: 1450 | O41: 57 - Pirates Bend | P41: 4BD
A42: 2 | B42: Midtown | C42: — | D42: 1612 | E42: — | F42: — | G42: — | H42: — | K42: 46 - Grove Park | L42: 3BD | M42: 1700 | O42: 6 - Anaheim Gardens | P42: 1BD
A43: 34 | B43: Pacific Pointe | C43: — | D43: 1252 | E43: 1374 | F43: — | G43: — | H43: — | K43: 60 - La Promesa | L43: 2BD | M43: 1402 | O43: 6 - Anaheim Gardens | P43: 2BD
A44: 28 | B44: Granite Ridge | C44: — | D44: 1212 | E44: 1383 | F44: — | G44: — | H44: — | K44: 60 - La Promesa | L44: 3BD | M44: 1679 | O44: 6 - Anaheim Gardens | P44: 3BD
A45: 25 | B45: Columbia | C45: — | D45: — | E45: 1364 | F45: 1577.5 | G45: 1731 | H45: — | K45: 3 - Wilmington | L45: 1BD | M45: 1221 | O45: 11 - Fairfax | P45: 1BD
A46: 26 | B46: Forest View | C46: — | D46: 723.88 | E46: 855.17 | F46: — | G46: — | H46: — | K46: 3 - Wilmington | L46: 2BD | M46: 1563 | O46: 31 - Urban | P46: 0BD
A47: 24 | B47: Oak Hills | C47: — | D47: — | E47: 1308 | F47: 1526.47 | G47: — | H47: — | K47: 3 - Wilmington | L47: 3BD | M47: 1820 | O47: 31 - Urban | P47: 2BD
A48: 58 | B48: River Garden | C48: — | D48: — | E48: 1140 | F48: 1317 | G48: 1470 | H48: 1784 | K48: 3 - Wilmington | L48: 4BD | M48: 2128 | O48: 2 - Midtown | P48: 1BD
A49: 36 | B49: Silver Springs | C49: — | D49: 970 | E49: 1185 | F49: 1400 | G49: 1695 | H49: — | K49: 19 - Gates | L49: 1BD | M49: 1000 | O49: 34 - Pacific Pointe | P49: 1BD
A50: 44 | B50: Thomasville | C50: — | D50: 946 | E50: 1054 | F50: 1328 | G50: 1425 | H50: — | K50: 19 - Gates | L50: 2BD | M50: 1150 | O50: 34 - Pacific Pointe | P50: 2BD
A51: 63 | B51: Crossroads | C51: — | D51: — | E51: 1388 | F51: 1592 | G51: — | H51: — | K51: 19 - Gates | L51: 3BD | M51: 1300 | O51: 28 - Granite Ridge | P51: 1BD
A52: Total: 42 properties | All values are live formula links — change rent on building sheet to update here | M52: 1223 | O52: 28 - Granite Ridge | P52: 2BD

Sheet 21 - Boca Ciega
A2: RENT COMPARABLES ANALYSIS — BOCA CIEGA | ST. PETERSBURG, FL 33711 | Z2: 21 - Boca Ciega | 109 Units | LIHTC / Section 8 | 2BD & 3BD
A3: 3401 37th Street South, St. Petersburg, FL 33711 | Pinellas County | Tampa-St. Petersburg MSA | FY2026 FMR: 2BD $2,170 / 3BD $2,780
A4: Data as of April 30, 2026 | Sources: Apartments.com, HUD FMR Database, HUD Multifamily Assisted Housing, Apartment Corp Records
A5: COLUMN GUIDE — Income-restricted comps show AMI-based maximum allowable rents at 50% and 60% AMI tiers. Market-rate comps show what unrestricted renters pay in the same market. LOW = 50% AMI max rent. MID = 60% AMI max rent. FMR = HUD FY2026 Fair Market Rent (40th percentile). ACTUAL = Verified advertised rent from Apartments.com (highlighted in orange). 'Not Listed' = property does not publicly advertise rents. AMI source: HUD FY2025 MTSP Income Limits, effective April 1, 2025.
A6: Rank | B6: Type | C6: Property Name | E6: Address | F6: City | G6: St | H6: ZIP | I6: Distance | J6: 2BD 50% AMI | K6: 2BD 60% AMI | L6: 2BD FMR | M6: 2BD - Actual | N6: 3BD 50% AMI | O6: 3BD 60% AMI | P6: 3BD FMR | Q6: 3BD - Actual | R6: Units | S6: Yr Built | T6: Yr Diff | U6: Utils Incl. | V6: Pet Friendly | W6: Gated | X6: Pool | Y6: W/D In-Unit | Z6: Competition Level | AA6: Notes / Why Competitive | AB6: Data Source
A7: ★ | B7: SUBJECT | C7: Boca Ciega (SUBJECT) | E7: 3401 37th Street South | F7: St. Petersburg | G7: FL | H7: 33711 | I7: 0.0 mi | J7: $3,912 | K7: $4,695 | L7: $2,170 | M7: 1736 | N7: $4,345 | O7: $5,215 | P7: $2,780 | Q7: 2376 | R7: 109 | S7: 2015 | T7: 0 | U7: Yes | V7: No | W7: No | X7: No | Y7: No | Z7: SUBJECT | AA7: 109 units | Layered HUD/LIHTC. Year built: 1974. Subject property. | AB7: Apartment Corp Records
A8: 1 | B8: AFFORDABLE | C8: Clearwater Gardens Apartments | E8: 1501 N Greenwood Ave | F8: Clearwater | G8: FL | H8: 33755 | I8: 14.2 mi | J8: $3,912 | K8: $4,695 | L8: $2,170 | M8: Not Listed | N8: $4,345 | O8: $5,215 | P8: $2,780 | Q8: Not Listed | R8: 100 | S8: 1974 | T8: 0 | U8: Yes | V8: No | W8: No | X8: No | Y8: No | Z8: HIGH | AA8: Section 8/HUD, 1974 vintage, 100 units, 14.2 mi. | AB8: HUD Multifamily Assisted Housing
A9: 2 | B9: AFFORDABLE | C9: Pinellas Park Manor | E9: 6200 Park Blvd | F9: Pinellas Park | G9: FL | H9: 33781 | I9: 7.1 mi | J9: $3,912 | K9: $4,695 | L9: $2,170 | M9: Not Listed | N9: $4,345 | O9: $5,215 | P9: $2,780 | Q9: Not Listed | R9: 112 | S9: 1975 | T9: 1 | U9: Yes | V9: No | W9: No | X9: No | Y9: No | Z9: HIGH | AA9: Section 8/HUD, 1975 vintage, 112 units, 7.1 mi. | AB9: HUD Multifamily Assisted Housing
A10: 3 | B10: AFFORDABLE | C10: Tarpon Springs Housing Authority | E10: 200 S Walton Ave | F10: Tarpon Springs | G10: FL | H10: 34689 | I10: 22.5 mi | J10: $3,912 | K10: $4,695 | L10: $2,170 | M10: Not Listed | N10: $4,345 | O10: $5,215 | P10: $2,780 | Q10: Not Listed | R10: 96 | S10: 1972 | T10: 2 | U10: Yes | V10: No | W10: No | X10: No | Y10: No | Z10: MODERATE-HIGH | AA10: Public Housing/HUD, 1972 vintage, 96 units, 22.5 mi. | AB10: Tarpon Springs Housing Authority
A11: 1 | B11: MARKET RATE | C11: Addison at Bayfront | D11: COMPETITION | E11: 2800 1st Ave S | F11: St. Petersburg | G11: FL | H11: 33712 | I11: 1.2 mi | J11: N/A | K11: N/A | L11: $2,170 | M11: 2446 | N11: N/A | O11: N/A | P11: $2,780 | Q11: 2947 | R11: 266 | S11: 2020 | T11: 5 | U11: No | V11: Yes | W11: No | X11: Yes | Y11: Yes | Z11: HIGH | AA11: No income restrictions, 2020 vintage, 266 units, 1.2 mi. 2BD $2,446 / 3BD $2,947. | AB11: apartments.com/addison-at-bayfront-saint-petersburg-fl/
A12: 2 | B12: MARKET RATE | C12: Marina Walk at One Waterfront | E12: 101 1st Ave S | F12: St. Petersburg | G12: FL | H12: 33701 | I12: 2.8 mi | J12: N/A | K12: N/A | L12: $2,170 | M12: 2600 | N12: N/A | O12: N/A | P12: $2,780 | Q12: N/A | R12: 163 | S12: 2023 | T12: 8 | U12: No | V12: Yes | W12: Yes | X12: Yes | Y12: Yes | Z12: HIGH | AA12: No income restrictions, 2023 vintage, 163 units, 2.8 mi. 2BD $2,600. | AB12: apartments.com/marina-walk-at-one-waterfront-saint-petersburg-fl/
A13: 3 | B13: MARKET RATE | C13: Flagler Pointe | E13: 3001 Gandy Blvd N | F13: St. Petersburg | G13: FL | H13: 33702 | I13: 1.9 mi | J13: N/A | K13: N/A | L13: $2,170 | M13: 1890 | N13: N/A | O13: N/A | P13: $2,780 | Q13: 2150 | R13: N/A | S13: 1974 | T13: 0 | U13: No | V13: Yes | W13: No | X13: Yes | Y13: No | Z13: HIGH | AA13: No income restrictions, 1974 vintage, 1.9 mi. 2BD $1,890 / 3BD $2,150. | AB13: apartments.com/flagler-pointe-apartments-saint-petersburg-fl/
A14: 4 | B14: MARKET RATE | C14: Sur Club | E14: 3301 32nd Ave S | F14: St. Petersburg | G14: FL | H14: 33712 | I14: 1.5 mi | J14: N/A | K14: N/A | L14: $2,170 | M14: 2250 | N14: N/A | O14: N/A | P14: $2,780 | Q14: N/A | R14: 296 | S14: 2021 | T14: 47 | U14: No | V14: Yes | W14: No | X14: Yes | Y14: Yes | Z14: HIGH | AA14: No income restrictions, 2021 vintage, 296 units, 1.5 mi. 2BD $2,250. | AB14: apartments.com/sur-club-saint-petersburg-fl/
A15: 5 | B15: MARKET RATE | C15: Lake Maggiore | E15: 825 32nd Ave S | F15: St. Petersburg | G15: FL | H15: 33705 | I15: 2.1 mi | J15: N/A | K15: N/A | L15: $2,170 | M15: 2520 | N15: N/A | O15: N/A | P15: $2,780 | Q15: 3840 | R15: 330 | S15: 2023 | T15: 8 | U15: No | V15: Yes | W15: Yes | X15: Yes | Y15: Yes | Z15: HIGH | AA15: No income restrictions, 2023 vintage, 330 units, 2.1 mi. 2BD $2,520 / 3BD $3,840. | AB15: apartments.com/lake-maggiore-saint-petersburg-fl/
A16: 6 | B16: MARKET RATE | C16: The Courtney at Bay Pines | E16: 4652 Miramar Dr | F16: St. Petersburg | G16: FL | H16: 33708 | I16: 5.2 mi | J16: N/A | K16: N/A | L16: $2,170 | M16: 2310 | N16: N/A | O16: N/A | P16: $2,780 | Q16: 2755 | R16: 312 | S16: 2013 | T16: 2 | U16: No | V16: Yes | W16: Yes | X16: Yes | Y16: Yes | Z16: HIGH | AA16: No income restrictions, 2013 vintage, 312 units, 5.2 mi. 2BD $2,310 / 3BD $2,755. | AB16: apartments.com/the-courtney-at-bay-pines-saint-petersburg-fl/
A17: — | B17: BENCHMARK | C17: FY2026 FMR — Tampa-St. Petersburg MSA | E17: N/A | F17: St. Petersburg | G17: FL | H17: N/A | I17: N/A | J17: $2,170 | K17: $2,170 | L17: $2,170 | M17: N/A | N17: $2,780 | O17: $2,780 | P17: $2,780 | Q17: N/A | R17: N/A | S17: N/A | T17: N/A | U17: N/A | V17: N/A | W17: N/A | X17: N/A | Y17: N/A | Z17: BENCHMARK | AA17: HUD FMR for Tampa-St. Petersburg MSA, FY2026. 40th percentile of gross rents. | AB17: HUD FMR Database (huduser.gov)
A18: — | B18: BENCHMARK | C18: Metro Market Avg — St. Petersburg (Apr 2026) | E18: N/A | F18: St. Petersburg | G18: FL | H18: N/A | I18: N/A | J18: $2,336 | K18: $2,336 | L18: $2,336 | M18: $2,336 | N18: $2,923 | O18: $2,923 | P18: $2,923 | Q18: $2,923 | R18: N/A | S18: N/A | T18: N/A | U18: N/A | V18: N/A | W18: N/A | X18: N/A | Y18: N/A | Z18: BENCHMARK | AA18: Live Market Average from 6 market-rate comps, Apr 30, 2026. 2BD avg $2,336 / 3BD avg $2,923. | AB18: Apartments.com live data, Apr 30, 2026
A20: COLOR KEY: GREEN = Subject Property | TEAL = Affordable/Income-Restricted Comps | BLUE = Market Rate Comps | ORANGE = Actual Advertised Rent | YELLOW = Market Average Benchmark
A22: CURRENT RENT vs. MARKET AVERAGE
A23: Market Average = Avg of Actual Advertised Rents from 6 Market-Rate Comps (Apartments.com)
B24: Current Rents | C24: Market Avg | E24: Difference
A25: 2BD | B25: 1736 | C25: 2336 | E25: =B25-C25 -> -600 | F25: =IF(E25<-75,"LOOK INTO INCREASING THE RENT!","") -> LOOK INTO INCREASING THE RENT!
A26: 3BD | B26: 2376 | C26: 2923 | E26: =B26-C26 -> -547 | F26: =IF(E26<-75,"LOOK INTO INCREASING THE RENT!","") -> LOOK INTO INCREASING THE RENT!

Sheet 13 - Jefferson
A2: RENT COMPARABLES ANALYSIS — JEFFERSON ARMS | MONTICELLO, FL 32344 | Z2: 13 - Jefferson | 60 Units | LIHTC / Section 8 | 2BD & 3BD
A3: 1001 W Washington St, Monticello, FL 32344 | Jefferson County
A4: Data as of June 16, 2026 | Sources: Apartments.com, HUD FMR Database, Apartment Corp Records
A5: COLUMN GUIDE — Income-restricted comps show AMI-based maximum rents (50%/60% AMI) alongside FMR. Market-rate comps show N/A for AMI columns. Actual = advertised/in-place rent. Competition Level: HIGH = direct competition; MODERATE-HIGH = partial overlap.
A6: Rank | B6: Type | C6: Property Name | E6: Address | F6: City | G6: St | H6: ZIP | I6: Distance | J6: 2BD 50% AMI | K6: 2BD 60% AMI | L6: 2BD FMR | M6: 2BD - Actual | N6: 3BD 50% AMI | O6: 3BD 60% AMI | P6: 3BD FMR | Q6: 3BD - Actual | R6: Units | S6: Yr Built | T6: Yr Diff | U6: Utils Incl. | V6: Pet Friendly | W6: Gated | X6: Pool | Y6: W/D In-Unit | Z6: Competition Level | AA6: Notes / Why Competitive | AB6: Data Source
A7: ★ | B7: SUBJECT | C7: Jefferson (SUBJECT) | E7: 1001 W Washington St | F7: Monticello | G7: FL | H7: 32344 | I7: 0.0 mi | J7: $2,420 | K7: $2,904 | L7: $1,210 | M7: ='Current Rents'!E12 -> 1020 | N7: $2,797 | O7: $3,357 | P7: $1,540 | Q7: ='Current Rents'!F12 -> 1150 | R7: 60 | S7: 1971 | U7: Yes | V7: No | W7: No | X7: No | Y7: No | Z7: SUBJECT | AA7: 60 units | LIHTC/Section 8. Year built: 1971. Subject property. | AB7: Apartment Corp Records
A8: 1 | B8: AFFORDABLE | C8: Monticello Manor | E8: 500 S Jefferson St | F8: Monticello | G8: FL | H8: 32344 | I8: 0.5 mi | J8: $2,420 | K8: $2,904 | L8: $1,210 | M8: Not Listed | N8: $2,797 | O8: $3,357 | P8: $1,540 | Q8: Not Listed | R8: 40 | S8: 1972 | T8: 1 | U8: Yes | V8: No | W8: No | X8: No | Y8: No | Z8: HIGH | AA8: Section 8/HUD, 1972 vintage, 40 units, 0.5 mi. | AB8: HUD Multifamily Assisted Housing
A9: 2 | B9: AFFORDABLE | C9: Waukeenah Manor | E9: US-19, Waukeenah | F9: Waukeenah | G9: FL | H9: 32344 | I9: 8.0 mi | J9: $2,420 | K9: $2,904 | L9: $1,210 | M9: Not Listed | N9: $2,797 | O9: $3,357 | P9: $1,540 | Q9: Not Listed | R9: 24 | S9: 1974 | T9: 3 | U9: Yes | V9: No | W9: No | X9: No | Y9: No | Z9: HIGH | AA9: Section 8/HUD, 1974 vintage, 24 units, 8.0 mi. | AB9: HUD Multifamily Assisted Housing
A10: 3 | B10: AFFORDABLE | C10: Greenville Manor | E10: Hwy 221, Greenville | F10: Greenville | G10: FL | H10: 32331 | I10: 15.0 mi | J10: $2,420 | K10: $2,904 | L10: $1,210 | M10: Not Listed | N10: $2,797 | O10: $3,357 | P10: $1,540 | Q10: Not Listed | R10: 20 | S10: 1975 | T10: 4 | U10: Yes | V10: No | W10: No | X10: No | Y10: No | Z10: MODERATE-HIGH | AA10: Section 8/HUD, 1975 vintage, 20 units, 15.0 mi. | AB10: HUD Multifamily Assisted Housing
A11: 1 | B11: MARKET RATE | C11: Magnolia Terrace | D11: COMPETITION | E11: 1200 N Jefferson St | F11: Monticello | G11: FL | H11: 32344 | I11: 0.3 mi | J11: N/A | K11: N/A | L11: $1,210 | M11: 1250 | N11: N/A | O11: N/A | P11: $1,540 | Q11: 1450 | R11: 48 | S11: 1985 | T11: 14 | U11: No | V11: Yes | W11: No | X11: Yes | Y11: No | Z11: HIGH | AA11: No income restrictions, 1985 vintage, 48 units, 0.3 mi. 2BD avg $1,250/mo. | AB11: apartments.com/magnolia-terrace-monticello-fl/
A12: 2 | B12: MARKET RATE | C12: Jefferson Commons | E12: 450 E Pearl St | F12: Monticello | G12: FL | H12: 32344 | I12: 0.5 mi | J12: N/A | K12: N/A | L12: $1,210 | M12: 1195 | N12: N/A | O12: N/A | P12: $1,540 | Q12: 1395 | R12: 36 | S12: 1978 | T12: 7 | U12: No | V12: Yes | W12: No | X12: No | Y12: No | Z12: HIGH | AA12: No income restrictions, 1978 vintage, 36 units, 0.5 mi. 2BD avg $1,195/mo. | AB12: apartments.com/jefferson-commons-monticello-fl/
A13: 3 | B13: MARKET RATE | C13: Monticello Village Apts | E13: 300 S Cherry St | F13: Monticello | G13: FL | H13: 32344 | I13: 0.4 mi | J13: N/A | K13: N/A | L13: $1,210 | M13: 1100 | N13: N/A | O13: N/A | P13: $1,540 | Q13: 1350 | R13: 24 | S13: 1970 | U13: No | V13: No | W13: No | X13: No | Y13: No | Z13: HIGH | AA13: No income restrictions, 1970 vintage, 24 units, 0.4 mi. 2BD avg $1,100/mo. | AB13: apartments.com/monticello-village-fl/
A14: 4 | B14: MARKET RATE | C14: Tallahassee Crossing | E14: 4200 Apalachee Pkwy | F14: Tallahassee | G14: FL | H14: 32311 | I14: 26.0 mi | J14: N/A | K14: N/A | L14: $1,210 | M14: 1399 | N14: N/A | O14: N/A | P14: $1,540 | Q14: 1599 | R14: 312 | S14: 2005 | T14: 34 | U14: No | V14: Yes | W14: Yes | X14: Yes | Y14: Yes | Z14: HIGH | AA14: No income restrictions, 2005 vintage, 312 units, 26.0 mi. 2BD avg $1,399/mo. | AB14: apartments.com/tallahassee-crossing-fl/
A15: 5 | B15: MARKET RATE | C15: Arbor Station Apartments | E15: 4105 Arbor Hill Ln | F15: Tallahassee | G15: FL | H15: 32312 | I15: 28.0 mi | J15: N/A | K15: N/A | L15: $1,210 | M15: 1539 | N15: N/A | O15: N/A | P15: $1,540 | Q15: 1659 | R15: 252 | S15: 1990 | T15: 19 | U15: No | V15: Yes | W15: No | X15: Yes | Y15: Yes | Z15: HIGH | AA15: No income restrictions, 1990 vintage, 252 units, 28.0 mi. 2BD avg $1,539/mo. | AB15: apartments.com/arbor-station-apartments-tallahassee-fl/
A16: 6 | B16: MARKET RATE | C16: Capital Place at Southwood | E16: 2300 Bluff Oak Way | F16: Tallahassee | G16: FL | H16: 32311 | I16: 30.0 mi | J16: N/A | K16: N/A | L16: $1,210 | M16: N/A | N16: N/A | O16: N/A | P16: $1,540 | Q16: 1675 | R16: 288 | S16: 2013 | T16: 42 | U16: No | V16: Yes | W16: Yes | X16: Yes | Y16: Yes | Z16: HIGH | AA16: No income restrictions, 2013 vintage, 288 units, 30.0 mi. 3BD avg $1,675/mo. | AB16: apartments.com/capital-place-at-southwood-tallahassee-fl/
A17: — | B17: BENCHMARK | C17: FY2026 FMR — Jefferson County, FL | E17: N/A | F17: Monticello | G17: FL | H17: N/A | I17: N/A | J17: $1,210 | K17: $1,210 | L17: $1,210 | M17: N/A | N17: $1,540 | O17: $1,540 | P17: $1,540 | Q17: N/A | R17: N/A | S17: N/A | T17: N/A | U17: N/A | V17: N/A | W17: N/A | X17: N/A | Y17: N/A | Z17: BENCHMARK | AA17: HUD FMR for Jefferson County, FL, FY2026. 40th percentile rent. | AB17: HUD FMR Database (huduser.gov)
A18: — | B18: BENCHMARK | C18: Metro Market Avg — Monticello/Tallahassee (Apr 2026) | E18: N/A | F18: Monticello | G18: FL | H18: N/A | I18: N/A | J18: $1,380 | K18: $1,380 | L18: $1,380 | M18: $1,380 | N18: $1,507 | O18: $1,507 | P18: $1,507 | Q18: $1,507 | R18: N/A | S18: N/A | T18: N/A | U18: N/A | V18: N/A | W18: N/A | X18: N/A | Y18: N/A | Z18: BENCHMARK | AA18: Live Market Average from 6 market-rate comps, Apr 30, 2026. 2BD avg $1,380; 3BD avg $1,507. | AB18: Apartments.com live data, Apr 30, 2026
A20: COLOR KEY: GREEN = Subject Property | TEAL = Affordable/Income-Restricted Comp | BLUE = Market-Rate Comp | LIGHT BLUE = FMR Benchmark | YELLOW = Market Average | ORANGE = Actual Rent
A22: CURRENT RENT vs. MARKET AVERAGE
A23: Market Average = Avg of Actual Advertised Rents from 6 Market-Rate Comps (Apartments.com)
B24: Current Rents | C24: Market Avg | E24: Difference
A25: 2BD | B25: ='Current Rents'!E12 -> 1020 | C25: 1380 | E25: =B25-C25 -> -360 | F25: =IF(E25<-75,"LOOK INTO INCREASING THE RENT!","") -> LOOK INTO INCREASING THE RENT!
A26: 3BD | B26: ='Current Rents'!F12 -> 1150 | C26: 1507 | E26: =B26-C26 -> -357 | F26: =IF(E26<-75,"LOOK INTO INCREASING THE RENT!","") -> LOOK INTO INCREASING THE RENT!

Sheet 18 - Opa Locka
A2: RENT COMPARABLES ANALYSIS — OPA LOCKA 135TH ST | OPA LOCKA, FL 33054 | AD2: 18 - Opa Locka | 65 Units | LIHTC / Section 8 | 1BD, 2BD & 3BD
A3: 2860 NW 135th Street, Opa Locka, FL 33054 | Miami-Dade County
A4: Data as of June 16, 2026 | Sources: Apartments.com, HUD FMR Database, Apartment Corp Records
A5: COLUMN GUIDE — Income-restricted comps show AMI-based maximum rents (50%/60% AMI) alongside FMR. Market-rate comps show N/A for AMI columns. Actual = advertised/in-place rent. Competition Level: HIGH = direct competition; MODERATE-HIGH = partial overlap.
A6: Rank | B6: Type | C6: Property Name | E6: Address | F6: City | G6: St | H6: ZIP | I6: Distance | J6: 1BD 50% AMI | K6: 1BD 60% AMI | L6: 1BD FMR | M6: 1BD - Actual | N6: 2BD 50% AMI | O6: 2BD 60% AMI | P6: 2BD FMR | Q6: 2BD - Actual | R6: 3BD 50% AMI | S6: 3BD 60% AMI | T6: 3BD FMR | U6: 3BD - Actual | V6: Units | W6: Yr Built | X6: Yr Diff | Y6: Utils Incl. | Z6: Pet Friendly | AA6: Gated | AB6: Pool | AC6: W/D In-Unit | AD6: Competition Level | AE6: Notes / Why Competitive | AF6: Data Source
A7: ★ | B7: SUBJECT | C7: Opa Locka 135th St (SUBJECT) | E7: 2860 NW 135th Street | F7: Opa Locka | G7: FL | H7: 33054 | I7: 0.0 mi | J7: $3,872 | K7: $4,647 | L7: $1,736 | M7: ='Current Rents'!D13 -> 1470 | N7: $4,645 | O7: $5,575 | P7: $2,376 | Q7: ='Current Rents'!E13 -> 1800 | R7: $5,162 | S7: $6,195 | T7: $3,044 | U7: ='Current Rents'!F13 -> 2320 | V7: 65 | W7: 1968 | X7: 0 | Y7: Yes | Z7: No | AA7: No | AB7: No | AC7: No | AD7: SUBJECT | AE7: 65 units | LIHTC/Section 8. Year built: 1968. Subject property. | AF7: Apartment Corp Records
A8: 1 | B8: AFFORDABLE | C8: Liberty City Manor | E8: 6200 NW 7th Ave | F8: Miami | G8: FL | H8: 33150 | I8: 8.5 mi | J8: $3,872 | K8: $4,647 | L8: $1,736 | M8: Not Listed | N8: $4,645 | O8: $5,575 | P8: $2,376 | Q8: Not Listed | R8: $5,162 | S8: $6,195 | T8: $3,044 | U8: Not Listed | V8: 64 | W8: 1968 | X8: 0 | Y8: Yes | Z8: No | AA8: No | AB8: No | AC8: No | AD8: HIGH | AE8: Section 8/HUD, 1968 vintage, 64 units, 8.5 mi. Income-restricted. | AF8: HUD Multifamily Assisted Housing
A9: 2 | B9: AFFORDABLE | C9: Hialeah Gardens Apartments | E9: 1200 W 68th St | F9: Hialeah | G9: FL | H9: 33012 | I9: 5.2 mi | J9: $3,872 | K9: $4,647 | L9: $1,736 | M9: 3200 | N9: $4,645 | O9: $5,575 | P9: $2,376 | Q9: 3896 | R9: $5,162 | S9: $6,195 | T9: $3,044 | U9: 4686 | V9: 72 | W9: 1970 | X9: 2 | Y9: Yes | Z9: No | AA9: No | AB9: No | AC9: No | AD9: HIGH | AE9: Section 8/HUD, 1970 vintage, 72 units, 5.2 mi. Income-restricted. | AF9: HUD Multifamily Assisted Housing
A10: 3 | B10: AFFORDABLE | C10: Carol City Manor | E10: 18800 NW 27th Ave | F10: Miami Gardens | G10: FL | H10: 33056 | I10: 4.1 mi | J10: $3,872 | K10: $4,647 | L10: $1,736 | M10: Not Listed | N10: $4,645 | O10: $5,575 | P10: $2,376 | Q10: Not Listed | R10: $5,162 | S10: $6,195 | T10: $3,044 | U10: Not Listed | V10: 60 | W10: 1967 | X10: 1 | Y10: Yes | Z10: No | AA10: No | AB10: No | AC10: No | AD10: HIGH | AE10: Section 8/HUD, 1967 vintage, 60 units, 4.1 mi. Income-restricted. | AF10: HUD Multifamily Assisted Housing
A11: 4 | B11: AFFORDABLE | C11: North Miami HA - Arch Creek Apts | E11: 1800 NE 135th St | F11: North Miami | G11: FL | H11: 33161 | I11: 6.8 mi | J11: $3,872 | K11: $4,647 | L11: $1,736 | M11: Not Listed | N11: $4,645 | O11: $5,575 | P11: $2,376 | Q11: Not Listed | R11: $5,162 | S11: $6,195 | T11: $3,044 | U11: Not Listed | V11: 68 | W11: 1969 | X11: 1 | Y11: Yes | Z11: No | AA11: No | AB11: No | AC11: No | AD11: MODERATE-HIGH | AE11: Public Housing/HUD, 1969 vintage, 68 units, 6.8 mi. Income-restricted. | AF11: HUD Multifamily Assisted Housing
A12: 1 | B12: MARKET RATE | C12: Sherbondy Villas | D12: COMPETITION | E12: 200 S Perviz Ave | F12: Opa Locka | G12: FL | H12: 33054 | I12: 1.2 mi | J12: N/A | K12: N/A | L12: $1,736 | M12: 1400 | N12: N/A | O12: N/A | P12: $2,376 | Q12: N/A | R12: N/A | S12: N/A | T12: $3,044 | U12: N/A | V12: 32 | W12: 1967 | X12: 1 | Y12: No | Z12: No | AA12: No | AB12: No | AC12: No | AD12: HIGH | AE12: No income restrictions, 1967 vintage, 32 units, 1.2 mi. 1BD avg $1,400/mo. | AF12: apartments.com/sherbondy-villas-opa-locka-fl/
A13: 2 | B13: MARKET RATE | C13: Wellspring Apartments | E13: 14701 NW 27th Ave | F13: Opa Locka | G13: FL | H13: 33054 | I13: 1.8 mi | J13: N/A | K13: N/A | L13: $1,736 | M13: 1989 | N13: N/A | O13: N/A | P13: $2,376 | Q13: 2440 | R13: N/A | S13: N/A | T13: $3,044 | U13: N/A | V13: N/A | W13: 2024 | X13: 56 | Y13: No | Z13: Yes | AA13: No | AB13: Yes | AC13: No | AD13: HIGH | AE13: No income restrictions, 2024 vintage, 1.8 mi. 1BD avg $1,989; 2BD avg $2,440/mo. | AF13: apartments.com/wellspring-apartments-opa-locka-fl/
A14: 3 | B14: MARKET RATE | C14: Individual Units — 33054 (avg) | E14: Various, Opa Locka, FL 33054 | F14: Opa Locka | G14: FL | H14: 33054 | I14: < 3 mi | J14: N/A | K14: N/A | L14: $1,736 | M14: 1300 | N14: N/A | O14: N/A | P14: $2,376 | Q14: 1760 | R14: N/A | S14: N/A | T14: $3,044 | U14: 2598 | V14: N/A | W14: Various | X14: N/A | Y14: Varies | Z14: Varies | AA14: Varies | AB14: Varies | AC14: Varies | AD14: MODERATE-HIGH | AE14: Individual units listed on Zillow/Apartments.com in 33054 zip. Avg asking rents. | AF14: Zillow/Apartments.com — 33054 zip, Apr 2026
A15: 4 | B15: MARKET RATE | C15: Oak Enclave | E15: 2301 NW 167th St | F15: Miami Gardens | G15: FL | H15: 33056 | I15: 3.1 mi | J15: N/A | K15: N/A | L15: $1,736 | M15: 2000 | N15: N/A | O15: N/A | P15: $2,376 | Q15: 2240 | R15: N/A | S15: N/A | T15: $3,044 | U15: 2670 | V15: N/A | W15: N/A | X15: N/A | Y15: N/A | Z15: N/A | AA15: N/A | AB15: No | AC15: No | AD15: HIGH | AE15: No income restrictions, 3.1 mi. 1BD avg $2,000; 2BD avg $2,240; 3BD avg $2,670/mo. | AF15: apartments.com/oak-enclave-miami-gardens-fl/
A16: 5 | B16: MARKET RATE | C16: Emerald Bay | E16: 8570 W 40th Ave | F16: Hialeah | G16: FL | H16: 33018 | I16: 6.0 mi | J16: N/A | K16: N/A | L16: $1,736 | M16: 1900 | N16: N/A | O16: N/A | P16: $2,376 | Q16: 2200 | R16: N/A | S16: N/A | T16: $3,044 | U16: N/A | V16: N/A | W16: 2020 | X16: 52 | Y16: No | Z16: Yes | AA16: Yes | AB16: Yes | AC16: Yes | AD16: HIGH | AE16: No income restrictions, 2020 vintage, 6.0 mi. 1BD avg $1,900; 2BD avg $2,200/mo. | AF16: apartments.com/emerald-bay-hialeah-fl/
A17: 6 | B17: MARKET RATE | C17: The Oasis at Opa Locka | E17: 13400 NW 22nd Ave | F17: Opa Locka | G17: FL | H17: 33054 | I17: 2.5 mi | J17: N/A | K17: N/A | L17: $1,736 | M17: 1750 | N17: N/A | O17: N/A | P17: $2,376 | Q17: 2100 | R17: N/A | S17: N/A | T17: $3,044 | U17: 2500 | V17: N/A | W17: 2018 | X17: 50 | Y17: No | Z17: Yes | AA17: Yes | AB17: Yes | AC17: No | AD17: HIGH | AE17: No income restrictions, 2018 vintage, 2.5 mi. 1BD avg $1,750; 2BD avg $2,100; 3BD avg $2,500/mo. | AF17: apartments.com/the-oasis-at-opa-locka-fl/
A18: — | B18: BENCHMARK | C18: FY2026 FMR — Miami-Dade County | E18: N/A | F18: Opa Locka | G18: FL | H18: N/A | I18: N/A | J18: $1,736 | K18: $1,736 | L18: $1,736 | M18: N/A | N18: $2,376 | O18: $2,376 | P18: $2,376 | Q18: N/A | R18: $3,044 | S18: $3,044 | T18: $3,044 | U18: N/A | V18: N/A | W18: N/A | X18: N/A | Y18: N/A | Z18: N/A | AA18: N/A | AB18: N/A | AC18: N/A | AD18: BENCHMARK | AE18: HUD FMR for Miami-Dade County, FL, FY2026. 40th percentile rent. | AF18: HUD FMR Database (huduser.gov)
A19: — | B19: BENCHMARK | C19: Metro Market Avg — Opa Locka/Miami (Apr 2026) | E19: N/A | F19: Opa Locka | G19: FL | H19: N/A | I19: N/A | J19: $1,723 | K19: $1,723 | L19: $1,723 | M19: $1,723 | N19: $2,148 | O19: $2,148 | P19: $2,148 | Q19: $2,148 | R19: $2,589 | S19: $2,589 | T19: $2,589 | U19: $2,589 | V19: N/A | W19: N/A | X19: N/A | Y19: N/A | Z19: N/A | AA19: N/A | AB19: N/A | AC19: N/A | AD19: BENCHMARK | AE19: Live Market Average from 6 market-rate comps, Apr 30, 2026. 1BD avg $1,723; 2BD avg $2,148; 3BD avg $2,589. | AF19: Apartments.com live data, Apr 30, 2026
A21: COLOR KEY: GREEN = Subject Property | TEAL = Affordable/Income-Restricted Comp | BLUE = Market-Rate Comp | LIGHT BLUE = FMR Benchmark | YELLOW = Market Average | ORANGE = Actual Rent
A23: CURRENT RENT vs. MARKET AVERAGE
A24: Market Average = Avg of Actual Advertised Rents from 6 Market-Rate Comps (Apartments.com)
B25: Current Rents | C25: Market Avg | E25: Difference
A26: 1BD | B26: ='Current Rents'!D13 -> 1470 | C26: 1723 | E26: =B26-C26 -> -253 | F26: =IF(E26<-75,"LOOK INTO INCREASING THE RENT!","") -> LOOK INTO INCREASING THE RENT!
A27: 2BD | B27: ='Current Rents'!E13 -> 1800 | C27: 2148 | E27: =B27-C27 -> -348 | F27: =IF(E27<-75,"LOOK INTO INCREASING THE RENT!","") -> LOOK INTO INCREASING THE RENT!
A28: 3BD | B28: ='Current Rents'!F13 -> 2320 | C28: 2589 | E28: =B28-C28 -> -269 | F28: =IF(E28<-75,"LOOK INTO INCREASING THE RENT!","") -> LOOK INTO INCREASING THE RENT!

Sheet 14 - Macedonia
A2: RENT COMPARABLES ANALYSIS — MACEDONIA | PANAMA CITY, FL 32405 | Z2: 14 - Macedonia | 100 Units | LIHTC / Section 8 | 2BD & 3BD
A3: 3101 E 15th St, Panama City, FL 32405 | Bay County | Panama City MSA
A4: Data as of April 30, 2026 | Sources: Apartments.com, HUD FMR Database, Apartment Corp Records
A5: COLUMN GUIDE — Income-restricted comps show AMI-based maximum allowable rents (50%/60% AMI) alongside FMR. Market-rate comps show N/A for AMI columns. Actual = advertised/in-place rent. Competition Level: HIGH = direct competition; MODERATE-HIGH = partial overlap.
A6: Rank | B6: Type | C6: Property Name | E6: Address | F6: City | G6: St | H6: ZIP | I6: Distance | J6: 2BD 50% AMI | K6: 2BD 60% AMI | L6: 2BD FMR | M6: 2BD - Actual | N6: 3BD 50% AMI | O6: 3BD 60% AMI | P6: 3BD FMR | Q6: 3BD - Actual | R6: Units | S6: Yr Built | T6: Yr Diff | U6: Utils Incl. | V6: Pet Friendly | W6: Gated | X6: Pool | Y6: W/D In-Unit | Z6: Competition Level | AA6: Notes / Why Competitive | AB6: Data Source
A7: ★ | B7: SUBJECT | C7: Macedonia (SUBJECT) | E7: 3101 E 15th St | F7: Panama City | G7: FL | H7: 32405 | I7: 0.0 mi | J7: $3,529 | K7: $4,235 | L7: $1,426 | M7: ='Current Rents'!E14 -> 1451 | N7: $3,920 | O7: $4,705 | P7: $1,818 | Q7: ='Current Rents'!F14 -> 1613 | R7: 100 | S7: 1969 | T7: 0 | U7: Yes | V7: No | W7: No | X7: No | Y7: No | Z7: SUBJECT | AA7: 100 units | LIHTC/Section 8. Year built: 1969. Subject property. | AB7: Apartment Corp Records
A8: 1 | B8: AFFORDABLE | C8: Bay County Housing Authority | E8: 2300 E 11th St | F8: Panama City | G8: FL | H8: 32401 | I8: 3.2 mi | J8: $3,529 | K8: $4,235 | L8: $1,426 | M8: Not Listed | N8: $3,920 | O8: $4,705 | P8: $1,818 | Q8: Not Listed | R8: 100 | S8: 1969 | T8: 0 | U8: Yes | V8: No | W8: No | X8: No | Y8: No | Z8: HIGH | AA8: Public Housing/HUD, 1969 vintage, 100 units, 3.2 mi. Income-restricted. | AB8: Bay County Housing Authority
A9: 2 | B9: AFFORDABLE | C9: Pensacola HA - Attucks Court | E9: 600 N Hayne St | F9: Pensacola | G9: FL | H9: 32501 | I9: 95.0 mi | J9: $3,529 | K9: $4,235 | L9: $1,426 | M9: Not Listed | N9: $3,920 | O9: $4,705 | P9: $1,818 | Q9: Not Listed | R9: 96 | S9: 1970 | T9: 1 | U9: Yes | V9: No | W9: No | X9: No | Y9: No | Z9: LOW-MODERATE | AA9: Public Housing/HUD, 1970 vintage, 96 units, 95.0 mi. | AB9: Pensacola Housing Authority
A10: 3 | B10: AFFORDABLE | C10: Tallahassee HA - Bond Homes | E10: 1400 S Bronough St | F10: Tallahassee | G10: FL | H10: 32301 | I10: 100.0 mi | J10: $3,529 | K10: $4,235 | L10: $1,426 | M10: Not Listed | N10: $3,920 | O10: $4,705 | P10: $1,818 | Q10: Not Listed | R10: 104 | S10: 1968 | T10: 1 | U10: Yes | V10: No | W10: No | X10: No | Y10: No | Z10: LOW-MODERATE | AA10: Public Housing/HUD, 1968 vintage, 104 units, 100.0 mi. | AB10: Tallahassee Housing Authority
A11: 4 | B11: AFFORDABLE | C11: Panama City Beach Housing Authority | E11: 800 Thomas Dr | F11: Panama City Beach | G11: FL | H11: 32408 | I11: 8.5 mi | J11: $3,529 | K11: $4,235 | L11: $1,426 | M11: Not Listed | N11: $3,920 | O11: $4,705 | P11: $1,818 | Q11: Not Listed | R11: 88 | S11: 1970 | T11: 1 | U11: Yes | V11: No | W11: No | X11: No | Y11: No | Z11: HIGH | AA11: Section 8/HUD, 1970 vintage, 88 units, 8.5 mi. | AB11: HUD Multifamily Assisted Housing
A12: 1 | B12: MARKET RATE | C12: Arbor Crossing at Mill Bayou | D12: COMPETITION | E12: 198 Mill Bayou Blvd | F12: Panama City | G12: FL | H12: 32404 | I12: 3.2 mi | J12: N/A | K12: N/A | L12: $1,426 | M12: 1559 | N12: N/A | O12: N/A | P12: $1,818 | Q12: 1799 | R12: N/A | S12: 2024 | T12: 55 | U12: No | V12: Yes | W12: Yes | X12: Yes | Y12: Yes | Z12: HIGH | AA12: No income restrictions, 2024 vintage, 3.2 mi. 2BD $1,559 / 3BD $1,799. | AB12: apartments.com/arbor-crossing-at-mill-bayou-panama-city-fl/
A13: 2 | B13: MARKET RATE | C13: The Kelly at 23rd Luxury Apts | E13: 2002 Wilson Ave | F13: Panama City | G13: FL | H13: 32405 | I13: 0.5 mi | J13: N/A | K13: N/A | L13: $1,426 | M13: 1839 | N13: N/A | O13: N/A | P13: $1,818 | Q13: 1850 | R13: N/A | S13: 2025 | T13: 56 | U13: No | V13: Yes | W13: Yes | X13: Yes | Y13: Yes | Z13: HIGH | AA13: No income restrictions, 2025 vintage, 0.5 mi. 2BD $1,839 / 3BD $1,850. | AB13: apartments.com/the-kelly-at-23rd-panama-city-fl/
A14: 3 | B14: MARKET RATE | C14: Residences at SweetBay | E14: 3100 Sweetbay Ave | F14: Panama City | G14: FL | H14: 32405 | I14: 1.1 mi | J14: N/A | K14: N/A | L14: $1,426 | M14: 1558 | N14: N/A | O14: N/A | P14: $1,818 | Q14: 2015 | R14: N/A | S14: 2022 | T14: 53 | U14: No | V14: Yes | W14: Yes | X14: Yes | Y14: Yes | Z14: HIGH | AA14: No income restrictions, 2022 vintage, 1.1 mi. 2BD $1,558 / 3BD $2,015. | AB14: apartments.com/residences-at-sweetbay-panama-city-fl/
A15: 4 | B15: MARKET RATE | C15: Exchange at North Bay | E15: 3625 Frankford Ave | F15: Panama City | G15: FL | H15: 32405 | I15: 0.8 mi | J15: N/A | K15: N/A | L15: $1,426 | M15: 1529 | N15: N/A | O15: N/A | P15: $1,818 | Q15: 1786 | R15: N/A | S15: 2022 | T15: 53 | U15: No | V15: Yes | W15: Yes | X15: Yes | Y15: Yes | Z15: HIGH | AA15: No income restrictions, 2022 vintage, 0.8 mi. 2BD $1,529 / 3BD $1,786. | AB15: apartments.com/exchange-at-north-bay-panama-city-fl/
A16: 5 | B16: MARKET RATE | C16: Eagles Landing Luxury Apts | E16: 2870 Harrison Ave | F16: Panama City | G16: FL | H16: 32405 | I16: 1.5 mi | J16: N/A | K16: N/A | L16: $1,426 | M16: 1509 | N16: N/A | O16: N/A | P16: $1,818 | Q16: 1770 | R16: N/A | S16: 1993 | T16: 24 | U16: No | V16: Yes | W16: No | X16: Yes | Y16: No | Z16: HIGH | AA16: No income restrictions, 1993 vintage, 1.5 mi. 2BD $1,509 / 3BD $1,770. | AB16: apartments.com/eagles-landing-luxury-apts-panama-city-fl/
A17: 6 | B17: MARKET RATE | C17: The Enclave | E17: 2950 Harrison Ave | F17: Panama City | G17: FL | H17: 32405 | I17: 1.4 mi | J17: N/A | K17: N/A | L17: $1,426 | M17: 1525 | N17: N/A | O17: N/A | P17: $1,818 | Q17: 1700 | R17: N/A | S17: 1993 | T17: 24 | U17: No | V17: Yes | W17: No | X17: Yes | Y17: No | Z17: HIGH | AA17: No income restrictions, 1993 vintage, 1.4 mi. 2BD $1,525 / 3BD $1,700. | AB17: apartments.com/the-enclave-panama-city-fl/
A18: — | B18: BENCHMARK | C18: FY2026 FMR — Bay County, FL | E18: N/A | F18: Panama City | G18: FL | H18: N/A | I18: N/A | J18: $1,426 | K18: $1,426 | L18: $1,426 | M18: N/A | N18: $1,818 | O18: $1,818 | P18: $1,818 | Q18: N/A | R18: N/A | S18: N/A | T18: N/A | U18: N/A | V18: N/A | W18: N/A | X18: N/A | Y18: N/A | Z18: BENCHMARK | AA18: HUD FMR for Bay County (Panama City MSA), FL, FY2026. 40th percentile rent. | AB18: HUD FMR Database (huduser.gov)
A19: — | B19: BENCHMARK | C19: Metro Market Avg — Panama City (Apr 2026) | E19: N/A | F19: Panama City | G19: FL | H19: N/A | I19: N/A | J19: $1,586 | K19: $1,586 | L19: $1,586 | M19: $1,586 | N19: $1,820 | O19: $1,820 | P19: $1,820 | Q19: $1,820 | R19: N/A | S19: N/A | T19: N/A | U19: N/A | V19: N/A | W19: N/A | X19: N/A | Y19: N/A | Z19: BENCHMARK | AA19: Live Market Average from 6 comps, Apr 30, 2026. 2BD avg $1,586 / 3BD avg $1,820. | AB19: Apartments.com live data, Apr 30, 2026
A21: COLOR KEY: GREEN = Subject Property | TEAL = Affordable/Income-Restricted Comp | BLUE = Market-Rate Comp | LIGHT BLUE = FMR Benchmark | YELLOW = Market Average | ORANGE = Actual Rent
A23: CURRENT RENT vs. MARKET AVERAGE
A24: Market Average = Avg of Actual Advertised Rents from 6 Market-Rate Comps (Apartments.com)
B25: Current Rents | C25: Market Avg | E25: Difference
A26: 2BD | B26: ='Current Rents'!E14 -> 1451 | C26: 1586 | E26: =B26-C26 -> -135 | F26: =IF(E26<-75,"LOOK INTO INCREASING THE RENT!","") -> LOOK INTO INCREASING THE RENT!
A27: 3BD | B27: ='Current Rents'!F14 -> 1613 | C27: 1820 | E27: =B27-C27 -> -207 | F27: =IF(E27<-75,"LOOK INTO INCREASING THE RENT!","") -> LOOK INTO INCREASING THE RENT!

Sheet 48 - Coral Village
A8: RENT COMPARABLES ANALYSIS — CORAL VILLAGE | CAPE CORAL, FL 33990 | Z8: 48 - Coral Village | 72 Units | Section 8 / HUD | 1BD & 2BD
A9: Cape Coral, FL 33990 | Lee County | Cape Coral-Fort Myers MSA
A10: Data as of April 30, 2026 | Sources: Apartments.com, HUD FMR Database, Apartment Corp Records
A11: COLUMN GUIDE — Income-restricted comps show AMI-based maximum allowable rents (50%/60% AMI) alongside FMR. Market-rate comps show N/A for AMI columns. Actual = advertised/in-place rent. Competition Level: HIGH = direct competition; MODERATE-HIGH = partial overlap.
A12: Rank | B12: Type | C12: Property Name | E12: Address | F12: City | G12: St | H12: ZIP | I12: Distance | J12: 1BD 50% AMI | K12: 1BD 60% AMI | L12: 1BD FMR | M12: 1BD - Actual | N12: 2BD 50% AMI | O12: 2BD 60% AMI | P12: 2BD FMR | Q12: 2BD - Actual | R12: Units | S12: Yr Built | T12: Yr Diff | U12: Utils Incl. | V12: Pet Friendly | W12: Gated | X12: Pool | Y12: W/D In-Unit | Z12: Competition Level | AA12: Notes / Why Competitive | AB12: Data Source
A13: ★ | B13: SUBJECT | C13: Coral Village (SUBJECT) | E13: Cape Coral | F13: Cape Coral | G13: FL | H13: 33990 | I13: 0.0 mi | J13: $3,193 | K13: $3,832 | L13: $1,371 | M13: ='Current Rents'!D15 -> 1375 | N13: $3,829 | O13: $4,595 | P13: $1,876 | Q13: ='Current Rents'!E15 -> 1552 | R13: 72 | S13: 1999 | T13: 0 | U13: Yes | V13: No | W13: No | X13: Yes | Y13: No | Z13: SUBJECT | AA13: 72 units | Section 8/HUD. Year built: 1999. Subject property. | AB13: Apartment Corp Records
A14: 1 | B14: AFFORDABLE | C14: Brittany II | E14: 4050 Winkler Ave Ext | F14: Fort Myers | G14: FL | H14: 33916 | I14: 8.0 mi | J14: $3,193 | K14: $3,832 | L14: $1,371 | M14: Not Listed | N14: $3,829 | O14: $4,595 | P14: $1,876 | Q14: Not Listed | R14: 112 | S14: 2000 | T14: 1 | U14: Yes | V14: No | W14: No | X14: No | Y14: No | Z14: HIGH | AA14: LIHTC, 2000 vintage, 112 units, 8.0 mi. Income-restricted. | AB14: HUD LIHTC Database
A15: 2 | B15: AFFORDABLE | C15: Brittany | E15: 4054 Winkler Ave | F15: Fort Myers | G15: FL | H15: 33916 | I15: 7.9 mi | J15: $3,193 | K15: $3,832 | L15: $1,371 | M15: Not Listed | N15: $3,829 | O15: $4,595 | P15: $1,876 | Q15: Not Listed | R15: 208 | S15: 1999 | T15: 0 | U15: Yes | V15: No | W15: No | X15: No | Y15: No | Z15: HIGH | AA15: LIHTC, 1999 vintage, 208 units, 7.9 mi. Income-restricted. | AB15: HUD LIHTC Database
A16: 3 | B16: AFFORDABLE | C16: Crossings at Cape Coral | E16: 1150 Hancock Crk Blvd | F16: Cape Coral | G16: FL | H16: 33909 | I16: 7.7 mi | J16: $3,193 | K16: $3,832 | L16: $1,371 | M16: Not Listed | N16: $3,829 | O16: $4,595 | P16: $1,876 | Q16: 1224 | R16: 168 | S16: 2000 | T16: 1 | U16: Yes | V16: No | W16: No | X16: No | Y16: No | Z16: HIGH | AA16: LIHTC, 2000 vintage, 168 units, 7.7 mi. Income-restricted. | AB16: HUD LIHTC Database
A17: 4 | B17: AFFORDABLE | C17: Westchase | E17: 3810 Metro Pkwy | F17: Fort Myers | G17: FL | H17: 33916 | I17: 6.8 mi | J17: $3,193 | K17: $3,832 | L17: $1,371 | M17: Not Listed | N17: $3,829 | O17: $4,595 | P17: $1,876 | Q17: Not Listed | R17: 352 | S17: 1999 | T17: 0 | U17: Yes | V17: No | W17: No | X17: No | Y17: No | Z17: HIGH | AA17: LIHTC, 1999 vintage, 352 units, 6.8 mi. Income-restricted. | AB17: HUD LIHTC Database
A18: 1 | B18: MARKET RATE | C18: Cape at Savona Point | D18: COMPETITION | E18: 1730 Savona Point Cir | F18: Cape Coral | G18: FL | H18: 33914 | I18: 5.2 mi | J18: N/A | K18: N/A | L18: $1,371 | M18: 1287 | N18: N/A | O18: N/A | P18: $1,876 | Q18: 1472 | R18: N/A | S18: 2021 | T18: 22 | U18: No | V18: Yes | W18: Yes | X18: Yes | Y18: Yes | Z18: HIGH | AA18: No income restrictions, 2021 vintage, 5.2 mi. 1BD $1,287 / 2BD $1,472. | AB18: apartments.com/cape-at-savona-point-cape-coral-fl/
A19: 2 | B19: MARKET RATE | C19: The Palms at Cape Coral | E19: 701 SW Pine Island Rd | F19: Cape Coral | G19: FL | H19: 33991 | I19: 4.8 mi | J19: N/A | K19: N/A | L19: $1,371 | M19: 1243 | N19: N/A | O19: N/A | P19: $1,876 | Q19: 1503 | R19: N/A | S19: 2023 | T19: 24 | U19: No | V19: Yes | W19: Yes | X19: Yes | Y19: Yes | Z19: HIGH | AA19: No income restrictions, 2023 vintage, 4.8 mi. 1BD $1,243 / 2BD $1,503. | AB19: apartments.com/the-palms-at-cape-coral-fl/
A20: 3 | B20: MARKET RATE | C20: Oasis at Surfside | E20: 2200 Oasis Palm Cir | F20: Cape Coral | G20: FL | H20: 33991 | I20: 4.1 mi | J20: N/A | K20: N/A | L20: $1,371 | M20: 1389 | N20: N/A | O20: N/A | P20: $1,876 | Q20: 1549 | R20: N/A | S20: 2022 | T20: 23 | U20: No | V20: Yes | W20: Yes | X20: Yes | Y20: Yes | Z20: HIGH | AA20: No income restrictions, 2022 vintage, 4.1 mi. 1BD $1,389 / 2BD $1,549. | AB20: apartments.com/oasis-at-surfside-cape-coral-fl/
A21: 4 | B21: MARKET RATE | C21: Springs at Coral Shores | E21: 606 SW 29th Ave | F21: Cape Coral | G21: FL | H21: 33991 | I21: 3.9 mi | J21: N/A | K21: N/A | L21: $1,371 | M21: 1327 | N21: N/A | O21: N/A | P21: $1,876 | Q21: 1480 | R21: N/A | S21: 2020 | T21: 21 | U21: No | V21: Yes | W21: Yes | X21: Yes | Y21: Yes | Z21: HIGH | AA21: No income restrictions, 2020 vintage, 3.9 mi. 1BD $1,327 / 2BD $1,480. | AB21: apartments.com/springs-at-coral-shores-cape-coral-fl/
A22: 5 | B22: MARKET RATE | C22: Coralina Apartments | E22: 3305 Grant Cove Cir | F22: Cape Coral | G22: FL | H22: 33991 | I22: 4.5 mi | J22: N/A | K22: N/A | L22: $1,371 | M22: 1360 | N22: N/A | O22: N/A | P22: $1,876 | Q22: 1694 | R22: N/A | S22: 2022 | T22: 23 | U22: No | V22: Yes | W22: Yes | X22: Yes | Y22: Yes | Z22: HIGH | AA22: No income restrictions, 2022 vintage, 4.5 mi. 1BD $1,360 / 2BD $1,694. | AB22: apartments.com/coralina-apartments-cape-coral-fl/
A23: 6 | B23: MARKET RATE | C23: Apts at Isles of Porto Vista | E23: 3936 Pomodoro Cir | F23: Cape Coral | G23: FL | H23: 33909 | I23: 7.3 mi | J23: N/A | K23: N/A | L23: $1,371 | M23: 1424 | N23: N/A | O23: N/A | P23: $1,876 | Q23: 1499 | R23: N/A | S23: 2023 | T23: 24 | U23: No | V23: Yes | W23: Yes | X23: Yes | Y23: Yes | Z23: HIGH | AA23: No income restrictions, 2023 vintage, 7.3 mi. 1BD $1,424 / 2BD $1,499. | AB23: apartments.com/isles-of-porto-vista-cape-coral-fl/
A24: — | B24: BENCHMARK | C24: FY2026 FMR — Cape Coral-Fort Myers MSA | E24: N/A | F24: Cape Coral | G24: FL | H24: N/A | I24: N/A | J24: $1,371 | K24: $1,371 | L24: $1,371 | M24: N/A | N24: $1,876 | O24: $1,876 | P24: $1,876 | Q24: N/A | R24: N/A | S24: N/A | T24: N/A | U24: N/A | V24: N/A | W24: N/A | X24: N/A | Y24: N/A | Z24: BENCHMARK | AA24: HUD FMR for Cape Coral-Fort Myers MSA, FY2026. 40th percentile rent. | AB24: HUD FMR Database (huduser.gov)
A25: — | B25: BENCHMARK | C25: Metro Market Avg — Cape Coral (Apr 2026) | E25: N/A | F25: Cape Coral | G25: FL | H25: N/A | I25: N/A | J25: $1,338 | K25: $1,338 | L25: $1,338 | M25: $1,338 | N25: $1,533 | O25: $1,533 | P25: $1,533 | Q25: $1,533 | R25: N/A | S25: N/A | T25: N/A | U25: N/A | V25: N/A | W25: N/A | X25: N/A | Y25: N/A | Z25: BENCHMARK | AA25: Live Market Average from 6 comps, Apr 30, 2026. 1BD avg $1,338 / 2BD avg $1,533. | AB25: Apartments.com live data, Apr 30, 2026
A27: COLOR KEY: GREEN = Subject Property | TEAL = Affordable/Income-Restricted Comp | BLUE = Market-Rate Comp | LIGHT BLUE = FMR Benchmark | YELLOW = Market Average | ORANGE = Actual Rent
A29: CURRENT RENT vs. MARKET AVERAGE
A30: Market Average = Avg of Actual Advertised Rents from 6 Market-Rate Comps (Apartments.com)
B31: Current Rents | C31: Market Avg | E31: Difference
A32: 1BD | B32: ='Current Rents'!D15 -> 1375 | C32: 1338 | E32: =B32-C32 -> 37 | F32: =IF(E32<-75,"LOOK INTO INCREASING THE RENT!","")
A33: 2BD | B33: ='Current Rents'!E15 -> 1552 | C33: 1533 | E33: =B33-C33 -> 19 | F33: =IF(E33<-75,"LOOK INTO INCREASING THE RENT!","")

Sheet 15 - Holiday
A8: RENT COMPARABLES ANALYSIS — HOLIDAY APTS | NATCHEZ, MS 39120 | AG8: 15 - Holiday | 115 Units | Section 8 / HUD | 2BD, 3BD, 4BD & 5BD
A9: 601 Old Washington Road, Natchez, MS 39120 | Adams County | FY2026 HUD FMR Area: Adams County, MS
A10: Data as of April 30, 2026 | Sources: Apartments.com, HUD FMR Database, Apartment Corp Records
A11: COLUMN GUIDE — Income-restricted comps show AMI-based maximum allowable rents (50%/60% AMI) alongside FMR. Market-rate comps show N/A for AMI columns. Actual = advertised/in-place rent. Competition Level: HIGH = direct competition; MODERATE-HIGH = partial overlap.
A12: Rank | B12: Type | C12: Property Name | E12: Address | F12: City | G12: St | H12: ZIP | I12: Distance | J12: 2BD 50% AMI | K12: 2BD 60% AMI | L12: 2BD FMR | M12: 2BD - Actual | N12: 3BD 50% AMI | O12: 3BD 60% AMI | P12: 3BD FMR | Q12: 3BD - Actual | R12: 4BD 50% AMI | S12: 4BD 60% AMI | T12: 4BD FMR | U12: 4BD - Actual | V12: 5BD 50% AMI | W12: 5BD 60% AMI | X12: 5BD FMR | Y12: Units | Z12: Yr Built | AA12: Yr Diff | AB12: Utils Incl. | AC12: Pet Friendly | AD12: Gated | AE12: Pool | AF12: W/D In-Unit | AG12: Competition Level | AH12: Notes / Why Competitive | AI12: Data Source
A13: ★ | B13: SUBJECT | C13: Holiday Apts (SUBJECT) | E13: 601 Old Washington Road | F13: Natchez | G13: MS | H13: 39120 | I13: 0.0 mi | J13: $2,591 | K13: $3,110 | L13: $820 | M13: ='Current Rents'!E16 -> 935 | N13: $2,879 | O13: $3,455 | P13: $1,040 | Q13: ='Current Rents'!F16 -> 1073 | R13: $3,112 | S13: $3,735 | T13: $1,202 | U13: ='Current Rents'!G16 -> 1147 | V13: $3,341 | W13: $4,010 | X13: $1,382 | Y13: 115 | Z13: 1951 | AA13: 0 | AB13: Yes | AC13: No | AD13: No | AE13: No | AF13: No | AG13: SUBJECT | AH13: 115 units | Section 8/HUD. Year built: 1951. Subject property. | AI13: Apartment Corp Records
A14: 1 | B14: AFFORDABLE | C14: Natchez HA - Sadie V. Thompson Homes | E14: 200 Sadie Thompson Dr | F14: Natchez | G14: MS | H14: 39120 | I14: 1.5 mi | J14: $2,591 | K14: $3,110 | L14: $820 | M14: Not Listed | N14: $2,879 | O14: $3,455 | P14: $1,040 | Q14: Not Listed | R14: $3,112 | S14: $3,735 | T14: $1,202 | U14: Not Listed | V14: $3,341 | W14: $4,010 | X14: $1,382 | Y14: 100 | Z14: 1952 | AA14: 1 | AB14: Yes | AC14: No | AD14: No | AE14: No | AF14: No | AG14: HIGH | AH14: Public Housing/HUD, 1952 vintage, 100 units, 1.5 mi. Income-restricted. | AI14: Natchez Housing Authority
A15: 2 | B15: AFFORDABLE | C15: Vicksburg HA - Ida B. Wells Homes | E15: 1 Ida B Wells Dr | F15: Vicksburg | G15: MS | H15: 39180 | I15: 72.0 mi | J15: $2,591 | K15: $3,110 | L15: $820 | M15: Not Listed | N15: $2,879 | O15: $3,455 | P15: $1,040 | Q15: Not Listed | R15: $3,112 | S15: $3,735 | T15: $1,202 | U15: Not Listed | V15: $3,341 | W15: $4,010 | X15: $1,382 | Y15: 150 | Z15: 1955 | AA15: 4 | AB15: Yes | AC15: No | AD15: No | AE15: No | AF15: No | AG15: LOW-MODERATE | AH15: Public Housing/HUD, 1955 vintage, 150 units, 72.0 mi. | AI15: Vicksburg Housing Authority
A16: 3 | B16: AFFORDABLE | C16: Laurel HA - Queensburg Homes | E16: 100 Queensburg Dr | F16: Laurel | G16: MS | H16: 39440 | I16: 145.0 mi | J16: $2,591 | K16: $3,110 | L16: $820 | M16: Not Listed | N16: $2,879 | O16: $3,455 | P16: $1,040 | Q16: Not Listed | R16: $3,112 | S16: $3,735 | T16: $1,202 | U16: Not Listed | V16: $3,341 | W16: $4,010 | X16: $1,382 | Y16: 100 | Z16: 1950 | AA16: 1 | AB16: Yes | AC16: No | AD16: No | AE16: No | AF16: No | AG16: LOW-MODERATE | AH16: Public Housing/HUD, 1950 vintage, 100 units, 145.0 mi. | AI16: Laurel Housing Authority
A17: 4 | B17: AFFORDABLE | C17: Natchez HA - Belleview Homes | E17: 400 Belleview Ave | F17: Natchez | G17: MS | H17: 39120 | I17: 1.8 mi | J17: $2,591 | K17: $3,110 | L17: $820 | M17: Not Listed | N17: $2,879 | O17: $3,455 | P17: $1,040 | Q17: Not Listed | R17: $3,112 | S17: $3,735 | T17: $1,202 | U17: Not Listed | V17: $3,341 | W17: $4,010 | X17: $1,382 | Y17: 120 | Z17: 1953 | AA17: 2 | AB17: Yes | AC17: No | AD17: No | AE17: No | AF17: No | AG17: HIGH | AH17: Public Housing/HUD, 1953 vintage, 120 units, 1.8 mi. Income-restricted. | AI17: Natchez Housing Authority
A18: 1 | B18: MARKET RATE | C18: Camelot Apartments | D18: COMPETITION | E18: 156 Jefferson Davis Blvd | F18: Natchez | G18: MS | H18: 39120 | I18: 1.2 mi | J18: N/A | K18: N/A | L18: $820 | M18: 850 | N18: N/A | O18: N/A | P18: $1,040 | Q18: Not Listed | R18: N/A | S18: N/A | T18: $1,202 | U18: Not Listed | V18: N/A | W18: N/A | X18: $1,382 | Y18: N/A | Z18: 1975 | AA18: 24 | AB18: No | AC18: No | AD18: No | AE18: No | AF18: No | AG18: HIGH | AH18: No income restrictions, 1975 vintage, 1.2 mi. 2BD avg $850/mo. | AI18: Apartments.com / Zillow
A19: 2 | B19: MARKET RATE | C19: Bienville Apartments | E19: 500 N Commerce St | F19: Natchez | G19: MS | H19: 39120 | I19: 0.8 mi | J19: N/A | K19: N/A | L19: $820 | M19: 815 | N19: N/A | O19: N/A | P19: $1,040 | Q19: Not Listed | R19: N/A | S19: N/A | T19: $1,202 | U19: Not Listed | V19: N/A | W19: N/A | X19: $1,382 | Y19: N/A | Z19: 1970 | AA19: 19 | AB19: No | AC19: No | AD19: No | AE19: No | AF19: No | AG19: HIGH | AH19: No income restrictions, 1970 vintage, 0.8 mi. 2BD avg $815/mo. | AI19: Apartments.com / Zillow
A20: 3 | B20: MARKET RATE | C20: Riverbreeze Manor | E20: 144 N Shields Ln | F20: Natchez | G20: MS | H20: 39120 | I20: 1.5 mi | J20: N/A | K20: N/A | L20: $820 | M20: 750 | N20: N/A | O20: N/A | P20: $1,040 | Q20: 850 | R20: N/A | S20: N/A | T20: $1,202 | U20: Not Listed | V20: N/A | W20: N/A | X20: $1,382 | Y20: N/A | Z20: 1980 | AA20: 29 | AB20: No | AC20: No | AD20: No | AE20: No | AF20: No | AG20: HIGH | AH20: No income restrictions, 1980 vintage, 1.5 mi. 2BD avg $750; 3BD avg $850/mo. | AI20: Apartments.com / Zillow
A21: 4 | B21: MARKET RATE | C21: Covington II | E21: 22 T Waring Bennett Jr Rd | F21: Natchez | G21: MS | H21: 39120 | I21: 2.1 mi | J21: N/A | K21: N/A | L21: $820 | M21: 730 | N21: N/A | O21: N/A | P21: $1,040 | Q21: Not Listed | R21: N/A | S21: N/A | T21: $1,202 | U21: Not Listed | V21: N/A | W21: N/A | X21: $1,382 | Y21: N/A | Z21: 1985 | AA21: 34 | AB21: No | AC21: No | AD21: No | AE21: No | AF21: No | AG21: HIGH | AH21: No income restrictions, 1985 vintage, 2.1 mi. 2BD avg $730/mo. | AI21: Apartments.com / Zillow
A22: 5 | B22: MARKET RATE | C22: 2116 Second St (House) | E22: 2116 Second St | F22: Natchez | G22: MS | H22: 39120 | I22: 0.9 mi | J22: N/A | K22: N/A | L22: $820 | M22: N/A | N22: N/A | O22: N/A | P22: $1,040 | Q22: 1150 | R22: N/A | S22: N/A | T22: $1,202 | U22: Not Listed | V22: N/A | W22: N/A | X22: $1,382 | Y22: 1 | Z22: 1960 | AA22: 9 | AB22: No | AC22: No | AD22: No | AE22: No | AF22: No | AG22: HIGH | AH22: Individual rental house, 1960 vintage, 0.9 mi. 3BD avg $1,150/mo. | AI22: Zillow
A23: 6 | B23: MARKET RATE | C23: 214 Margaret Ave (House) | E23: 214 Margaret Ave | F23: Natchez | G23: MS | H23: 39120 | I23: 1.3 mi | J23: N/A | K23: N/A | L23: $820 | M23: N/A | N23: N/A | O23: N/A | P23: $1,040 | Q23: 1895 | R23: N/A | S23: N/A | T23: $1,202 | U23: Not Listed | V23: N/A | W23: N/A | X23: $1,382 | Y23: 1 | Z23: 1965 | AA23: 14 | AB23: No | AC23: No | AD23: No | AE23: No | AF23: No | AG23: HIGH | AH23: Individual rental house, 1965 vintage, 1.3 mi. 3BD avg $1,895/mo. | AI23: Zillow
A24: — | B24: BENCHMARK | C24: FY2026 FMR — Adams County, MS | E24: N/A | F24: Natchez | G24: MS | H24: N/A | I24: N/A | J24: $820 | K24: $820 | L24: $820 | M24: N/A | N24: $1,040 | O24: $1,040 | P24: $1,040 | Q24: N/A | R24: $1,202 | S24: $1,202 | T24: $1,202 | U24: N/A | V24: $1,382 | W24: $1,382 | X24: $1,382 | Y24: N/A | Z24: N/A | AA24: N/A | AB24: N/A | AC24: N/A | AD24: N/A | AE24: N/A | AF24: N/A | AG24: BENCHMARK | AH24: HUD FMR for Adams County, MS, FY2026. 40th percentile rent. | AI24: HUD FMR Database (huduser.gov)
A25: — | B25: BENCHMARK | C25: Metro Market Avg — Natchez (Apr 2026) | E25: N/A | F25: Natchez | G25: MS | H25: N/A | I25: N/A | J25: $786 | K25: $786 | L25: $786 | M25: $786 | N25: $1,298 | O25: $1,298 | P25: $1,298 | Q25: $1,298 | R25: N/A | S25: N/A | T25: N/A | U25: N/A | V25: N/A | W25: N/A | X25: N/A | Y25: N/A | Z25: N/A | AA25: N/A | AB25: N/A | AC25: N/A | AD25: N/A | AE25: N/A | AF25: N/A | AG25: BENCHMARK | AH25: Live Market Average from available comps, Apr 30, 2026. 2BD avg $786 / 3BD avg $1,298. | AI25: Apartments.com live data, Apr 30, 2026
A27: COLOR KEY: GREEN = Subject Property | TEAL = Affordable/Income-Restricted Comp | BLUE = Market-Rate Comp | LIGHT BLUE = FMR Benchmark | YELLOW = Market Average | ORANGE = Actual Rent
A29: CURRENT RENT vs. MARKET AVERAGE
A30: Market Average = Avg of Actual Advertised Rents from 6 Market-Rate Comps (Apartments.com)
B31: Current Rents | C31: Market Avg | E31: Difference
A32: 2BD | B32: ='Current Rents'!E16 -> 935 | C32: 786 | E32: =B32-C32 -> 149 | F32: =IF(E32<-75,"LOOK INTO INCREASING THE RENT!","")
A33: 3BD | B33: ='Current Rents'!F16 -> 1073 | C33: 1298 | E33: =B33-C33 -> -225 | F33: =IF(E33<-75,"LOOK INTO INCREASING THE RENT!","") -> LOOK INTO INCREASING THE RENT!
A34: 4BD | B34: ='Current Rents'!G16 -> 1147 | C34: N/A | E34: =B34-C34 -> #VALUE! | F34: =IF(E34<-75,"LOOK INTO INCREASING THE RENT!","") -> #VALUE!

Sheet 16 - Cumberland
A8: RENT COMPARABLES ANALYSIS — CUMBERLAND | CRYSTAL SPRINGS, MS 39059 | AH8: 16 - Cumberland | 68 Units | Section 8 / HUD | 1BD, 2BD, 3BD & 4BD
A9: 100 Cumberland Drive, Crystal Springs, MS 39059 | Copiah County | FY2026 FMR: 1BD $642 / 2BD $880 / 3BD $1,100 / 4BD $1,272
A10: Data as of April 30, 2026 | Sources: Apartments.com, HUD FMR Database, HUD Multifamily Assisted Housing, Apartment Corp Records
A11: COLUMN GUIDE — Income-restricted comps show AMI-based maximum allowable rents at 50% and 60% AMI tiers. Market-rate comps show what unrestricted renters pay in the same market. LOW = 50% AMI max rent. MID = 60% AMI max rent. FMR = HUD FY2026 Fair Market Rent (40th percentile). ACTUAL = Verified advertised rent from Apartments.com (highlighted in orange). 'Not Listed' = property does not publicly advertise rents. AMI source: HUD FY2025 MTSP Income Limits, effective April 1, 2025.
A12: Rank | B12: Type | C12: Property Name | E12: Address | F12: City | G12: St | H12: ZIP | I12: Distance | J12: 1BD 50% AMI | K12: 1BD 60% AMI | L12: 1BD FMR | M12: 1BD - Actual | N12: 2BD 50% AMI | O12: 2BD 60% AMI | P12: 2BD FMR | Q12: 2BD - Actual | R12: 3BD 50% AMI | S12: 3BD 60% AMI | T12: 3BD FMR | U12: 3BD - Actual | V12: 4BD 50% AMI | W12: 4BD 60% AMI | X12: 4BD FMR | Y12: 4BD - Actual | Z12: Units | AA12: Yr Built | AB12: Yr Diff | AC12: Utils Incl. | AD12: Pet Friendly | AE12: Gated | AF12: Pool | AG12: W/D In-Unit | AH12: Competition Level | AI12: Notes / Why Competitive | AJ12: Data Source
A13: ★ | B13: SUBJECT | C13: Cumberland (SUBJECT) | E13: 100 Cumberland Drive | F13: Crystal Springs | G13: MS | H13: 39059 | I13: 0.0 mi | J13: $2,160 | K13: $2,592 | L13: $642 | M13: ='Current Rents'!D17 -> 1074 | N13: $2,591 | O13: $3,110 | P13: $880 | Q13: ='Current Rents'!E17 -> 1166 | R13: $2,879 | S13: $3,455 | T13: $1,100 | U13: ='Current Rents'!F17 -> 1290 | V13: $3,112 | W13: $3,735 | X13: $1,272 | Y13: ='Current Rents'!G17 -> 1433 | Z13: 68 | AA13: 1985 | AB13: 0 | AC13: Yes | AD13: No | AE13: No | AF13: No | AG13: No | AH13: SUBJECT | AI13: 68 units | Section 8/HUD. Year built: 1985. Subject property. | AJ13: Apartment Corp Records
A14: 1 | B14: AFFORDABLE | C14: Indian Creek Phase II | E14: 150 Hwy 469 N | F14: Florence | G14: MS | H14: 39073 | I14: 18.4 mi | J14: $2,160 | K14: $2,592 | L14: $642 | M14: Not Listed | N14: $2,591 | O14: $3,110 | P14: $880 | Q14: Not Listed | R14: $2,879 | S14: $3,455 | T14: $1,100 | U14: Not Listed | V14: $3,112 | W14: $3,735 | X14: $1,272 | Y14: Not Listed | Z14: 32 | AA14: 1987 | AB14: 2 | AC14: Yes | AD14: No | AE14: No | AF14: No | AG14: No | AH14: HIGH | AI14: LIHTC, 1987 vintage, 32 units, 18.4 mi. | AJ14: HUD LIHTC Database
A15: 2 | B15: AFFORDABLE | C15: Towncreek Apts | E15: Red Dog Rd | F15: Carthage | G15: MS | H15: N/A | I15: N/A | J15: $2,160 | K15: $2,592 | L15: $642 | M15: Not Listed | N15: $2,591 | O15: $3,110 | P15: $880 | Q15: Not Listed | R15: $2,879 | S15: $3,455 | T15: $1,100 | U15: Not Listed | V15: $3,112 | W15: $3,735 | X15: $1,272 | Y15: Not Listed | Z15: 52 | AA15: 1988 | AB15: 3 | AC15: Yes | AD15: No | AE15: No | AF15: No | AG15: No | AH15: HIGH | AI15: LIHTC, 1988 vintage, 52 units. | AJ15: HUD LIHTC Database
A16: 3 | B16: AFFORDABLE | C16: Bloom Street Apts | E16: 515 Bloom St | F16: Jackson | G16: MS | H16: 39202 | I16: 24.2 mi | J16: $2,160 | K16: $2,592 | L16: $642 | M16: Not Listed | N16: $2,591 | O16: $3,110 | P16: $880 | Q16: Not Listed | R16: $2,879 | S16: $3,455 | T16: $1,100 | U16: Not Listed | V16: $3,112 | W16: $3,735 | X16: $1,272 | Y16: Not Listed | Z16: 24 | AA16: 1987 | AB16: 2 | AC16: Yes | AD16: No | AE16: No | AF16: No | AG16: No | AH16: HIGH | AI16: LIHTC, 1987 vintage, 24 units, 24.2 mi. | AJ16: HUD LIHTC Database
A17: 4 | B17: AFFORDABLE | C17: Sandstone Apts | E17: 607 Wallace Dr | F17: Edwards | G17: MS | H17: 39066 | I17: 28.2 mi | J17: $2,160 | K17: $2,592 | L17: $642 | M17: Not Listed | N17: $2,591 | O17: $3,110 | P17: $880 | Q17: Not Listed | R17: $2,879 | S17: $3,455 | T17: $1,100 | U17: Not Listed | V17: $3,112 | W17: $3,735 | X17: $1,272 | Y17: Not Listed | Z17: 24 | AA17: 1987 | AB17: 2 | AC17: Yes | AD17: No | AE17: No | AF17: No | AG17: No | AH17: HIGH | AI17: LIHTC, 1987 vintage, 24 units, 28.2 mi. | AJ17: HUD LIHTC Database
A18: 1 | B18: MARKET RATE | C18: Highland Hills | D18: COMPETITION | E18: 20 N Hill Pky | F18: Jackson | G18: MS | H18: 39206 | I18: 28 mi | J18: N/A | K18: N/A | L18: N/A | M18: N/A | N18: N/A | O18: N/A | P18: N/A | Q18: 815 | R18: N/A | S18: N/A | T18: N/A | U18: 975 | V18: N/A | W18: N/A | X18: N/A | Y18: N/A | Z18: N/A | AA18: N/A | AB18: N/A | AC18: N/A | AD18: N/A | AE18: No | AF18: N/A | AG18: N/A | AH18: HIGH | AI18: No income restrictions, 28 mi. 2BD $815 / 3BD $975. | AJ18: Apartments.com verified, Apr 2026
A19: 2 | B19: MARKET RATE | C19: The Pines at Autumn Woods | E19: 4901 McWillie Cir | F19: Jackson | G19: MS | H19: 39206 | I19: 29 mi | J19: N/A | K19: N/A | L19: N/A | M19: N/A | N19: N/A | O19: N/A | P19: N/A | Q19: 1100 | R19: N/A | S19: N/A | T19: N/A | U19: N/A | V19: N/A | W19: N/A | X19: N/A | Y19: N/A | Z19: N/A | AA19: N/A | AB19: N/A | AC19: N/A | AD19: N/A | AE19: No | AF19: N/A | AG19: N/A | AH19: HIGH | AI19: No income restrictions, 29 mi. 2BD $1,100. | AJ19: Apartments.com verified, Apr 2026
A20: 3 | B20: MARKET RATE | C20: The Pines at 55 | E20: 3875 S I-55 | F20: Jackson | G20: MS | H20: 39212 | I20: 31 mi | J20: N/A | K20: N/A | L20: N/A | M20: N/A | N20: N/A | O20: N/A | P20: N/A | Q20: 1100 | R20: N/A | S20: N/A | T20: N/A | U20: N/A | V20: N/A | W20: N/A | X20: N/A | Y20: N/A | Z20: N/A | AA20: N/A | AB20: N/A | AC20: N/A | AD20: N/A | AE20: No | AF20: N/A | AG20: N/A | AH20: HIGH | AI20: No income restrictions, 31 mi. 2BD $1,100. | AJ20: Apartments.com verified, Apr 2026
A21: 4 | B21: MARKET RATE | C21: Pear Orchard Apartments | E21: 580 Pear Orchard Rd | F21: Ridgeland | G21: MS | H21: 39157 | I21: 35 mi | J21: N/A | K21: N/A | L21: N/A | M21: N/A | N21: N/A | O21: N/A | P21: N/A | Q21: 1183 | R21: N/A | S21: N/A | T21: N/A | U21: 1697 | V21: N/A | W21: N/A | X21: N/A | Y21: N/A | Z21: N/A | AA21: N/A | AB21: N/A | AC21: N/A | AD21: N/A | AE21: No | AF21: N/A | AG21: N/A | AH21: HIGH | AI21: No income restrictions, 35 mi. 2BD $1,183 / 3BD $1,697. | AJ21: Apartments.com verified, Apr 2026
A22: 5 | B22: MARKET RATE | C22: Northtown Apartments | E22: 50 Northtown Dr | F22: Jackson | G22: MS | H22: 39211 | I22: 30 mi | J22: N/A | K22: N/A | L22: N/A | M22: N/A | N22: N/A | O22: N/A | P22: N/A | Q22: 1002 | R22: N/A | S22: N/A | T22: N/A | U22: N/A | V22: N/A | W22: N/A | X22: N/A | Y22: N/A | Z22: N/A | AA22: N/A | AB22: N/A | AC22: N/A | AD22: N/A | AE22: No | AF22: N/A | AG22: N/A | AH22: HIGH | AI22: No income restrictions, 30 mi. 2BD $1,002. | AJ22: Apartments.com verified, Apr 2026
A23: 6 | B23: MARKET RATE | C23: Royal Oak Apartments | E23: 110 Pine Knoll Dr | F23: Ridgeland | G23: MS | H23: 39157 | I23: 36 mi | J23: N/A | K23: N/A | L23: N/A | M23: N/A | N23: N/A | O23: N/A | P23: N/A | Q23: 1045 | R23: N/A | S23: N/A | T23: N/A | U23: 1450 | V23: N/A | W23: N/A | X23: N/A | Y23: N/A | Z23: N/A | AA23: N/A | AB23: N/A | AC23: N/A | AD23: N/A | AE23: No | AF23: N/A | AG23: N/A | AH23: HIGH | AI23: No income restrictions, 36 mi. 2BD $1,045 / 3BD $1,450. | AJ23: Apartments.com verified, Apr 2026
A24: — | B24: BENCHMARK | C24: FY2026 FMR — Copiah County, MS | E24: N/A | F24: Crystal Springs | G24: MS | H24: N/A | I24: N/A | J24: $642 | K24: $642 | L24: $642 | M24: N/A | N24: $880 | O24: $880 | P24: $880 | Q24: N/A | R24: $1,100 | S24: $1,100 | T24: $1,100 | U24: N/A | V24: $1,272 | W24: $1,272 | X24: $1,272 | Y24: N/A | Z24: N/A | AA24: N/A | AB24: N/A | AC24: N/A | AD24: N/A | AE24: N/A | AF24: N/A | AG24: N/A | AH24: BENCHMARK | AI24: HUD FMR for Copiah County, MS, FY2026. | AJ24: HUD FMR Database (huduser.gov)
A25: — | B25: BENCHMARK | C25: Metro Market Avg — Crystal Springs/Jackson (Apr 2026) | E25: N/A | F25: Crystal Springs | G25: MS | H25: N/A | I25: N/A | J25: N/A | K25: N/A | L25: N/A | M25: N/A | N25: 1041 | O25: 1041 | P25: 1041 | Q25: 1041 | R25: 1374 | S25: 1374 | T25: 1374 | U25: 1374 | V25: N/A | W25: N/A | X25: N/A | Y25: N/A | Z25: N/A | AA25: N/A | AB25: N/A | AC25: N/A | AD25: N/A | AE25: N/A | AF25: N/A | AG25: N/A | AH25: BENCHMARK | AI25: Live Market Average from 6 comps, Apr 30, 2026. 2BD avg $1,041 / 3BD avg $1,374. | AJ25: Apartments.com live data, Apr 30, 2026
A27: COLOR KEY: GREEN = Subject Property | TEAL = Affordable/Income-Restricted Comp | BLUE = Market-Rate Comp | LIGHT BLUE = FMR Benchmark | YELLOW = Market Average | ORANGE = Actual Rent
A29: CURRENT RENT vs. MARKET AVERAGE
A30: Market Average = Avg of Actual Advertised Rents from 6 Market-Rate Comps (Apartments.com)
B31: Current Rents | C31: Market Avg | E31: Difference
A32: 1BD | B32: ='Current Rents'!D17 -> 1074 | C32: N/A | E32: =B32-C32 -> #VALUE! | F32: =IF(E32<-75,"LOOK INTO INCREASING THE RENT!","") -> #VALUE!
A33: 2BD | B33: ='Current Rents'!E17 -> 1166 | C33: 1041 | E33: =B33-C33 -> 125 | F33: =IF(E33<-75,"LOOK INTO INCREASING THE RENT!","")
A34: 3BD | B34: ='Current Rents'!F17 -> 1290 | C34: 1374 | E34: =B34-C34 -> -84 | F34: =IF(E34<-75,"LOOK INTO INCREASING THE RENT!","") -> LOOK INTO INCREASING THE RENT!
A35: 4BD | B35: ='Current Rents'!G17 -> 1433 | C35: N/A | E35: =B35-C35 -> #VALUE! | F35: =IF(E35<-75,"LOOK INTO INCREASING THE RENT!","") -> #VALUE!

Sheet 59 - Walnut Hill
A8: RENT COMPARABLES ANALYSIS — WALNUT HILL | NATCHEZ, MS 39120 | Z8: 59 - Walnut Hill | 168 Units | Section 8 / HUD | 2BD & 3BD
A9: Natchez, MS 39120 | Adams County | FY2026 FMR: 2BD $820 / 3BD $1,040
A10: Data as of April 30, 2026 | Sources: Apartments.com, HUD FMR Database, HUD Multifamily Assisted Housing, Apartment Corp Records
A11: COLUMN GUIDE — Income-restricted comps show AMI-based maximum allowable rents at 50% and 60% AMI tiers. Market-rate comps show what unrestricted renters pay in the same market. LOW = 50% AMI max rent. MID = 60% AMI max rent. FMR = HUD FY2026 Fair Market Rent (40th percentile). ACTUAL = Verified advertised rent from Apartments.com (highlighted in orange). 'Not Listed' = property does not publicly advertise rents. AMI source: HUD FY2025 MTSP Income Limits, effective April 1, 2025.
A12: Rank | B12: Type | C12: Property Name | E12: Address | F12: City | G12: St | H12: ZIP | I12: Distance | J12: 2BD 50% AMI | K12: 2BD 60% AMI | L12: 2BD FMR | M12: 2BD - Actual | N12: 3BD 50% AMI | O12: 3BD 60% AMI | P12: 3BD FMR | Q12: 3BD - Actual | R12: Units | S12: Yr Built | T12: Yr Diff | U12: Utils Incl. | V12: Pet Friendly | W12: Gated | X12: Pool | Y12: W/D In-Unit | Z12: Competition Level | AA12: Notes / Why Competitive | AB12: Data Source
A13: ★ | B13: SUBJECT | C13: Walnut Hill (SUBJECT) | E13: Natchez | F13: Natchez | G13: MS | H13: 39120 | I13: 0.0 mi | J13: $2,591 | K13: $3,110 | L13: $820 | M13: ='Current Rents'!E18 -> 1346 | N13: $2,879 | O13: $3,455 | P13: $1,040 | Q13: ='Current Rents'!F18 -> 1465 | R13: 168 | S13: 1975 | T13: 0 | U13: Yes | V13: No | W13: No | X13: No | Y13: No | Z13: SUBJECT | AA13: 168 units | Section 8/HUD. Year built: 1975. Subject property. | AB13: Apartment Corp Records
A14: 1 | B14: AFFORDABLE | C14: Natchez HA - Duncan Park Homes | E14: 400 Duncan Ave | F14: Natchez | G14: MS | H14: 39120 | I14: 1.5 mi | J14: $2,591 | K14: $3,110 | L14: $820 | M14: Not Listed | N14: $2,879 | O14: $3,455 | P14: $1,040 | Q14: Not Listed | R14: 160 | S14: 1975 | T14: 0 | U14: Yes | V14: No | W14: No | X14: No | Y14: No | Z14: HIGH | AA14: Public Housing/HUD, 1975 vintage, 160 units, 1.5 mi. | AB14: Natchez Housing Authority
A15: 2 | B15: AFFORDABLE | C15: Vicksburg HA - Parkway Village | E15: 300 Parkway Blvd | F15: Vicksburg | G15: MS | H15: 39180 | I15: 72.0 mi | J15: $2,591 | K15: $3,110 | L15: $820 | M15: Not Listed | N15: $2,879 | O15: $3,455 | P15: $1,040 | Q15: Not Listed | R15: 150 | S15: 1976 | T15: 1 | U15: Yes | V15: No | W15: No | X15: No | Y15: No | Z15: LOW-MODERATE | AA15: Section 8/HUD, 1976 vintage, 150 units, 72.0 mi. | AB15: HUD Multifamily Assisted Housing
A16: 3 | B16: AFFORDABLE | C16: Hattiesburg HA - Eureka Homes | E16: 200 Eureka St | F16: Hattiesburg | G16: MS | H16: 39401 | I16: 145.0 mi | J16: $2,591 | K16: $3,110 | L16: $820 | M16: Not Listed | N16: $2,879 | O16: $3,455 | P16: $1,040 | Q16: Not Listed | R16: 172 | S16: 1974 | T16: 1 | U16: Yes | V16: No | W16: No | X16: No | Y16: No | Z16: LOW-MODERATE | AA16: Public Housing/HUD, 1974 vintage, 172 units, 145.0 mi. | AB16: Hattiesburg Housing Authority
A17: 4 | B17: AFFORDABLE | C17: Natchez Terrace Apartments | E17: 600 Seargent Prentiss Dr | F17: Natchez | G17: MS | H17: 39120 | I17: 2.1 mi | J17: $2,591 | K17: $3,110 | L17: $820 | M17: Not Listed | N17: $2,879 | O17: $3,455 | P17: $1,040 | Q17: Not Listed | R17: 156 | S17: 1977 | T17: 2 | U17: Yes | V17: No | W17: No | X17: No | Y17: No | Z17: HIGH | AA17: Section 8/HUD, 1977 vintage, 156 units, 2.1 mi. | AB17: HUD Multifamily Assisted Housing
A18: 1 | B18: MARKET RATE | C18: Camelot Apartments | D18: COMPETITION | E18: 156 Jefferson Davis Blvd | F18: Natchez | G18: MS | H18: 39120 | I18: 1.1 mi | J18: N/A | K18: N/A | L18: N/A | M18: N/A | N18: N/A | O18: N/A | P18: N/A | Q18: 850 | R18: N/A | S18: N/A | T18: N/A | U18: N/A | V18: N/A | W18: No | X18: N/A | Y18: N/A | Z18: HIGH | AA18: No income restrictions, 1.1 mi. 3BD $850. | AB18: Apartments.com verified, Apr 2026
A19: 2 | B19: MARKET RATE | C19: Bienville Apartments | E19: 500 N Commerce St | F19: Natchez | G19: MS | H19: 39120 | I19: 1.5 mi | J19: N/A | K19: N/A | L19: N/A | M19: N/A | N19: N/A | O19: N/A | P19: N/A | Q19: 815 | R19: N/A | S19: N/A | T19: N/A | U19: N/A | V19: N/A | W19: No | X19: N/A | Y19: N/A | Z19: HIGH | AA19: No income restrictions, 1.5 mi. 3BD $815. | AB19: Apartments.com verified, Apr 2026
A20: 3 | B20: MARKET RATE | C20: Covington II | E20: 22 T Waring Bennett Jr Rd | F20: Natchez | G20: MS | H20: 39120 | I20: 1.8 mi | J20: N/A | K20: N/A | L20: N/A | M20: N/A | N20: N/A | O20: N/A | P20: N/A | Q20: 730 | R20: N/A | S20: N/A | T20: N/A | U20: N/A | V20: N/A | W20: No | X20: N/A | Y20: N/A | Z20: HIGH | AA20: No income restrictions, 1.8 mi. 3BD $730. | AB20: Apartments.com verified, Apr 2026
A21: 4 | B21: MARKET RATE | C21: Riverbreeze Manor | E21: 144 N Shields Ln | F21: Natchez | G21: MS | H21: 39120 | I21: 2.1 mi | J21: N/A | K21: N/A | L21: N/A | M21: N/A | N21: N/A | O21: N/A | P21: N/A | Q21: 850 | R21: N/A | S21: N/A | T21: N/A | U21: N/A | V21: N/A | W21: No | X21: N/A | Y21: N/A | Z21: HIGH | AA21: No income restrictions, 2.1 mi. 3BD $850. | AB21: Apartments.com verified, Apr 2026
A22: 5 | B22: MARKET RATE | C22: Individual Unit — 1008 N Union St | E22: 1008 N Union St | F22: Natchez | G22: MS | H22: 39120 | I22: 1.3 mi | J22: N/A | K22: N/A | L22: N/A | M22: N/A | N22: N/A | O22: N/A | P22: N/A | Q22: 1289 | R22: 1 | S22: N/A | T22: N/A | U22: N/A | V22: N/A | W22: No | X22: N/A | Y22: N/A | Z22: HIGH | AA22: Single-family rental, 1.3 mi. 3BD $1,289. | AB22: Apartments.com verified, Apr 2026
A23: 6 | B23: MARKET RATE | C23: Individual Unit — 2116 Second St | E23: 2116 Second St | F23: Natchez | G23: MS | H23: 39120 | I23: 1.0 mi | J23: N/A | K23: N/A | L23: N/A | M23: N/A | N23: N/A | O23: N/A | P23: N/A | Q23: 1150 | R23: 1 | S23: N/A | T23: N/A | U23: N/A | V23: N/A | W23: No | X23: N/A | Y23: N/A | Z23: HIGH | AA23: Single-family rental, 1.0 mi. 3BD $1,150. | AB23: Apartments.com verified, Apr 2026
A24: — | B24: BENCHMARK | C24: FY2026 FMR — Adams County, MS | E24: N/A | F24: Natchez | G24: MS | H24: N/A | I24: N/A | J24: $820 | K24: $820 | L24: $820 | M24: N/A | N24: $1,040 | O24: $1,040 | P24: $1,040 | Q24: N/A | R24: N/A | S24: N/A | T24: N/A | U24: N/A | V24: N/A | W24: N/A | X24: N/A | Y24: N/A | Z24: BENCHMARK | AA24: HUD FMR for Adams County, MS, FY2026. | AB24: HUD FMR Database (huduser.gov)
A25: — | B25: BENCHMARK | C25: Metro Market Avg — Natchez (Apr 2026) | E25: N/A | F25: Natchez | G25: MS | H25: N/A | I25: N/A | J25: N/A | K25: N/A | L25: N/A | M25: N/A | N25: 786 | O25: 786 | P25: 786 | Q25: =AVERAGE(Q18:Q23) -> 947.33333 | R25: N/A | S25: N/A | T25: N/A | U25: N/A | V25: N/A | W25: N/A | X25: N/A | Y25: N/A | Z25: BENCHMARK | AA25: Live Market Average from 6 comps, Apr 30, 2026. 3BD avg $786 (limited 2BD data available). | AB25: Apartments.com live data, Apr 30, 2026
A27: COLOR KEY: GREEN = Subject Property | TEAL = Affordable/Income-Restricted Comp | BLUE = Market-Rate Comp | LIGHT BLUE = FMR Benchmark | YELLOW = Market Average | ORANGE = Actual Rent
A29: CURRENT RENT vs. MARKET AVERAGE
A30: Market Average = Avg of Actual Advertised Rents from 6 Market-Rate Comps (Apartments.com)
B31: Current Rents | C31: Market Avg | E31: Difference
A32: 2BD | B32: ='Current Rents'!E18 -> 1346 | C32: N/A | E32: =B32-C32 -> #VALUE! | F32: =IF(E32<-75,"LOOK INTO INCREASING THE RENT!","") -> #VALUE!
A33: 3BD | B33: ='Current Rents'!F18 -> 1465 | C33: =Q25 -> 947.33333 | E33: =C33-B33 -> -517.66667 | F33: =IF(E33<-75,"LOOK INTO INCREASING THE RENT!","") -> LOOK INTO INCREASING THE RENT!

Sheet 29 - River Pointe
A5: RENT COMPARABLES ANALYSIS — RIVER POINTE | COLUMBUS, OH 43228 | Y5: 29 - River Pointe | 160 Units | Section 8 / HUD | 1BD & 2BD
A6: 777 Avonia Drive, Columbus, OH 43228 | Franklin County | Columbus OH HMFA | FY2026 FMR: 1BD $1,044 / 2BD $1,430
A7: Data as of April 30, 2026 | Sources: Apartments.com, RentCafe, HUD FMR Database, HUD LIHTC Database, Apartment Corp Records
A8: COLUMN GUIDE — Income-restricted comps show AMI-based maximum allowable rents at 50% and 60% AMI tiers. Market-rate comps show what unrestricted renters pay in the same market. LOW = 50% AMI max rent. MID = 60% AMI max rent. FMR = HUD FY2026 Fair Market Rent (40th percentile). ACTUAL = Verified advertised rent from Apartments.com (highlighted in orange). 'Not Listed' = property does not publicly advertise rents. AMI source: HUD FY2025 MTSP Income Limits, effective April 1, 2025.
A9: Rank | B9: Type | C9: Property Name | E9: Address | F9: City | G9: St | H9: ZIP | I9: Distance | J9: 1BD 50% AMI | K9: 1BD 60% AMI | L9: 1BD FMR | M9: 2BD 50% AMI | N9: 2BD 60% AMI | O9: 2BD FMR | P9: 2BD - Actual | Q9: Units | R9: Yr Built | S9: Yr Diff | T9: Utils Incl. | U9: Pet Friendly | V9: Gated | W9: Pool | X9: W/D In-Unit | Y9: Competition Level | Z9: Notes / Why Competitive | AA9: Data Source
A10: ★ | B10: SUBJECT | C10: River Pointe (SUBJECT) | E10: 777 Avonia Drive | F10: Columbus | G10: OH | H10: 43228 | I10: 0.0 mi | J10: Income-Based | K10: Income-Based | L10: $1,044 | M10: Income-Based | N10: Income-Based | O10: $1,430 | P10: ='Current Rents'!E19 -> 1400 | Q10: 160 | R10: 1996 | S10: 0 | T10: Partial | U10: No | V10: No | W10: No | X10: No | Y10: SUBJECT | Z10: 160 units | Section 8/HUD. Year built: 1996. Subject property. | AA10: Apartment Corp Records
A11: 1 | B11: AFFORDABLE | C11: Abbey Church Village | E11: 2914 Bishops Retreat Pl | F11: Dublin | G11: OH | H11: 43017 | I11: 9.5 mi | J11: N/A | K11: N/A | L11: $1,044 | M11: N/A | N11: N/A | O11: $1,430 | P11: Not Listed | Q11: 160 | R11: 1996 | S11: 0 | T11: Yes | U11: No | V11: No | W11: No | X11: No | Y11: HIGH | Z11: LIHTC, 1996 vintage, 160 units, 9.5 mi. Income-restricted. | AA11: HUD LIHTC Database
A12: 2 | B12: AFFORDABLE | C12: Winchester Lakes Apts | E12: 6621 Kodiak Dr | F12: Canal Winchester | G12: OH | H12: 43110 | I12: 11.5 mi | J12: N/A | K12: N/A | L12: $1,044 | M12: N/A | N12: N/A | O12: $1,430 | P12: 1031 | Q12: 150 | R12: 1996 | S12: 0 | T12: Yes | U12: No | V12: No | W12: No | X12: No | Y12: HIGH | Z12: LIHTC, 1996 vintage, 150 units, 11.5 mi. Income-restricted. | AA12: HUD LIHTC Database
A13: 3 | B13: AFFORDABLE | C13: Fourth Street YWCA Renovation | E13: 65 S Fourth St | F13: Columbus | G13: OH | H13: 43215 | I13: 0.1 mi | J13: N/A | K13: N/A | L13: $1,044 | M13: N/A | N13: N/A | O13: $1,430 | P13: Not Listed | Q13: 102 | R13: 1996 | S13: 0 | T13: Yes | U13: No | V13: No | W13: No | X13: No | Y13: HIGH | Z13: LIHTC, 1996 vintage, 102 units, 0.1 mi. Income-restricted. | AA13: HUD LIHTC Database
A14: 4 | B14: AFFORDABLE | C14: Strattford Lakes | E14: 3555 Ashton Cross | F14: Canal Winchester | G14: OH | H14: 43110 | I14: 10.0 mi | J14: N/A | K14: N/A | L14: $1,044 | M14: N/A | N14: N/A | O14: $1,430 | P14: Not Listed | Q14: 124 | R14: 1996 | S14: 0 | T14: Yes | U14: No | V14: No | W14: No | X14: No | Y14: HIGH | Z14: LIHTC, 1996 vintage, 124 units, 10.0 mi. Income-restricted. | AA14: HUD LIHTC Database
A15: 1 | B15: MARKET RATE | C15: Raccoon Creek Apartments | D15: COMPETITION | E15: 3819 Plane Tree Dr W | F15: Columbus | G15: OH | H15: 43228 | I15: 0.5 mi | J15: N/A | K15: N/A | L15: $1,044 | M15: N/A | N15: N/A | O15: $1,430 | P15: N/A | Q15: N/A | R15: 1994 | S15: 2 | T15: No | U15: Varies | V15: Varies | W15: Varies | X15: Varies | Y15: HIGH | Z15: No income restrictions, 1994 vintage, 0.5 mi. 1BD $990. | AA15: apartments.com/raccoon-creek-columbus-oh/
A16: 2 | B16: MARKET RATE | C16: The Reserve at Parkwick | E16: 4711 Bay Run Dr | F16: Columbus | G16: OH | H16: 43228 | I16: 1.5 mi | J16: N/A | K16: N/A | L16: $1,044 | M16: N/A | N16: N/A | O16: $1,430 | P16: 1175 | Q16: N/A | R16: 1995 | S16: 1 | T16: No | U16: Varies | V16: Varies | W16: Varies | X16: Varies | Y16: HIGH | Z16: No income restrictions, 1995 vintage, 1.5 mi. 1BD $990 / 2BD $1,175. | AA16: apartments.com/reserve-at-parkwick-columbus-oh/
A17: 3 | B17: MARKET RATE | C17: Waterford Pointe | E17: 5750 Feder Rd | F17: Columbus | G17: OH | H17: 43228 | I17: 2.0 mi | J17: N/A | K17: N/A | L17: $1,044 | M17: N/A | N17: N/A | O17: $1,430 | P17: 1095 | Q17: N/A | R17: 1996 | S17: 0 | T17: No | U17: Varies | V17: Varies | W17: Varies | X17: Varies | Y17: HIGH | Z17: No income restrictions, 1996 vintage, 2.0 mi. 1BD $995 / 2BD $1,095. | AA17: apartments.com/waterford-pointe-columbus-oh/
A18: 4 | B18: MARKET RATE | C18: Newbridge Commons | E18: 4551 Durrow Dr | F18: Columbus | G18: OH | H18: 43228 | I18: 1.5 mi | J18: N/A | K18: N/A | L18: $1,044 | M18: N/A | N18: N/A | O18: $1,430 | P18: 1109 | Q18: N/A | R18: 1998 | S18: 2 | T18: No | U18: Varies | V18: Varies | W18: Varies | X18: Varies | Y18: HIGH | Z18: No income restrictions, 1998 vintage, 1.5 mi. 1BD $917 / 2BD $1,109. | AA18: apartments.com/newbridge-commons-columbus-oh/
A19: 5 | B19: MARKET RATE | C19: Hartford Village Commons | E19: 1040 Hartford Village Blvd | F19: Columbus | G19: OH | H19: 43228 | I19: 2.0 mi | J19: N/A | K19: N/A | L19: $1,044 | M19: N/A | N19: N/A | O19: $1,430 | P19: 1025 | Q19: N/A | R19: 1997 | S19: 1 | T19: N/A | U19: N/A | V19: N/A | W19: N/A | X19: N/A | Y19: HIGH | Z19: No income restrictions, 1997 vintage, 2.0 mi. 1BD $925 / 2BD $1,025. | AA19: apartments.com/hartford-village-commons-columbus-oh/
A20: 6 | B20: MARKET RATE | C20: Bolton Estates | E20: 5400 Lindberg Blvd | F20: Columbus | G20: OH | H20: 43228 | I20: 2.5 mi | J20: N/A | K20: N/A | L20: $1,044 | M20: N/A | N20: N/A | O20: $1,430 | P20: 1030 | Q20: N/A | R20: 1993 | S20: 3 | T20: N/A | U20: N/A | V20: N/A | W20: N/A | X20: N/A | Y20: HIGH | Z20: No income restrictions, 1993 vintage, 2.5 mi. 1BD $895 / 2BD $1,030. | AA20: apartments.com/bolton-estates-columbus-oh/
A21: — | B21: BENCHMARK | C21: FY2026 FMR — Columbus, OH HMFA | E21: N/A | F21: Columbus | G21: OH | H21: N/A | I21: N/A | J21: $1,044 | K21: $1,044 | L21: $1,044 | M21: $1,430 | N21: $1,430 | O21: $1,430 | P21: N/A | Q21: N/A | R21: N/A | S21: N/A | T21: N/A | U21: N/A | V21: N/A | W21: N/A | X21: N/A | Y21: BENCHMARK | Z21: HUD FMR for Columbus, OH HMFA, FY2026. | AA21: HUD FMR Database (huduser.gov)
A22: — | B22: BENCHMARK | C22: Metro Market Avg — Columbus West (Apr 2026) | E22: N/A | F22: Columbus | G22: OH | H22: N/A | I22: N/A | J22: 952 | K22: 952 | L22: 952 | M22: 1087 | N22: 1087 | O22: 1087 | P22: 1087 | Q22: N/A | R22: N/A | S22: N/A | T22: N/A | U22: N/A | V22: N/A | W22: N/A | X22: N/A | Y22: BENCHMARK | Z22: Live Market Average from 6 comps, Apr 30, 2026. 1BD avg $952 / 2BD avg $1,087. | AA22: Apartments.com live data, Apr 30, 2026
A24: COLOR KEY: GREEN = Subject Property | TEAL = Affordable/Income-Restricted Comp | BLUE = Market-Rate Comp | LIGHT BLUE = FMR Benchmark | YELLOW = Market Average | ORANGE = Actual Rent
A26: CURRENT RENT vs. MARKET AVERAGE
A27: Market Average = Avg of Actual Advertised Rents from 6 Market-Rate Comps (Apartments.com)
B28: Current Rents | C28: Market Avg | E28: Difference
A29: 2BD | B29: ='Current Rents'!E19 -> 1400 | C29: 1087 | E29: =B29-C29 -> 313 | F29: =IF(E29<-75,"LOOK INTO INCREASING THE RENT!","")

Sheet 12 - Breckenridge
A8: RENT COMPARABLES ANALYSIS — BRECKENRIDGE VILLAGE | ENNIS, TX 75119 | Z8: 12 - Breckenridge | 66 Units | LIHTC | 2BD & 4BD
A9: 2001 N Floyd St, Ennis, TX 75119 | Ellis County | FY2026 FMR: 2BD $1,931 / 4BD $2,810
A10: Data as of June 2026 | Sources: Apartments.com, HUD FMR Database, HUD LIHTC Database, Apartment Corp Records
A11: COLUMN GUIDE — Income-restricted comps show AMI-based maximum allowable rents at 50% and 60% AMI tiers. Market-rate comps show what unrestricted renters pay in the same market. LOW = 50% AMI max rent. MID = 60% AMI max rent. FMR = HUD FY2026 Fair Market Rent (40th percentile). ACTUAL = Verified advertised rent from Apartments.com (highlighted in orange). 'Not Listed' = property does not publicly advertise rents. AMI source: HUD FY2025 MTSP Income Limits, effective April 1, 2025.
A12: Rank | B12: Type | C12: Property Name | E12: Address | F12: City | G12: St | H12: ZIP | I12: Distance | J12: 2BD 50% AMI | K12: 2BD 60% AMI | L12: 2BD FMR | M12: 2BD - Actual | N12: 4BD 50% AMI | O12: 4BD 60% AMI | P12: 4BD FMR | Q12: 4BD - Actual | R12: Units | S12: Yr Built | T12: Yr Diff | U12: Utils Incl. | V12: Pet Friendly | W12: Gated | X12: Pool | Y12: W/D In-Unit | Z12: Competition Level | AA12: Notes / Why Competitive | AB12: Data Source
A13: ★ | B13: SUBJECT | C13: Breckenridge Village (SUBJECT) | E13: 2001 N Floyd St | F13: Ennis | G13: TX | H13: 75119 | I13: 0.0 mi | J13: $4,400 | K13: $5,280 | L13: $1,931 | M13: ='Current Rents'!E20 -> 964 | N13: $5,279 | O13: $6,335 | P13: $2,810 | Q13: ='Current Rents'!G20 -> 1221 | R13: 66 | S13: 1997 | T13: 0 | U13: No | V13: No | W13: No | X13: No | Y13: No | Z13: SUBJECT | AA13: 66 units | LIHTC property. Year built: 1997. Subject property for market context. | AB13: Apartment Corp Records
A14: 1 | B14: AFFORDABLE | C14: Breckenridge Village | E14: 2001A Floyd St | F14: Ennis | G14: TX | H14: 75119 | I14: 1.2 mi | J14: $4,400 | K14: $5,280 | L14: $1,931 | M14: Not Listed | N14: $5,279 | O14: $6,335 | P14: $2,810 | Q14: Not Listed | R14: 66 | S14: 1997 | T14: 0 | U14: Yes | V14: No | W14: No | X14: No | Y14: No | Z14: HIGH | AA14: Affordable Comp #1: LIHTC property, 1997 vintage (0 yr diff), 66 units, 1.2 mi from subject. Same income-eligible renter pool. | AB14: HUD LIHTC Database (huduser.gov)
A15: 2 | B15: AFFORDABLE | C15: Lexington Arms | E15: 418 Lexington Dr | F15: Waxahachie | G15: TX | H15: 75165 | I15: 12.0 mi | J15: $4,400 | K15: $5,280 | L15: $1,931 | M15: Not Listed | N15: $5,279 | O15: $6,335 | P15: $2,810 | Q15: 1641 | R15: 61 | S15: 1997 | T15: 0 | U15: Yes | V15: No | W15: No | X15: No | Y15: No | Z15: HIGH | AA15: Affordable Comp #2: LIHTC property, 1997 vintage (0 yr diff), 61 units, 12.0 mi from subject. Same income-eligible renter pool. | AB15: HUD LIHTC Database (huduser.gov)
A16: 3 | B16: AFFORDABLE | C16: Creekside Terrace Apts | E16: 1000 E Burnett St | F16: Ennis | G16: TX | H16: 75119 | I16: 0.7 mi | J16: $4,400 | K16: $5,280 | L16: $1,931 | M16: 1270 | N16: $5,279 | O16: $6,335 | P16: $2,810 | Q16: 1650 | R16: 80 | S16: 1998 | T16: 1 | U16: Yes | V16: No | W16: No | X16: No | Y16: No | Z16: HIGH | AA16: Affordable Comp #3: LIHTC property, 1998 vintage (1 yr diff), 80 units, 0.7 mi from subject. Same income-eligible renter pool. | AB16: HUD LIHTC Database (huduser.gov)
A17: 4 | B17: AFFORDABLE | C17: Sherwood Arms Apts | E17: 213 N Val Verde Cir | F17: Keene | G17: TX | H17: 76059 | I17: 41.4 mi | J17: $4,400 | K17: $5,280 | L17: $1,931 | M17: Not Listed | N17: $5,279 | O17: $6,335 | P17: $2,810 | Q17: Not Listed | R17: 56 | S17: 1997 | T17: 0 | U17: Yes | V17: No | W17: No | X17: No | Y17: No | Z17: MODERATE | AA17: Affordable Comp #4: LIHTC property, 1997 vintage (0 yr diff), 56 units, 41.4 mi from subject. Same income-eligible renter pool. | AB17: HUD LIHTC Database (huduser.gov)
A18: 1 | B18: MARKET RATE | C18: Grace Townhomes | D18: COMPETITION | E18: 1212 Grace Cir | F18: Ennis | G18: TX | H18: 75119 | I18: 0.8 mi | J18: N/A | K18: N/A | L18: N/A | M18: 1430 | N18: N/A | O18: N/A | P18: N/A | Q18: N/A | R18: N/A | S18: 2005 | T18: N/A | U18: N/A | V18: Varies | W18: Varies | X18: Varies | Y18: Varies | Z18: HIGH | AA18: Market Rate Comp #1: No income restrictions, 2005 vintage, Ennis TX 75119. 2BD $1,430 (2BD only — no 4BD market rate units available in this market) | AB18: Apartments.com verified, May 2026
A19: 2 | B19: MARKET RATE | C19: Silverton Village | E19: 3700 Fm-85 | F19: Ennis | G19: TX | H19: 75119 | I19: 1.2 mi | J19: N/A | K19: N/A | L19: N/A | M19: 1497 | N19: N/A | O19: N/A | P19: N/A | Q19: N/A | R19: N/A | S19: 2010 | T19: N/A | U19: N/A | V19: Varies | W19: Varies | X19: Varies | Y19: Varies | Z19: HIGH | AA19: Market Rate Comp #2: No income restrictions, 2010 vintage, Ennis TX 75119. 2BD $1,497 (2BD only — no 4BD market rate units available in this market) | AB19: https://www.rentcafe.com/apartments-for-rent/us/tx/waxahachie/
A20: 3 | B20: MARKET RATE | C20: The Willows | E20: 2300 Yorkstown Dr | F20: Ennis | G20: TX | H20: 75119 | I20: 1.5 mi | J20: N/A | K20: N/A | L20: N/A | M20: 1424 | N20: N/A | O20: N/A | P20: N/A | Q20: N/A | R20: N/A | S20: 2008 | T20: N/A | U20: N/A | V20: Varies | W20: Varies | X20: Varies | Y20: Varies | Z20: MODERATE-HIGH | AA20: Market Rate Comp #3: No income restrictions, 2008 vintage, Ennis TX 75119. 2BD $1,424 (2BD only — no 4BD market rate units available in this market) | AB20: https://www.rentcafe.com/apartments-for-rent/us/tx/corsicana/
A21: 4 | B21: MARKET RATE | C21: Spyglass of Ennis | E21: 1803 W Ennis Ave | F21: Ennis | G21: TX | H21: 75119 | I21: 0.9 mi | J21: N/A | K21: N/A | L21: N/A | M21: 1559 | N21: N/A | O21: N/A | P21: N/A | Q21: N/A | R21: N/A | S21: 2012 | T21: N/A | U21: N/A | V21: Varies | W21: Varies | X21: Varies | Y21: Varies | Z21: MODERATE-HIGH | AA21: Market Rate Comp #4: No income restrictions, 2012 vintage, Ennis TX 75119. 2BD $1,559 (2BD only — no 4BD market rate units available in this market) | AB21: https://www.rentcafe.com/apartments-for-rent/us/tx/mansfield/
A22: 5 | B22: MARKET RATE | C22: Townhouse Apartments | E22: 1001 Biloxi Dr | F22: Ennis | G22: TX | H22: 75119 | I22: 1.1 mi | J22: N/A | K22: N/A | L22: N/A | M22: 1505 | N22: N/A | O22: N/A | P22: N/A | Q22: N/A | R22: N/A | S22: 2000 | T22: N/A | U22: N/A | V22: N/A | W22: N/A | X22: N/A | Y22: N/A | Z22: HIGH | AA22: Market Rate Comp #5: No income restrictions, 2000 vintage, Ennis TX 75119. 2BD $1,505 (2BD only — no 4BD market rate units available in this market) | AB22: Apartments.com verified, May 2026
A23: 6 | B23: MARKET RATE | C23: Emerald Garden Apartments | E23: 901 N I-45 | F23: Ennis | G23: TX | H23: 75119 | I23: 1.8 mi | J23: N/A | K23: N/A | L23: N/A | M23: 1328 | N23: N/A | O23: N/A | P23: N/A | Q23: N/A | R23: N/A | S23: 2003 | T23: N/A | U23: N/A | V23: N/A | W23: N/A | X23: N/A | Y23: N/A | Z23: HIGH | AA23: Market Rate Comp #6: No income restrictions, 2003 vintage, Ennis TX 75119. 2BD $1,328 (2BD only — no 4BD market rate units available in this market) | AB23: Apartments.com verified, May 2026
A24: — | B24: BENCHMARK | C24: FY2026 FMR — Ellis County, TX (Dallas-Fort Worth MSA) | E24: N/A | F24: Ennis | G24: TX | H24: N/A | I24: N/A | J24: $1,931 | K24: $1,931 | L24: $1,931 | M24: N/A | N24: $2,810 | O24: $2,810 | P24: $2,810 | Q24: N/A | R24: N/A | S24: N/A | T24: N/A | U24: N/A | V24: N/A | W24: N/A | X24: N/A | Y24: N/A | Z24: BENCHMARK | AA24: HUD FMR for Ellis County, TX (Dallas-Fort Worth MSA), FY2026. | AB24: HUD FMR Database (huduser.gov)
A25: — | B25: BENCHMARK | C25: Metro Market Avg — Ennis, TX (May 2026) | E25: N/A | F25: Ennis | G25: TX | H25: N/A | I25: N/A | J25: 1457 | K25: 1457 | L25: 1457 | M25: 1457 | N25: N/A | O25: N/A | P25: N/A | Q25: N/A | R25: N/A | S25: N/A | T25: N/A | U25: N/A | V25: N/A | W25: N/A | X25: N/A | Y25: N/A | Z25: BENCHMARK | AA25: Live Market Average from 6 comps, May 2026. 2BD avg $1,457 (2BD only — limited 4BD market rate data). | AB25: Apartments.com live data, Apr 30, 2026
A27: COLOR KEY: GREEN = Subject Property | TEAL = Affordable/Income-Restricted Comp | BLUE = Market-Rate Comp | LIGHT BLUE = FMR Benchmark | YELLOW = Market Average | ORANGE = Actual Rent
A29: CURRENT RENT vs. MARKET AVERAGE
A30: Market Average = Avg of Actual Advertised Rents from 6 Market-Rate Comps (Apartments.com)
B31: Current Rents | C31: Market Avg | E31: Difference
A32: 2BD | B32: ='Current Rents'!E20 -> 964 | C32: 1457 | E32: ='Current Rents'!F16-1457 -> -384 | F32: =IF(E32<-75,"LOOK INTO INCREASING THE RENT!","") -> LOOK INTO INCREASING THE RENT!
A33: 4BD | B33: ='Current Rents'!G20 -> 1221 | C33: N/A | E33: =B33-C33 -> #VALUE! | F33: =IF(E33<-75,"LOOK INTO INCREASING THE RENT!","") -> #VALUE!

Sheet 38 - Lexington
A1: RENT COMPARABLES ANALYSIS — Lexington Arms | AA1: ID: 38
A2: 418 Lexington Dr, Waxahachie, TX 75165 | 61 units | LIHTC
A3: Data as of June 2026 | Sources: CoStar, Apartments.com, HUD, Zillow
A4: COLUMN GUIDE — Income-restricted rent limits (50% AMI, 60% AMI), HUD Fair Market Rent (FMR), and Actual Advertised Rent for each bedroom size.
A5: Rank | B5: Type | C5: Property Name | E5: Address | F5: City | G5: St | H5: ZIP | I5: Distance | J5: 2BD 50% AMI | K5: 2BD 60% AMI | L5: 2BD FMR | M5: 2BD - Actual | N5: 4BD 50% AMI | O5: 4BD 60% AMI | P5: 4BD FMR | Q5: 4BD - Actual | R5: Units | S5: Yr Built | T5: Yr Diff | U5: Utils Incl. | V5: Pet Friendly | W5: Gated | X5: Pool | Y5: W/D In-Unit | Z5: Competition Level | AA5: Notes / Why Competitive | AB5: Data Source
A6: ★ | B6: SUBJECT | C6: Lexington Arms (SUBJECT) | E6: 418 Lexington Dr | F6: Waxahachie | G6: TX | H6: 75165 | I6: 0.0 mi | J6: $4,400 | K6: $5,280 | L6: $1,931 | M6: ='Current Rents'!E20 -> 964 | N6: $5,279 | O6: $6,335 | P6: $2,810 | Q6: ='Current Rents'!G20 -> 1221 | R6: 61 | S6: 1997 | T6: 0 | U6: No | V6: No | W6: No | X6: No | Y6: No | Z6: N/A
A7: 1 | B7: AFFORDABLE | C7: Breckenridge Village | E7: 2001A Floyd St | F7: Ennis | G7: TX | H7: 75119 | I7: 12.8 mi | J7: $4,400 | K7: $5,280 | L7: $1,931 | M7: Not Listed | N7: $5,279 | O7: $6,335 | P7: $2,810 | Q7: Not Listed | R7: 66 | S7: 1997 | T7: 0 | U7: Yes | V7: No | W7: No | X7: No | Y7: No | Z7: HIGH | AA7: Affordable Comp #1: LIHTC property, 1997 vintage (0 yr diff), 66 units, 12.8 mi from subject. Same income-eligible renter pool. | AB7: HUD LIHTC Database (huduser.gov)
A8: 2 | B8: AFFORDABLE | C8: Sherwood Arms Apts | E8: 213 N Val Verde Cir | F8: Keene | G8: TX | H8: 76059 | I8: 28.1 mi | J8: $4,400 | K8: $5,280 | L8: $1,931 | M8: Not Listed | N8: $5,279 | O8: $6,335 | P8: $2,810 | Q8: Not Listed | R8: 56 | S8: 1997 | T8: 0 | U8: Yes | V8: No | W8: No | X8: No | Y8: No | Z8: MODERATE-HIGH | AA8: Affordable Comp #2: LIHTC property, 1997 vintage (0 yr diff), 56 units, 28.1 mi from subject. Same income-eligible renter pool. | AB8: HUD LIHTC Database (huduser.gov)
A9: 3 | B9: AFFORDABLE | C9: Creekside Terrace Apts | E9: 1000 E Burnett St | F9: Ennis | G9: TX | H9: 75119 | I9: 14.3 mi | J9: $4,400 | K9: $5,280 | L9: $1,931 | M9: $1,270 | N9: $5,279 | O9: $6,335 | P9: $2,810 | Q9: $1,650 | R9: 80 | S9: 1998 | T9: 1 | U9: Yes | V9: No | W9: No | X9: No | Y9: No | Z9: HIGH | AA9: Affordable Comp #3: LIHTC property, 1998 vintage (1 yr diff), 80 units, 14.3 mi from subject. Same income-eligible renter pool. | AB9: HUD LIHTC Database (huduser.gov)
A10: 4 | B10: AFFORDABLE | C10: Hillcrest House | E10: 834 N Marsalis Ave | F10: Dallas | G10: TX | H10: 75203 | I10: 25.7 mi | J10: $4,400 | K10: $5,280 | L10: $1,931 | M10: Not Listed | N10: $5,279 | O10: $6,335 | P10: $2,810 | Q10: Not Listed | R10: 64 | S10: 1996 | T10: 1 | U10: Yes | V10: No | W10: No | X10: No | Y10: No | Z10: MODERATE-HIGH | AA10: Affordable Comp #4: LIHTC property, 1996 vintage (1 yr diff), 64 units, 25.7 mi from subject. Same income-eligible renter pool. | AB10: HUD LIHTC Database (huduser.gov)
A11: 5 | B11: AFFORDABLE
A12: 1 | B12: MARKET RATE | C12: Bridgepoint | D12: COMPETITION | E12: 2200 Brown St | F12: Waxahachie | G12: TX | H12: 75165 | I12: 1.5 mi | J12: N/A | K12: N/A | L12: N/A | M12: 1247 | N12: N/A | O12: N/A | P12: N/A | Q12: N/A (Market Rate) | R12: N/A | S12: 2015 | T12: N/A | U12: Varies | V12: Varies | W12: Varies | X12: Varies | Y12: Varies | Z12: HIGH | AA12: Market Rate Comp #1: No income restrictions, 1997 vintage (0 yr diff), N/A units, N/A from subject. Shows market-rate rents vs. affordable housing discount. | AB12: HUD FY2026 FMR - Ellis County, TX (limited market rate listings in Waxahachie)
A13: 2 | B13: MARKET RATE | C13: Oxford at Crossroads Centre | E13: 411 Alliance Blvd | F13: Waxahachie | G13: TX | H13: 75165 | I13: 2.0 mi | J13: N/A | K13: N/A | L13: N/A | M13: 1525 | N13: N/A | O13: N/A | P13: N/A | Q13: N/A (Market Rate) | R13: N/A | S13: 2018 | T13: N/A | U13: Varies | V13: Varies | W13: Varies | X13: Varies | Y13: Varies | Z13: HIGH | AA13: Market Rate Comp #2: No income restrictions, 1999 vintage (2 yr diff), 66 units, 12.0 mi from subject. Shows market-rate rents vs. affordable housing discount. | AB13: https://www.rentcafe.com/apartments-for-rent/us/tx/ennis/
A14: 3 | B14: MARKET RATE | C14: Emory on Grand | E14: 1831 John Arden Dr | F14: Waxahachie | G14: TX | H14: 75165 | I14: 1.8 mi | J14: N/A | K14: N/A | L14: N/A | M14: 1395 | N14: N/A | O14: N/A | P14: N/A | Q14: N/A (Market Rate) | R14: N/A | S14: 2016 | T14: N/A | U14: Varies | V14: Varies | W14: Varies | X14: Varies | Y14: Varies | Z14: HIGH | AA14: Market Rate Comp #3: No income restrictions, 2000 vintage (3 yr diff), 80 units, 15.0 mi from subject. Shows market-rate rents vs. affordable housing discount. | AB14: https://www.rentcafe.com/apartments-for-rent/us/tx/midlothian/
A15: 4 | B15: MARKET RATE | C15: Blue Lake Villas | E15: 155 Lakeside Dr | F15: Waxahachie | G15: TX | H15: 75165 | I15: 2.2 mi | J15: N/A | K15: N/A | L15: N/A | M15: 1349 | N15: N/A | O15: N/A | P15: N/A | Q15: N/A (Market Rate) | R15: N/A | S15: 2012 | T15: N/A | U15: Varies | V15: Varies | W15: Varies | X15: Varies | Y15: Varies | Z15: HIGH | AA15: Market Rate Comp #4: No income restrictions, 1998 vintage (1 yr diff), 72 units, 10.0 mi from subject. Shows market-rate rents vs. affordable housing discount. | AB15: https://www.rentcafe.com/apartments-for-rent/us/tx/red-oak/
A16: 5 | B16: MARKET RATE | C16: Hunter's Cove Apartments | E16: 1250 W Highway 287 Bypass | F16: Waxahachie | G16: TX | H16: 75165 | I16: 1.2 mi | J16: N/A | K16: N/A | L16: N/A | M16: 1599 | N16: N/A | O16: N/A | P16: N/A | Q16: N/A (Market Rate) | R16: N/A | S16: 2014 | T16: N/A | U16: Varies | V16: Varies | W16: N/A | X16: N/A | Y16: N/A | Z16: BENCHMARK | AA16: BENCHMARK — HUD Fair Market Rent (FMR) for Dallas-Fort Worth MSA, effective FY2026. The FMR represents the 40th percentile of gross rents for standard-quality units in this metro area, as published annually by HUD. It is used here as the market reference point. LIHTC-restricted rents are typically 40–70% of FMR depending on the AMI tier. | AB16: HUD FMR Database (huduser.gov)
A17: 6 | B17: MARKET RATE | C17: Bent Tree Townhomes | E17: 1721 S IH-35 E | F17: Waxahachie | G17: TX | H17: 75165 | I17: 1.0 mi | J17: N/A | K17: N/A | L17: N/A | M17: 1289 | N17: N/A | O17: N/A | P17: N/A | Q17: N/A (Market Rate) | R17: N/A | S17: 2010 | T17: N/A | U17: Varies | V17: Varies | W17: N/A | X17: N/A | Y17: N/A | Z17: BENCHMARK | AA17: BENCHMARK — Estimated Metro Market Average for Waxahachie, calculated at approximately 110% of the HUD FMR. This represents the typical asking rent for unrestricted market-rate units in this area. The gap between this figure and the affordable comp rents above shows the affordability discount our properties provide. | AB17: HUD FMR + Market Estimate
A18: 7 | B18: MARKET RATE | J18: N/A | K18: N/A | L18: N/A | N18: N/A | O18: N/A | P18: N/A
A19: — | B19: BENCHMARK | C19: FY2026 FMR — Dallas-Fort Worth MSA | E19: N/A | F19: Waxahachie | G19: TX | L19: $1,931 | P19: $2,810
A20: — | B20: BENCHMARK | C20: Metro Market Avg — Waxahachie (Apartments.com) | E20: N/A | F20: Waxahachie | G20: TX | M20: 1401
A22: COLOR KEY: GREEN = Subject Property | LIGHT GREEN = Affordable Comps (LIHTC/Section 8/HUD) | LIGHT BLUE = Market Rate Comps | ORANGE = Actual Advertised Rent
A24: CURRENT RENT vs. MARKET AVERAGE
A25: Market Average = Avg of Actual Advertised Rents from Market-Rate Comps (Apartments.com)
B26: Current Rents | C26: Market Avg | E26: Difference
A27: 2BD | B27: ='Current Rents'!E20 -> 964 | C27: 1401 | E27: =B27-C27 -> -437 | F27: =IF(E27<-75,"LOOK INTO INCREASING THE RENT!","") -> LOOK INTO INCREASING THE RENT!
A28: 4BD | B28: ='Current Rents'!G20 -> 1221 | C28: N/A | E28: =B28-C28 -> #VALUE! | F28: =IF(E28<-75,"LOOK INTO INCREASING THE RENT!","") -> #VALUE!
A31: PMTS — Vouchers / FMR / UAP / NET
B32: MKT | C32: VCH | D32: FMR | E32: UAP | F32: NET
A33: 2BD | C33: ='Current Rents'!E20 -> 964 | D33: 1931
A34: 4BD | C34: ='Current Rents'!G20 -> 1221 | D34: 2810

Sheet 23 - Grace Townhomes
A1: RENT COMPARABLES ANALYSIS — Grace Townhomes | AE1: ID: 23
A2: 1212 Grace Circle, Ennis, TX 75119 | 112 units | LIHTC
A3: Data as of June 2026 | Sources: CoStar, Apartments.com, HUD, Zillow
A4: COLUMN GUIDE — Income-restricted rent limits (50% AMI, 60% AMI), HUD Fair Market Rent (FMR), and Actual Advertised Rent for each bedroom size.
A5: Rank | B5: Type | C5: Property Name | E5: Address | F5: City | G5: St | H5: ZIP | I5: Distance | J5: 1BD 50% AMI | K5: 1BD 60% AMI | L5: 1BD FMR | M5: 1BD - Actual | N5: 2BD 50% AMI | O5: 2BD 60% AMI | P5: 2BD FMR | Q5: 2BD - Actual | R5: 3BD 50% AMI | S5: 3BD 60% AMI | T5: 3BD FMR | U5: 3BD - Actual | V5: Units | W5: Yr Built | X5: Yr Diff | Y5: Utils Incl. | Z5: Pet Friendly | AA5: Gated | AB5: Pool | AC5: W/D In-Unit | AD5: Competition Level | AE5: Notes / Why Competitive | AF5: Data Source
A6: ★ | B6: SUBJECT | C6: Grace Townhomes (SUBJECT) | E6: 1212 Grace Circle | F6: Ennis | G6: TX | H6: 75119 | I6: 0.0 mi | J6: $3,668 | K6: $4,402 | L6: $1,411 | M6: ='Current Rents'!D21 -> — | N6: $4,400 | O6: $5,280 | P6: $1,931 | Q6: ='Current Rents'!E21 -> 964 | R6: $4,887 | S6: $5,865 | T6: $2,431 | U6: ='Current Rents'!F21 -> — | V6: 112 | W6: 2001 | X6: 0 | Y6: No | Z6: No | AA6: No | AB6: No | AC6: Yes | AD6: N/A
A7: 1 | B7: AFFORDABLE | C7: Villas Of Hickory Estates | E7: 3211 Hickory Tree Rd | F7: Balch Springs | G7: TX | H7: 75180 | I7: 27.4 mi | J7: $3,668 | K7: $4,402 | L7: $1,411 | M7: Not Listed | N7: $4,400 | O7: $5,280 | P7: $1,931 | Q7: Not Listed | R7: $4,887 | S7: $5,865 | T7: $2,431 | U7: Not Listed | V7: 128 | W7: 2001 | X7: 0 | Y7: Yes | Z7: No | AA7: No | AB7: No | AC7: No | AD7: MODERATE-HIGH | AE7: Affordable Comp #1: LIHTC property, 2001 vintage (0 yr diff), 128 units, 27.4 mi from subject. Same income-eligible renter pool. | AF7: HUD LIHTC Database (huduser.gov)
A8: 2 | B8: AFFORDABLE | C8: Ryans Crossing (Pemberton Place) | E8: 1509 Mlk Jr Blvd | F8: Marshall | G8: TX | I8: N/A | J8: $3,668 | K8: $4,402 | L8: $1,411 | M8: $867 | N8: $4,400 | O8: $5,280 | P8: $1,931 | Q8: $1,101 | R8: $4,887 | S8: $5,865 | T8: $2,431 | U8: $1,221 | V8: 112 | W8: 2002 | X8: 1 | Y8: Yes | Z8: No | AA8: No | AB8: No | AC8: No | AD8: MODERATE | AE8: Affordable Comp #2: LIHTC property, 2002 vintage (1 yr diff), 112 units, N/A from subject. Same income-eligible renter pool. | AF8: HUD LIHTC Database (huduser.gov)
A9: 3 | B9: AFFORDABLE | C9: May Road Apts | E9: 1488 May Cir | F9: Seagoville | G9: TX | I9: N/A | J9: $3,668 | K9: $4,402 | L9: $1,411 | M9: Not Listed | N9: $4,400 | O9: $5,280 | P9: $1,931 | Q9: Not Listed | R9: $4,887 | S9: $5,865 | T9: $2,431 | U9: Not Listed | V9: 81 | W9: 2001 | X9: 0 | Y9: Yes | Z9: No | AA9: No | AB9: No | AC9: No | AD9: MODERATE | AE9: Affordable Comp #3: LIHTC property, 2001 vintage (0 yr diff), 81 units, N/A from subject. Same income-eligible renter pool. | AF9: HUD LIHTC Database (huduser.gov)
A10: 4 | B10: AFFORDABLE | C10: Creekside Terrace Apts | E10: 1000 E Burnett St | F10: Ennis | G10: TX | H10: 75119 | I10: 0.7 mi | J10: $3,668 | K10: $4,402 | L10: $1,411 | M10: $1,150 | N10: $4,400 | O10: $5,280 | P10: $1,931 | Q10: $1,270 | R10: $4,887 | S10: $5,865 | T10: $2,431 | U10: $1,450 | V10: 80 | W10: 1998 | X10: 3 | Y10: Yes | Z10: No | AA10: No | AB10: No | AC10: No | AD10: HIGH | AE10: Affordable Comp #4: LIHTC property, 1998 vintage (3 yr diff), 80 units, 0.7 mi from subject. Same income-eligible renter pool. | AF10: HUD LIHTC Database (huduser.gov)
A11: 5 | B11: AFFORDABLE
A12: 1 | B12: MARKET RATE | C12: Silverton Village | D12: COMPETITION | E12: 3700 Fm-85 | F12: Ennis | G12: TX | H12: 75119 | I12: 1.2 mi | J12: N/A | K12: N/A | L12: N/A | M12: 867 | N12: N/A | O12: N/A | P12: N/A | Q12: 1497 | R12: N/A | S12: N/A | T12: N/A | U12: 1725 | V12: 100 | W12: 2003 | X12: 2 | Y12: Varies | Z12: Varies | AA12: Varies | AB12: Varies | AC12: Varies | AD12: HIGH | AE12: Market Rate Comp #1: No income restrictions, 2003 vintage (2 yr diff), 100 units, 1.8 mi from subject. Shows market-rate rents vs. affordable housing discount. | AF12: https://www.rentcafe.com/apartments-for-rent/us/tx/ennis/ryans-crossing/
A13: 2 | B13: MARKET RATE | C13: The Willows | E13: 2300 Yorkstown Dr | F13: Ennis | G13: TX | H13: 75119 | I13: 0.8 mi | J13: N/A | K13: N/A | L13: N/A | M13: 1074 | N13: N/A | O13: N/A | P13: N/A | Q13: 1424 | R13: N/A | S13: N/A | T13: N/A | U13: 1375 | V13: 88 | W13: 2000 | X13: 1 | Y13: Varies | Z13: Varies | AA13: Varies | AB13: Varies | AC13: Varies | AD13: HIGH | AE13: Market Rate Comp #2: No income restrictions, 2000 vintage (1 yr diff), 88 units, 12.5 mi from subject. Shows market-rate rents vs. affordable housing discount. | AF13: https://www.rentcafe.com/apartments-for-rent/us/tx/waxahachie/
A14: 3 | B14: MARKET RATE | C14: Spyglass of Ennis | E14: 1803 W Ennis Ave | F14: Ennis | G14: TX | H14: 75119 | I14: 1.5 mi | J14: N/A | K14: N/A | L14: N/A | M14: 1304 | N14: N/A | O14: N/A | P14: N/A | Q14: 1559 | R14: N/A | S14: N/A | T14: N/A | U14: 1325 | V14: 72 | W14: 1999 | X14: 2 | Y14: Varies | Z14: Varies | AA14: Varies | AB14: Varies | AC14: Varies | AD14: MODERATE-HIGH | AE14: Market Rate Comp #3: No income restrictions, 1999 vintage (2 yr diff), 72 units, 28.0 mi from subject. Shows market-rate rents vs. affordable housing discount. | AF14: https://www.rentcafe.com/apartments-for-rent/us/tx/corsicana/
A15: 4 | B15: MARKET RATE | C15: Townhouse Apartments | E15: 1001 Biloxi Dr | F15: Ennis | G15: TX | H15: 75119 | I15: 0.9 mi | J15: N/A | K15: N/A | L15: N/A | M15: 1014 | N15: N/A | O15: N/A | P15: N/A | Q15: 1505 | R15: N/A | S15: N/A | T15: N/A | U15: 1400 | V15: 80 | W15: 2002 | X15: 1 | Y15: Varies | Z15: Varies | AA15: Varies | AB15: Varies | AC15: Varies | AD15: MODERATE-HIGH | AE15: Market Rate Comp #4: No income restrictions, 2002 vintage (1 yr diff), 80 units, 18.0 mi from subject. Shows market-rate rents vs. affordable housing discount. | AF15: https://www.rentcafe.com/apartments-for-rent/us/tx/midlothian/
A16: 5 | B16: MARKET RATE | C16: Emerald Garden Apartments | E16: 901 N I-45 | F16: Ennis | G16: TX | H16: 75119 | I16: 1.1 mi | J16: N/A | K16: N/A | L16: N/A | M16: 1025 | N16: N/A | O16: N/A | P16: N/A | Q16: 1150 | R16: N/A | S16: N/A | T16: N/A | U16: 1600 | V16: N/A | W16: N/A | X16: N/A | Y16: N/A | Z16: N/A | AA16: N/A | AB16: N/A | AC16: N/A | AD16: BENCHMARK | AE16: BENCHMARK — HUD Fair Market Rent (FMR) for Dallas-Fort Worth MSA, effective FY2026. The FMR represents the 40th percentile of gross rents for standard-quality units in this metro area, as published annually by HUD. It is used here as the market reference point. LIHTC-restricted rents are typically 40–70% of FMR depending on the AMI tier. | AF16: HUD FMR Database (huduser.gov)
A17: 6 | B17: MARKET RATE | C17: Ennis Place Apartments | E17: 2000 N Kaufman St | F17: Ennis | G17: TX | H17: 75119 | I17: 0.7 mi | J17: N/A | K17: N/A | L17: N/A | M17: 999 | N17: N/A | O17: N/A | P17: N/A | Q17: N/A | R17: N/A | S17: N/A | T17: N/A | U17: N/A | V17: N/A | W17: N/A | X17: N/A | Y17: N/A | Z17: N/A | AA17: N/A | AB17: N/A | AC17: N/A | AD17: BENCHMARK | AE17: BENCHMARK — Estimated Metro Market Average for Ennis, calculated at approximately 110% of the HUD FMR. This represents the typical asking rent for unrestricted market-rate units in this area. The gap between this figure and the affordable comp rents above shows the affordability discount our properties provide. | AF17: HUD FMR + Market Estimate
A18: 7 | B18: MARKET RATE | J18: N/A | K18: N/A | L18: N/A | N18: N/A | O18: N/A | P18: N/A | R18: N/A | S18: N/A | T18: N/A
A19: — | B19: BENCHMARK | C19: FY2026 FMR — Dallas-Fort Worth MSA | E19: N/A | F19: Ennis | G19: TX | L19: $1,411 | P19: $1,931 | T19: $2,431
A20: — | B20: BENCHMARK | C20: Metro Market Avg — Ennis (Apartments.com) | E20: N/A | F20: Ennis | G20: TX | M20: 1047 | Q20: 1427 | U20: 1485
A22: COLOR KEY: GREEN = Subject Property | LIGHT GREEN = Affordable Comps (LIHTC/Section 8/HUD) | LIGHT BLUE = Market Rate Comps | ORANGE = Actual Advertised Rent
A24: CURRENT RENT vs. MARKET AVERAGE
A25: Market Average = Avg of Actual Advertised Rents from Market-Rate Comps (Apartments.com)
B26: Current Rents | C26: Market Avg | E26: Difference
A27: 1BD | B27: ='Current Rents'!D21 -> — | C27: 1047 | E27: =B27-C27 -> #VALUE! | F27: =IF(E27<-75,"LOOK INTO INCREASING THE RENT!","") -> #VALUE!
A28: 2BD | B28: ='Current Rents'!E21 -> 964 | C28: 1427 | E28: =B28-C28 -> -463 | F28: =IF(E28<-75,"LOOK INTO INCREASING THE RENT!","") -> LOOK INTO INCREASING THE RENT!
A29: 3BD | B29: ='Current Rents'!F21 -> — | C29: 1485 | E29: =B29-C29 -> #VALUE! | F29: =IF(E29<-75,"LOOK INTO INCREASING THE RENT!","") -> #VALUE!
A32: PMTS — Vouchers / FMR / UAP / NET
B33: MKT | C33: VCH | D33: FMR | E33: UAP | F33: NET
A34: 1BD | C34: ='Current Rents'!D21 -> — | D34: 1411
A35: 2BD | C35: ='Current Rents'!E21 -> 964 | D35: 1931
A36: 3BD | C36: ='Current Rents'!F21 -> — | D36: 2431

Sheet 46 - Grove Park
A1: RENT COMPARABLES ANALYSIS — Grove Park Terrace | AE1: ID: 46
A2: 400 Peters St, Waxahachie, TX 75165 | 60 units | Layered HUD/LIHTC
A3: Data as of June 2026 | Sources: CoStar, Apartments.com, HUD, Zillow
A4: COLUMN GUIDE — Income-restricted rent limits (50% AMI, 60% AMI), HUD Fair Market Rent (FMR), and Actual Advertised Rent for each bedroom size.
A5: Rank | B5: Type | C5: Property Name | E5: Address | F5: City | G5: St | H5: ZIP | I5: Distance | J5: 1BD 50% AMI | K5: 1BD 60% AMI | L5: 1BD FMR | M5: 1BD - Actual | N5: 2BD 50% AMI | O5: 2BD 60% AMI | P5: 2BD FMR | Q5: 2BD - Actual | R5: 3BD 50% AMI | S5: 3BD 60% AMI | T5: 3BD FMR | U5: 3BD - Actual | V5: Units | W5: Yr Built | X5: Yr Diff | Y5: Utils Incl. | Z5: Pet Friendly | AA5: Gated | AB5: Pool | AC5: W/D In-Unit | AD5: Competition Level | AE5: Notes / Why Competitive | AF5: Data Source
A6: ★ | B6: SUBJECT | C6: Grove Park Terrace (SUBJECT) | E6: 400 Peters St | F6: Waxahachie | G6: TX | H6: 75165 | I6: 0.0 mi | J6: $3,668 | K6: $4,402 | L6: $1,411 | M6: ='Current Rents'!D22 -> 1198 | N6: $4,400 | O6: $5,280 | P6: $1,931 | Q6: ='Current Rents'!E22 -> 1430 | R6: $4,887 | S6: $5,865 | T6: $2,431 | U6: ='Current Rents'!F22 -> 1656 | V6: 60 | W6: 1998 | X6: 0 | Y6: Partial | Z6: No | AA6: No | AB6: No | AC6: No | AD6: N/A
A7: 1 | B7: AFFORDABLE | C7: Lexington Arms | E7: 418 Lexington Dr | F7: Waxahachie | G7: TX | H7: 75165 | I7: 1.6 mi | J7: $3,668 | K7: $4,402 | L7: $1,411 | M7: Not Listed | N7: $4,400 | O7: $5,280 | P7: $1,931 | Q7: Not Listed | R7: $4,887 | S7: $5,865 | T7: $2,431 | U7: Not Listed | V7: 61 | W7: 1997 | X7: 1 | Y7: Yes | Z7: No | AA7: No | AB7: No | AC7: No | AD7: HIGH | AE7: Affordable Comp #1: LIHTC property, 1997 vintage (1 yr diff), 61 units, 1.6 mi from subject. Same income-eligible renter pool. | AF7: HUD LIHTC Database (huduser.gov)
A8: 2 | B8: AFFORDABLE | C8: Creekside Terrace Apts | E8: 1000 E Burnett St | F8: Ennis | G8: TX | H8: 75119 | I8: 14.3 mi | J8: $3,668 | K8: $4,402 | L8: $1,411 | M8: $1,150 | N8: $4,400 | O8: $5,280 | P8: $1,931 | Q8: $1,270 | R8: $4,887 | S8: $5,865 | T8: $2,431 | U8: $1,450 | V8: 80 | W8: 1998 | X8: 0 | Y8: Yes | Z8: No | AA8: No | AB8: No | AC8: No | AD8: HIGH | AE8: Affordable Comp #2: LIHTC property, 1998 vintage (0 yr diff), 80 units, 14.3 mi from subject. Same income-eligible renter pool. | AF8: HUD LIHTC Database (huduser.gov)
A9: 3 | B9: AFFORDABLE | C9: Breckenridge Village | E9: 2001A Floyd St | F9: Ennis | G9: TX | H9: 75119 | I9: 12.8 mi | J9: $3,668 | K9: $4,402 | L9: $1,411 | M9: Not Listed | N9: $4,400 | O9: $5,280 | P9: $1,931 | Q9: Not Listed | R9: $4,887 | S9: $5,865 | T9: $2,431 | U9: Not Listed | V9: 66 | W9: 1997 | X9: 1 | Y9: Yes | Z9: No | AA9: No | AB9: No | AC9: No | AD9: HIGH | AE9: Affordable Comp #3: LIHTC property, 1997 vintage (1 yr diff), 66 units, 12.8 mi from subject. Same income-eligible renter pool. | AF9: HUD LIHTC Database (huduser.gov)
A10: 4 | B10: AFFORDABLE | C10: Treymore North Apts | E10: 4144 Office Pkwy | F10: Dallas | G10: TX | H10: 75204 | I10: 29.1 mi | J10: $3,668 | K10: $4,402 | L10: $1,411 | M10: Not Listed | N10: $4,400 | O10: $5,280 | P10: $1,931 | Q10: Not Listed | R10: $4,887 | S10: $5,865 | T10: $2,431 | U10: Not Listed | V10: 70 | W10: 1998 | X10: 0 | Y10: Yes | Z10: No | AA10: No | AB10: No | AC10: No | AD10: MODERATE-HIGH | AE10: Affordable Comp #4: LIHTC property, 1998 vintage (0 yr diff), 70 units, 29.1 mi from subject. Same income-eligible renter pool. | AF10: HUD LIHTC Database (huduser.gov)
A11: 5 | B11: AFFORDABLE
A12: 1 | B12: MARKET RATE | C12: Place at North Grove | D12: COMPETITION | E12: 600 E North Grove Blvd | F12: Waxahachie | G12: TX | H12: 75165 | I12: 1.0 mi | J12: N/A | K12: N/A | L12: N/A | M12: 1254 | N12: N/A | O12: N/A | P12: N/A | Q12: 1998 | R12: N/A | S12: N/A | T12: N/A | U12: 1450 | V12: N/A | W12: 1998 | X12: 0 | Y12: Varies | Z12: Varies | AA12: Varies | AB12: Varies | AC12: Varies | AD12: HIGH | AE12: Market Rate Comp #1: No income restrictions, 1998 vintage (0 yr diff), N/A units, N/A from subject. Shows market-rate rents vs. affordable housing discount. | AF12: HUD FY2026 FMR - Ellis County, TX
A13: 2 | B13: MARKET RATE | C13: The Village at Waxahachie | E13: 131 Village Pky | F13: Waxahachie | G13: TX | H13: 75165 | I13: 1.3 mi | J13: N/A | K13: N/A | L13: N/A | M13: 1447 | N13: N/A | O13: N/A | P13: N/A | Q13: 1970 | R13: N/A | S13: N/A | T13: N/A | U13: 1400 | V13: 80 | W13: 1997 | X13: 1 | Y13: Varies | Z13: Varies | AA13: Varies | AB13: Varies | AC13: Varies | AD13: HIGH | AE13: Market Rate Comp #2: No income restrictions, 1997 vintage (1 yr diff), 80 units, 12.0 mi from subject. Shows market-rate rents vs. affordable housing discount. | AF13: https://www.rentcafe.com/apartments-for-rent/us/tx/ennis/
A14: 3 | B14: MARKET RATE | C14: Bridgepoint | E14: 2200 Brown St | F14: Waxahachie | G14: TX | H14: 75165 | I14: 0.9 mi | J14: N/A | K14: N/A | L14: N/A | M14: 1136 | N14: N/A | O14: N/A | P14: N/A | Q14: 1247 | R14: N/A | S14: N/A | T14: N/A | U14: 1475 | V14: 72 | W14: 2000 | X14: 2 | Y14: Varies | Z14: Varies | AA14: Varies | AB14: Varies | AC14: Varies | AD14: HIGH | AE14: Market Rate Comp #3: No income restrictions, 2000 vintage (2 yr diff), 72 units, 15.0 mi from subject. Shows market-rate rents vs. affordable housing discount. | AF14: https://www.rentcafe.com/apartments-for-rent/us/tx/midlothian/
A15: 4 | B15: MARKET RATE | C15: The Hamilton at Garden Valley | E15: 880 Garden Valley Pky | F15: Waxahachie | G15: TX | H15: 75165 | I15: 1.8 mi | J15: N/A | K15: N/A | L15: N/A | M15: 1215 | N15: N/A | O15: N/A | P15: N/A | Q15: 2105 | R15: N/A | S15: N/A | T15: N/A | U15: 1475 | V15: 64 | W15: 1997 | X15: 1 | Y15: Varies | Z15: Varies | AA15: Varies | AB15: Varies | AC15: Varies | AD15: HIGH | AE15: Market Rate Comp #4: No income restrictions, 1997 vintage (1 yr diff), 64 units, 12.0 mi from subject. Shows market-rate rents vs. affordable housing discount. | AF15: https://www.rentcafe.com/apartments-for-rent/us/tx/midlothian/
A16: 5 | B16: MARKET RATE | C16: Oxford at Crossroads Centre | E16: 411 Alliance Blvd | F16: Waxahachie | G16: TX | H16: 75165 | I16: 1.5 mi | J16: N/A | K16: N/A | L16: N/A | M16: 1199 | N16: N/A | O16: N/A | P16: N/A | Q16: 1525 | R16: N/A | S16: N/A | T16: N/A | U16: 2250 | V16: N/A | W16: N/A | X16: N/A | Y16: N/A | Z16: N/A | AA16: N/A | AB16: N/A | AC16: N/A | AD16: BENCHMARK | AE16: BENCHMARK — HUD Fair Market Rent (FMR) for Dallas-Fort Worth MSA, effective FY2026. The FMR represents the 40th percentile of gross rents for standard-quality units in this metro area, as published annually by HUD. It is used here as the market reference point. LIHTC-restricted rents are typically 40–70% of FMR depending on the AMI tier. | AF16: HUD FMR Database (huduser.gov)
A17: 6 | B17: MARKET RATE | C17: Park Place Apartments | E17: 240 Park Place Blvd | F17: Waxahachie | G17: TX | H17: 75165 | I17: 1.2 mi | J17: N/A | K17: N/A | L17: N/A | M17: 1285 | N17: N/A | O17: N/A | P17: N/A | Q17: 1659 | R17: N/A | S17: N/A | T17: N/A | U17: N/A | V17: N/A | W17: N/A | X17: N/A | Y17: N/A | Z17: N/A | AA17: N/A | AB17: N/A | AC17: N/A | AD17: BENCHMARK | AE17: BENCHMARK — Estimated Metro Market Average for Waxahachie, calculated at approximately 110% of the HUD FMR. This represents the typical asking rent for unrestricted market-rate units in this area. The gap between this figure and the affordable comp rents above shows the affordability discount our properties provide. | AF17: HUD FMR + Market Estimate
A18: 7 | B18: MARKET RATE | J18: N/A | K18: N/A | L18: N/A | N18: N/A | O18: N/A | P18: N/A | R18: N/A | S18: N/A | T18: N/A
A19: — | B19: BENCHMARK | C19: FY2026 FMR — Dallas-Fort Worth MSA | E19: N/A | F19: Waxahachie | G19: TX | L19: $1,411 | P19: $1,931 | T19: $2,431
A20: — | B20: BENCHMARK | C20: Metro Market Avg — Waxahachie (Apartments.com) | E20: N/A | F20: Waxahachie | G20: TX | M20: 1256 | Q20: 1751 | U20: 1610
A22: COLOR KEY: GREEN = Subject Property | LIGHT GREEN = Affordable Comps (LIHTC/Section 8/HUD) | LIGHT BLUE = Market Rate Comps | ORANGE = Actual Advertised Rent
A24: CURRENT RENT vs. MARKET AVERAGE
A25: Market Average = Avg of Actual Advertised Rents from Market-Rate Comps (Apartments.com)
B26: Current Rents | C26: Market Avg | E26: Difference
A27: 1BD | B27: ='Current Rents'!D22 -> 1198 | C27: 1256 | E27: =B27-C27 -> -58 | F27: =IF(E27<-75,"LOOK INTO INCREASING THE RENT!","")
A28: 2BD | B28: ='Current Rents'!E22 -> 1430 | C28: 1751 | E28: =B28-C28 -> -321 | F28: =IF(E28<-75,"LOOK INTO INCREASING THE RENT!","") -> LOOK INTO INCREASING THE RENT!
A29: 3BD | B29: ='Current Rents'!F22 -> 1656 | C29: 1610 | E29: =B29-C29 -> 46 | F29: =IF(E29<-75,"LOOK INTO INCREASING THE RENT!","")
A32: PMTS — Vouchers / FMR / UAP / NET
B33: MKT | C33: VCH | D33: FMR | E33: UAP | F33: NET
A34: 1BD | C34: ='Current Rents'!D22 -> 1198 | D34: 1411
A35: 2BD | C35: ='Current Rents'!E22 -> 1430 | D35: 1931
A36: 3BD | C36: ='Current Rents'!F22 -> 1656 | D36: 2431

Sheet 60 - La Promesa
A1: RENT COMPARABLES ANALYSIS — La Promesa | AA1: ID: 60
A2: Odessa, Odessa, TX 79762 | 136 units | Layered HUD/LIHTC
A3: Data as of June 2026 | Sources: CoStar, Apartments.com, HUD, Zillow
A4: COLUMN GUIDE — Income-restricted rent limits (50% AMI, 60% AMI), HUD Fair Market Rent (FMR), and Actual Advertised Rent for each bedroom size.
A5: Rank | B5: Type | C5: Property Name | E5: Address | F5: City | G5: St | H5: ZIP | I5: Distance | J5: 2BD 50% AMI | K5: 2BD 60% AMI | L5: 2BD FMR | M5: 2BD - Actual | N5: 3BD 50% AMI | O5: 3BD 60% AMI | P5: 3BD FMR | Q5: 3BD - Actual | R5: Units | S5: Yr Built | T5: Yr Diff | U5: Utils Incl. | V5: Pet Friendly | W5: Gated | X5: Pool | Y5: W/D In-Unit | Z5: Competition Level | AA5: Notes / Why Competitive | AB5: Data Source
A6: ★ | B6: SUBJECT | C6: La Promesa (SUBJECT) | E6: Odessa | F6: Odessa | G6: TX | H6: 79762 | I6: 0.0 mi | J6: $3,529 | K6: $4,235 | L6: $1,254 | M6: ='Current Rents'!E23 -> 1450 | N6: $3,920 | O6: $4,705 | P6: $1,573 | Q6: ='Current Rents'!F23 -> 1700 | R6: 136 | S6: 1978 | T6: 0 | U6: Yes | V6: No | W6: No | X6: No | Y6: No | Z6: N/A
A7: 1 | B7: AFFORDABLE | C7: Skyline Village | F7: Mckinney | G7: TX | I7: N/A | J7: $3,529 | K7: $4,235 | L7: $1,254 | M7: Not Listed | N7: $3,920 | O7: $4,705 | P7: $1,573 | Q7: Not Listed | R7: 168 | S7: 1988 | T7: 10 | U7: Yes | V7: No | W7: No | X7: No | Y7: No | Z7: MODERATE | AA7: Affordable Comp #1: LIHTC property, 1988 vintage (10 yr diff), 168 units, N/A from subject. Same income-eligible renter pool. | AB7: HUD LIHTC Database (huduser.gov)
A8: 2 | B8: AFFORDABLE | C8: Orange Grove Apts | E8: Rr 1 | F8: Newton | G8: TX | H8: 75966 | I8: N/A | J8: $3,529 | K8: $4,235 | L8: $1,254 | M8: Not Listed | N8: $3,920 | O8: $4,705 | P8: $1,573 | Q8: Not Listed | R8: 24 | S8: 1987 | T8: 9 | U8: Yes | V8: No | W8: No | X8: No | Y8: No | Z8: MODERATE | AA8: Affordable Comp #2: LIHTC property, 1987 vintage (9 yr diff), 24 units, N/A from subject. Same income-eligible renter pool. | AB8: HUD LIHTC Database (huduser.gov)
A9: 3 | B9: AFFORDABLE | C9: Victoria Housing | E9: 2817 Yanez Ave | F9: Mission | G9: TX | I9: N/A | J9: $3,529 | K9: $4,235 | L9: $1,254 | M9: Not Listed | N9: $3,920 | O9: $4,705 | P9: $1,573 | Q9: Not Listed | R9: 1 | S9: 1987 | T9: 9 | U9: Yes | V9: No | W9: No | X9: No | Y9: No | Z9: MODERATE | AA9: Affordable Comp #3: LIHTC property, 1987 vintage (9 yr diff), 1 units, N/A from subject. Same income-eligible renter pool. | AB9: HUD LIHTC Database (huduser.gov)
A10: 4 | B10: AFFORDABLE | C10: Springhill Apts | E10: 4830 Ray Bon Dr | F10: San Antonio | G10: TX | H10: 78218 | I10: 287.1 mi | J10: $3,529 | K10: $4,235 | L10: $1,254 | M10: Not Listed | N10: $3,920 | O10: $4,705 | P10: $1,573 | Q10: Not Listed | R10: 132 | S10: 1987 | T10: 9 | U10: Yes | V10: No | W10: No | X10: No | Y10: No | Z10: LOW | AA10: Affordable Comp #4: LIHTC property, 1987 vintage (9 yr diff), 132 units, 287.1 mi from subject. Same income-eligible renter pool. | AB10: HUD LIHTC Database (huduser.gov)
A11: 5 | B11: AFFORDABLE
A12: 1 | B12: MARKET RATE | C12: Madison Square | D12: COMPETITION | E12: 2201 Rocky Lane Rd | F12: Odessa | G12: TX | H12: 79762 | I12: 2.1 mi | J12: N/A | K12: N/A | L12: N/A | M12: 1220 | N12: N/A | O12: N/A | P12: N/A | Q12: 1600 | R12: N/A | S12: 1978 | T12: 0 | U12: Varies | V12: Varies | W12: Varies | X12: Varies | Y12: Varies | Z12: HIGH | AA12: Market Rate Comp #1: No income restrictions, 1978 vintage (0 yr diff), N/A units, N/A from subject. Shows market-rate rents vs. affordable housing discount. | AB12: HUD FY2026 FMR - Ector County, TX (limited market rate listings for 1968-1988 vintage)
A13: 2 | B13: MARKET RATE | C13: Alara | E13: 6501 Eastridge Rd | F13: Odessa | G13: TX | H13: 79762 | I13: 3.5 mi | J13: N/A | K13: N/A | L13: N/A | M13: 1205 | N13: N/A | O13: N/A | P13: N/A | Q13: 1545 | R13: N/A | S13: 1975 | T13: 3 | U13: Varies | V13: Varies | W13: Varies | X13: Varies | Y13: Varies | Z13: HIGH | AA13: Market Rate Comp #2: No income restrictions, 1975 vintage (3 yr diff), N/A units, N/A from subject. Shows market-rate rents vs. affordable housing discount. | AB13: HUD FY2026 FMR - Ector County, TX
A14: 3 | B14: MARKET RATE | C14: Westwinds Village | E14: 4900 E University Blvd | F14: Odessa | G14: TX | H14: 79762 | I14: 1.8 mi | J14: N/A | K14: N/A | L14: N/A | M14: 1045 | N14: N/A | O14: N/A | P14: N/A | Q14: 1550 | R14: N/A | S14: 1980 | T14: 2 | U14: Varies | V14: Varies | W14: Varies | X14: Varies | Y14: Varies | Z14: HIGH | AA14: Market Rate Comp #3: No income restrictions, 1980 vintage (2 yr diff), N/A units, N/A from subject. Shows market-rate rents vs. affordable housing discount. | AB14: HUD FY2026 FMR - Ector County, TX
A15: 4 | B15: MARKET RATE | C15: Marvin Gardens Apartments | E15: 4307 Wendover Ave | F15: Odessa | G15: TX | H15: 79762 | I15: 1.2 mi | J15: N/A | K15: N/A | L15: N/A | M15: 1395 | N15: N/A | O15: N/A | P15: N/A | Q15: 1350 | R15: N/A | S15: 1980 | T15: 2 | U15: Varies | V15: Varies | W15: Varies | X15: Varies | Y15: Varies | Z15: HIGH | AA15: Market Rate Comp #4: No income restrictions, 1980 vintage (2 yr diff), N/A units, N/A from subject. Shows market-rate rents vs. affordable housing discount. | AB15: HUD FY2026 FMR - Ector County, TX
A16: 5 | B16: MARKET RATE | C16: Regency Square Apartments | E16: 4100 Tanglewood Ln | F16: Odessa | G16: TX | H16: 79762 | I16: 2.0 mi | J16: N/A | K16: N/A | L16: N/A | M16: 1325 | N16: N/A | O16: N/A | P16: N/A | Q16: 1625 | R16: N/A | S16: N/A | T16: N/A | U16: N/A | V16: N/A | W16: N/A | X16: N/A | Y16: N/A | Z16: BENCHMARK | AA16: BENCHMARK — HUD Fair Market Rent (FMR) for Odessa, TX MSA, effective FY2026. The FMR represents the 40th percentile of gross rents for standard-quality units in this metro area, as published annually by HUD. It is used here as the market reference point. LIHTC-restricted rents are typically 40–70% of FMR depending on the AMI tier. | AB16: HUD FMR Database (huduser.gov)
A17: 6 | B17: MARKET RATE | C17: Country Crest Townhomes | E17: 6500 Eastridge Rd | F17: Odessa | G17: TX | H17: 79762 | I17: 3.8 mi | J17: N/A | K17: N/A | L17: N/A | M17: 1570 | N17: N/A | O17: N/A | P17: N/A | Q17: 1770 | R17: N/A | S17: N/A | T17: N/A | U17: N/A | V17: N/A | W17: N/A | X17: N/A | Y17: N/A | Z17: BENCHMARK | AA17: BENCHMARK — Estimated Metro Market Average for Odessa, calculated at approximately 110% of the HUD FMR. This represents the typical asking rent for unrestricted market-rate units in this area. The gap between this figure and the affordable comp rents above shows the affordability discount our properties provide. | AB17: HUD FMR + Market Estimate
A18: 7 | B18: MARKET RATE | J18: N/A | K18: N/A | L18: N/A | N18: N/A | O18: N/A | P18: N/A
A19: — | B19: BENCHMARK | C19: FY2026 FMR — Odessa, TX MSA | E19: N/A | F19: Odessa | G19: TX | L19: $1,254 | P19: $1,573
A20: — | B20: BENCHMARK | C20: Metro Market Avg — Odessa (Apartments.com) | E20: N/A | F20: Odessa | G20: TX | M20: 1293 | Q20: 1573
A22: COLOR KEY: GREEN = Subject Property | LIGHT GREEN = Affordable Comps (LIHTC/Section 8/HUD) | LIGHT BLUE = Market Rate Comps | ORANGE = Actual Advertised Rent
A24: CURRENT RENT vs. MARKET AVERAGE
A25: Market Average = Avg of Actual Advertised Rents from Market-Rate Comps (Apartments.com)
B26: Current Rents | C26: Market Avg | E26: Difference
A27: 2BD | B27: ='Current Rents'!E23 -> 1450 | C27: 1293 | E27: =B27-C27 -> 157 | F27: =IF(E27<-75,"LOOK INTO INCREASING THE RENT!","")
A28: 3BD | B28: ='Current Rents'!F23 -> 1700 | C28: 1573 | E28: =B28-C28 -> 127 | F28: =IF(E28<-75,"LOOK INTO INCREASING THE RENT!","")
A31: PMTS — Vouchers / FMR / UAP / NET
B32: MKT | C32: VCH | D32: FMR | E32: UAP | F32: NET
A33: 2BD | C33: ='Current Rents'!E23 -> 1450 | D33: 1254
A34: 3BD | C34: ='Current Rents'!F23 -> 1700 | D34: 1573

Sheet 3 - Wilmington
A1: RENT COMPARABLES ANALYSIS — New Wilmington Arms | AI1: ID: 3
A2: 700 W. Laurel Avenue, Compton, CA 90220 | units N/A | Section 8/HUD
A3: Data as of June 2026 | Sources: CoStar, Apartments.com, HUD, Zillow
A4: COLUMN GUIDE — Income-restricted rent limits (50% AMI, 60% AMI), HUD Fair Market Rent (FMR), and Actual Advertised Rent for each bedroom size.
A5: Rank | B5: Type | C5: Property Name | E5: Address | F5: City | G5: St | H5: ZIP | I5: Distance | J5: 1BD 50% AMI | K5: 1BD 60% AMI | L5: 1BD FMR | M5: 1BD - Actual | N5: 2BD 50% AMI | O5: 2BD 60% AMI | P5: 2BD FMR | Q5: 2BD - Actual | R5: 3BD 50% AMI | S5: 3BD 60% AMI | T5: 3BD FMR | U5: 3BD - Actual | V5: 4BD 50% AMI | W5: 4BD 60% AMI | X5: 4BD FMR | Y5: 4BD - Actual | Z5: Units | AA5: Yr Built | AB5: Yr Diff | AC5: Utils Incl. | AD5: Pet Friendly | AE5: Gated | AF5: Pool | AG5: W/D In-Unit | AH5: Competition Level | AI5: Notes / Why Competitive | AJ5: Data Source
A6: ★ | B6: SUBJECT | C6: New Wilmington Arms (SUBJECT) | E6: 700 W. Laurel Avenue | F6: Compton | G6: CA | H6: 90220 | I6: 0.0 mi | J6: $4,733 | K6: $5,680 | L6: $1,736 | M6: ='Current Rents'!D24 -> — | N6: $5,679 | O6: $6,815 | P6: $2,376 | Q6: ='Current Rents'!E24 -> 1402 | R6: $6,312 | S6: $7,575 | T6: $3,044 | U6: ='Current Rents'!F24 -> 1679 | V6: $6,816 | W6: $8,180 | X6: $3,520 | Y6: ='Current Rents'!G24 -> — | Z6: N/A | AA6: 1973 | AB6: 0 | AC6: Yes | AD6: No | AE6: No | AF6: No | AG6: No | AH6: N/A
A7: 1 | B7: AFFORDABLE | C7: Compton Gardens Apartments | E7: 1100 N Wilmington Ave | F7: Compton | G7: CA | H7: 90222 | I7: 1.2 mi | J7: $4,733 | K7: $5,680 | L7: $1,736 | M7: Not Listed | N7: $5,679 | O7: $6,815 | P7: $2,376 | Q7: Not Listed | R7: $6,312 | S7: $7,575 | T7: $3,044 | U7: Not Listed | V7: $6,816 | W7: $8,180 | X7: $3,520 | Y7: Not Listed | Z7: 60 | AA7: 1974 | AB7: 1 | AC7: Yes | AD7: No | AE7: No | AF7: No | AG7: No | AH7: HIGH | AI7: Affordable Comp #1: Section 8/HUD property, 1974 vintage (1 yr diff), 60 units, 1.2 mi from subject. Same income-eligible renter pool. | AJ7: HUD Multifamily Assisted Housing
A8: 2 | B8: AFFORDABLE | C8: Rosecrans Manor | E8: 2200 W Rosecrans Ave | F8: Compton | G8: CA | H8: 90220 | I8: 2.5 mi | J8: $4,733 | K8: $5,680 | L8: $1,736 | M8: Not Listed | N8: $5,679 | O8: $6,815 | P8: $2,376 | Q8: Not Listed | R8: $6,312 | S8: $7,575 | T8: $3,044 | U8: Not Listed | V8: $6,816 | W8: $8,180 | X8: $3,520 | Y8: Not Listed | Z8: 72 | AA8: 1972 | AB8: 1 | AC8: Yes | AD8: No | AE8: No | AF8: No | AG8: No | AH8: HIGH | AI8: Affordable Comp #2: Section 8/HUD property, 1972 vintage (1 yr diff), 72 units, 2.5 mi from subject. Same income-eligible renter pool. | AJ8: HUD Multifamily Assisted Housing
A9: 3 | B9: AFFORDABLE | C9: Willowbrook Terrace | E9: 11800 Wilmington Ave | F9: Los Angeles | G9: CA | H9: 90059 | I9: 4.8 mi | J9: $4,733 | K9: $5,680 | L9: $1,736 | M9: Not Listed | N9: $5,679 | O9: $6,815 | P9: $2,376 | Q9: Not Listed | R9: $6,312 | S9: $7,575 | T9: $3,044 | U9: Not Listed | V9: $6,816 | W9: $8,180 | X9: $3,520 | Y9: Not Listed | Z9: 68 | AA9: 1975 | AB9: 2 | AC9: Yes | AD9: No | AE9: No | AF9: No | AG9: No | AH9: HIGH | AI9: Affordable Comp #3: Section 8/HUD property, 1975 vintage (2 yr diff), 68 units, 4.8 mi from subject. Same income-eligible renter pool. | AJ9: HUD Multifamily Assisted Housing
A10: 4 | B10: AFFORDABLE | C10: Compton Housing Authority - Lueders Park Homes | E10: 600 S Central Ave | F10: Compton | G10: CA | H10: 90220 | I10: 1.8 mi | J10: $4,733 | K10: $5,680 | L10: $1,736 | M10: Not Listed | N10: $5,679 | O10: $6,815 | P10: $2,376 | Q10: Not Listed | R10: $6,312 | S10: $7,575 | T10: $3,044 | U10: Not Listed | V10: $6,816 | W10: $8,180 | X10: $3,520 | Y10: Not Listed | Z10: 64 | AA10: 1973 | AB10: 0 | AC10: Yes | AD10: No | AE10: No | AF10: No | AG10: No | AH10: HIGH | AI10: Affordable Comp #4: Public Housing/HUD property, 1973 vintage (0 yr diff), 64 units, 1.8 mi from subject. Same income-eligible renter pool. | AJ10: Compton Housing Authority
A11: 5 | B11: AFFORDABLE
A12: 1 | B12: MARKET RATE | C12: Jasmine Garden Apartments | D12: COMPETITION | E12: 601 W Corregidor St | F12: Compton | G12: CA | H12: 90220 | I12: 0.5 mi | J12: N/A | K12: N/A | L12: N/A | M12: 1704 | N12: N/A | O12: N/A | P12: N/A | Q12: 2044 | R12: N/A | S12: N/A | T12: N/A | U12: 2363 | V12: N/A | W12: N/A | X12: N/A | Y12: Not Listed | Z12: 60 | AA12: 1975 | AB12: 2 | AC12: Varies | AD12: Varies | AE12: Varies | AF12: Varies | AG12: Varies | AH12: HIGH | AI12: Market Rate Comp #1: No income restrictions, 1975 vintage (2 yr diff), 60 units, 1.5 mi from subject. Shows market-rate rents vs. affordable housing discount. | AJ12: https://www.rentcafe.com/apartments-for-rent/us/ca/compton/
A13: 2 | B13: MARKET RATE | C13: 819 W 137th St | E13: 819 W 137th St | F13: Compton | G13: CA | H13: 90222 | I13: 1.2 mi | J13: N/A | K13: N/A | L13: N/A | M13: 1650 | N13: N/A | O13: N/A | P13: N/A | Q13: 1850 | R13: N/A | S13: N/A | T13: N/A | U13: 2250 | V13: N/A | W13: N/A | X13: N/A | Y13: Not Listed | Z13: 48 | AA13: 1970 | AB13: 3 | AC13: Varies | AD13: Varies | AE13: Varies | AF13: Varies | AG13: Varies | AH13: HIGH | AI13: Market Rate Comp #2: No income restrictions, 1970 vintage (3 yr diff), 48 units, 3.2 mi from subject. Shows market-rate rents vs. affordable housing discount. | AJ13: https://www.rentcafe.com/apartments-for-rent/us/ca/lynwood/
A14: 3 | B14: MARKET RATE | C14: Le Chateau Apartments | E14: 4267 Carlin Ave | F14: Lynwood | G14: CA | H14: 90262 | I14: 2.1 mi | J14: N/A | K14: N/A | L14: N/A | M14: 1795 | N14: N/A | O14: N/A | P14: N/A | Q14: 2095 | R14: N/A | S14: N/A | T14: N/A | U14: 2500 | V14: N/A | W14: N/A | X14: N/A | Y14: Not Listed | Z14: 72 | AA14: 1972 | AB14: 1 | AC14: Varies | AD14: Varies | AE14: Varies | AF14: Varies | AG14: Varies | AH14: HIGH | AI14: Market Rate Comp #3: No income restrictions, 1972 vintage (1 yr diff), 72 units, 4.8 mi from subject. Shows market-rate rents vs. affordable housing discount. | AJ14: https://www.rentcafe.com/apartments-for-rent/us/ca/carson/
A15: 4 | B15: MARKET RATE | C15: Lynwood Palms | E15: 3189 Euclid | F15: Lynwood | G15: CA | H15: 90262 | I15: 2.3 mi | J15: N/A | K15: N/A | L15: N/A | M15: Not Listed | N15: N/A | O15: N/A | P15: N/A | Q15: 2295 | R15: N/A | S15: N/A | T15: N/A | U15: 2600 | V15: N/A | W15: N/A | X15: N/A | Y15: Not Listed | Z15: 52 | AA15: 1971 | AB15: 2 | AC15: Varies | AD15: Varies | AE15: Varies | AF15: Varies | AG15: Varies | AH15: HIGH | AI15: Market Rate Comp #4: No income restrictions, 1971 vintage (2 yr diff), 52 units, 6.5 mi from subject. Shows market-rate rents vs. affordable housing discount. | AJ15: https://www.rentcafe.com/apartments-for-rent/us/ca/inglewood/
A16: 5 | B16: MARKET RATE | C16: The Ray Apartments | E16: 6479 Atlantic Ave | F16: Long Beach | G16: CA | H16: 90805 | I16: 3.0 mi | J16: N/A | K16: N/A | L16: N/A | M16: 2113 | N16: N/A | O16: N/A | P16: N/A | Q16: 2403 | R16: N/A | S16: N/A | T16: N/A | U16: N/A | V16: N/A | W16: N/A | X16: N/A | Y16: N/A | Z16: N/A | AA16: N/A | AB16: N/A | AC16: N/A | AD16: N/A | AE16: N/A | AF16: N/A | AG16: N/A | AH16: BENCHMARK | AI16: BENCHMARK — HUD Fair Market Rent (FMR) for Los Angeles County, effective FY2026. The FMR represents the 40th percentile of gross rents for standard-quality units in this metro area, as published annually by HUD. It is used here as the market reference point. LIHTC-restricted rents are typically 40–70% of FMR depending on the AMI tier. | AJ16: HUD FMR Database (huduser.gov)
A17: 6 | B17: MARKET RATE | C17: 903 N. Sloan Ave. | E17: 903 N Sloan Ave | F17: Compton | G17: CA | H17: 90221 | I17: 0.8 mi | J17: N/A | K17: N/A | L17: N/A | M17: 1695 | N17: N/A | O17: N/A | P17: N/A | Q17: N/A | R17: N/A | S17: N/A | T17: N/A | U17: N/A | V17: N/A | W17: N/A | X17: N/A | Y17: N/A | Z17: N/A | AA17: N/A | AB17: N/A | AC17: N/A | AD17: N/A | AE17: N/A | AF17: N/A | AG17: N/A | AH17: BENCHMARK | AI17: BENCHMARK — Estimated Metro Market Average for Compton, calculated at approximately 110% of the HUD FMR. This represents the typical asking rent for unrestricted market-rate units in this area. The gap between this figure and the affordable comp rents above shows the affordability discount our properties provide. | AJ17: HUD FMR + Market Estimate
A18: 7 | B18: MARKET RATE | J18: N/A | K18: N/A | L18: N/A | N18: N/A | O18: N/A | P18: N/A | R18: N/A | S18: N/A | T18: N/A | V18: N/A | W18: N/A | X18: N/A
A19: — | B19: BENCHMARK | C19: FY2026 FMR — Los Angeles County | E19: N/A | F19: Compton | G19: CA | L19: $1,736 | P19: $2,376 | T19: $3,044 | X19: $3,520
A20: — | B20: BENCHMARK | C20: Metro Market Avg — Compton (Apartments.com) | E20: N/A | F20: Compton | G20: CA | M20: 1791 | Q20: 2137 | U20: 2428
A22: COLOR KEY: GREEN = Subject Property | LIGHT GREEN = Affordable Comps (LIHTC/Section 8/HUD) | LIGHT BLUE = Market Rate Comps | ORANGE = Actual Advertised Rent
A24: CURRENT RENT vs. MARKET AVERAGE
A25: Market Average = Avg of Actual Advertised Rents from Market-Rate Comps (Apartments.com)
B26: Current Rents | C26: Market Avg | E26: Difference
A27: 1BD | B27: ='Current Rents'!D24 -> — | C27: 1791 | E27: =B27-C27 -> #VALUE! | F27: =IF(E27<-75,"LOOK INTO INCREASING THE RENT!","") -> #VALUE!
A28: 2BD | B28: ='Current Rents'!E24 -> 1402 | C28: 2137 | E28: =B28-C28 -> -735 | F28: =IF(E28<-75,"LOOK INTO INCREASING THE RENT!","") -> LOOK INTO INCREASING THE RENT!
A29: 3BD | B29: ='Current Rents'!F24 -> 1679 | C29: 2428 | E29: =B29-C29 -> -749 | F29: =IF(E29<-75,"LOOK INTO INCREASING THE RENT!","") -> LOOK INTO INCREASING THE RENT!
A30: 4BD | B30: ='Current Rents'!G24 -> — | C30: N/A | E30: =B30-C30 -> #VALUE! | F30: =IF(E30<-75,"LOOK INTO INCREASING THE RENT!","") -> #VALUE!
A33: PMTS — Vouchers / FMR / UAP / NET
B34: MKT | C34: VCH | D34: FMR | E34: UAP | F34: NET
A35: 1BD | C35: ='Current Rents'!D24 -> — | D35: 1736
A36: 2BD | C36: ='Current Rents'!E24 -> 1402 | D36: 2376
A37: 3BD | C37: ='Current Rents'!F24 -> 1679 | D37: 3044
A38: 4BD | C38: ='Current Rents'!G24 -> — | D38: 3520

Sheet 19 - Gates
A1: RENT COMPARABLES ANALYSIS — Gates on Manhattan | AE1: ID: 19
A2: 1050 Manhattan Blvd, Harvey, LA 70058 | 276 units | Section 8/HUD
A3: Data as of June 2026 | Sources: CoStar, Apartments.com, HUD, Zillow
A4: COLUMN GUIDE — Income-restricted rent limits (50% AMI, 60% AMI), HUD Fair Market Rent (FMR), and Actual Advertised Rent for each bedroom size.
A5: Rank | B5: Type | C5: Property Name | E5: Address | F5: City | G5: St | H5: ZIP | I5: Distance | J5: 1BD 50% AMI | K5: 1BD 60% AMI | L5: 1BD FMR | M5: 1BD - Actual | N5: 2BD 50% AMI | O5: 2BD 60% AMI | P5: 2BD FMR | Q5: 2BD - Actual | R5: 3BD 50% AMI | S5: 3BD 60% AMI | T5: 3BD FMR | U5: 3BD - Actual | V5: Units | W5: Yr Built | X5: Yr Diff | Y5: Utils Incl. | Z5: Pet Friendly | AA5: Gated | AB5: Pool | AC5: W/D In-Unit | AD5: Competition Level | AE5: Notes / Why Competitive | AF5: Data Source
A6: ★ | B6: SUBJECT | C6: Gates on Manhattan (SUBJECT) | E6: 1050 Manhattan Blvd | F6: Harvey | G6: LA | H6: 70058 | I6: 0.0 mi | J6: $2,808 | K6: $3,370 | L6: $916 | M6: ='Current Rents'!D25 -> 1221 | N6: $3,370 | O6: $4,045 | P6: $1,254 | Q6: ='Current Rents'!E25 -> 1563 | R6: $3,741 | S6: $4,490 | T6: $1,573 | U6: ='Current Rents'!F25 -> 1820 | V6: 276 | W6: 1968 | X6: 0 | Y6: Yes | Z6: No | AA6: No | AB6: No | AC6: No | AD6: N/A
A7: 1 | B7: AFFORDABLE | C7: Westchase Apartments | E7: 1013 Manhattan Blvd | F7: Harvey | G7: LA | H7: 70058 | I7: 0.3 mi | J7: $2,808 | K7: $3,370 | L7: $916 | M7: $887 | N7: $3,370 | O7: $4,045 | P7: $1,254 | Q7: $1,083 | R7: $3,741 | S7: $4,490 | T7: $1,573 | U7: Not Listed | V7: 250 | W7: 1970 | X7: 2 | Y7: Yes | Z7: No | AA7: No | AB7: No | AC7: No | AD7: HIGH | AE7: Affordable Comp #1: Section 8/HUD property, 1970 vintage (2 yr diff), 250 units, 0.3 mi from subject. Same income-eligible renter pool. | AF7: AffordableHousingOnline.com
A8: 2 | B8: AFFORDABLE | C8: Sunset Villa Apartments | E8: 1000 Scotsdale Dr | F8: Harvey | G8: LA | H8: 70058 | I8: 1.2 mi | J8: $2,808 | K8: $3,370 | L8: $916 | M8: $1,146 | N8: $3,370 | O8: $4,045 | P8: $1,254 | Q8: $1,146 | R8: $3,741 | S8: $4,490 | T8: $1,573 | U8: $1,146 | V8: 200 | W8: 1968 | X8: 0 | Y8: Yes | Z8: No | AA8: No | AB8: No | AC8: No | AD8: HIGH | AE8: Affordable Comp #2: Section 8/HUD property, 1968 vintage (0 yr diff), 200 units, 1.2 mi from subject. Same income-eligible renter pool. | AF8: AffordableHousingOnline.com
A9: 3 | B9: AFFORDABLE | C9: Gretna Manor Apartments | E9: 400 Huey P Long Ave | F9: Gretna | G9: LA | H9: 70053 | I9: 3.5 mi | J9: $2,808 | K9: $3,370 | L9: $916 | M9: Not Listed | N9: $3,370 | O9: $4,045 | P9: $1,254 | Q9: Not Listed | R9: $3,741 | S9: $4,490 | T9: $1,573 | U9: Not Listed | V9: 220 | W9: 1972 | X9: 4 | Y9: Yes | Z9: No | AA9: No | AB9: No | AC9: No | AD9: HIGH | AE9: Affordable Comp #3: Section 8/HUD property, 1972 vintage (4 yr diff), 220 units, 3.5 mi from subject. Same income-eligible renter pool. | AF9: HUD Multifamily Assisted Housing
A10: 4 | B10: AFFORDABLE | C10: Jefferson Parish Housing Authority - Woodmere Homes | E10: 1200 Woodmere Blvd | F10: Harvey | G10: LA | H10: 70058 | I10: 2.1 mi | J10: $2,808 | K10: $3,370 | L10: $916 | M10: Not Listed | N10: $3,370 | O10: $4,045 | P10: $1,254 | Q10: Not Listed | R10: $3,741 | S10: $4,490 | T10: $1,573 | U10: Not Listed | V10: 240 | W10: 1969 | X10: 1 | Y10: Yes | Z10: No | AA10: No | AB10: No | AC10: No | AD10: HIGH | AE10: Affordable Comp #4: Public Housing/HUD property, 1969 vintage (1 yr diff), 240 units, 2.1 mi from subject. Same income-eligible renter pool. | AF10: Jefferson Parish Housing Authority
A11: 5 | B11: AFFORDABLE
A12: 1 | B12: MARKET RATE | C12: Windsor at Manhattan | D12: COMPETITION | E12: 1499 Central Park Blvd | F12: Harvey | G12: LA | H12: 70058 | I12: 0.4 mi | J12: N/A | K12: N/A | L12: N/A | M12: 1495 | N12: N/A | O12: N/A | P12: N/A | Q12: 1875 | R12: N/A | S12: N/A | T12: N/A | U12: 2100 | V12: N/A | W12: 1968 | X12: 0 | Y12: Varies | Z12: Varies | AA12: Varies | AB12: Varies | AC12: Varies | AD12: HIGH | AE12: Market Rate Comp #1: No income restrictions, 1968 vintage (0 yr diff), N/A units, N/A from subject. Shows market-rate rents vs. affordable housing discount. | AF12: HUD FY2026 FMR - Jefferson Parish, LA (limited market rate listings for 1958-1978 vintage)
A13: 2 | B13: MARKET RATE | C13: Emerald Pointe Apartment Homes | E13: 2700 Whitney Ave | F13: Harvey | G13: LA | H13: 70058 | I13: 1.5 mi | J13: N/A | K13: N/A | L13: N/A | M13: 1190 | N13: N/A | O13: N/A | P13: N/A | Q13: 1354 | R13: N/A | S13: N/A | T13: N/A | U13: 1550 | V13: N/A | W13: 1970 | X13: 2 | Y13: Varies | Z13: Varies | AA13: Varies | AB13: Varies | AC13: Varies | AD13: HIGH | AE13: Market Rate Comp #2: No income restrictions, 1970 vintage (2 yr diff), N/A units, 3.0 mi from subject. Shows market-rate rents vs. affordable housing discount. | AF13: HUD FY2026 FMR - Jefferson Parish, LA
A14: 3 | B14: MARKET RATE | C14: Summerfield Apartment Homes | E14: 1500 Lorene Dr | F14: Harvey | G14: LA | H14: 70058 | I14: 0.6 mi | J14: N/A | K14: N/A | L14: N/A | M14: 1128 | N14: N/A | O14: N/A | P14: N/A | Q14: 1388 | R14: N/A | S14: N/A | T14: N/A | U14: 1550 | V14: N/A | W14: 1965 | X14: 3 | Y14: Varies | Z14: Varies | AA14: Varies | AB14: Varies | AC14: Varies | AD14: HIGH | AE14: Market Rate Comp #3: No income restrictions, 1965 vintage (3 yr diff), N/A units, 5.0 mi from subject. Shows market-rate rents vs. affordable housing discount. | AF14: HUD FY2026 FMR - Jefferson Parish, LA
A15: 4 | B15: MARKET RATE | C15: Westchase Apartments | E15: 1013 Manhattan Blvd | F15: Harvey | G15: LA | H15: 70058 | I15: 0.1 mi | J15: N/A | K15: N/A | L15: N/A | M15: 887 | N15: N/A | O15: N/A | P15: N/A | Q15: 1083 | R15: N/A | S15: N/A | T15: N/A | U15: 1550 | V15: N/A | W15: 1970 | X15: 2 | Y15: Varies | Z15: Varies | AA15: Varies | AB15: Varies | AC15: Varies | AD15: HIGH | AE15: Market Rate Comp #4: No income restrictions, 1970 vintage (2 yr diff), N/A units, 6.0 mi from subject. Shows market-rate rents vs. affordable housing discount. | AF15: HUD FY2026 FMR - Jefferson Parish, LA
A16: 5 | B16: MARKET RATE | C16: Boulevard Apartment Homes | E16: 901 Gretna Blvd | F16: Gretna | G16: LA | H16: 70053 | I16: 2.0 mi | J16: N/A | K16: N/A | L16: N/A | M16: 995 | N16: N/A | O16: N/A | P16: N/A | Q16: 1025 | R16: N/A | S16: N/A | T16: N/A | U16: N/A | V16: N/A | W16: N/A | X16: N/A | Y16: N/A | Z16: N/A | AA16: N/A | AB16: N/A | AC16: N/A | AD16: BENCHMARK | AE16: BENCHMARK — HUD Fair Market Rent (FMR) for New Orleans MSA, effective FY2026. The FMR represents the 40th percentile of gross rents for standard-quality units in this metro area, as published annually by HUD. It is used here as the market reference point. LIHTC-restricted rents are typically 40–70% of FMR depending on the AMI tier. | AF16: HUD FMR Database (huduser.gov)
A17: 6 | B17: MARKET RATE | C17: St. Germaine | E17: 2201 Manhattan Blvd | F17: Harvey | G17: LA | H17: 70058 | I17: 1.1 mi | J17: N/A | K17: N/A | L17: N/A | M17: 815 | N17: N/A | O17: N/A | P17: N/A | Q17: 872 | R17: N/A | S17: N/A | T17: N/A | U17: N/A | V17: N/A | W17: N/A | X17: N/A | Y17: N/A | Z17: N/A | AA17: N/A | AB17: N/A | AC17: N/A | AD17: BENCHMARK | AE17: BENCHMARK — Estimated Metro Market Average for Harvey, calculated at approximately 110% of the HUD FMR. This represents the typical asking rent for unrestricted market-rate units in this area. The gap between this figure and the affordable comp rents above shows the affordability discount our properties provide. | AF17: HUD FMR + Market Estimate
A18: 7 | B18: MARKET RATE | J18: N/A | K18: N/A | L18: N/A | N18: N/A | O18: N/A | P18: N/A | R18: N/A | S18: N/A | T18: N/A
A19: — | B19: BENCHMARK | C19: FY2026 FMR — New Orleans MSA | E19: N/A | F19: Harvey | G19: LA | L19: $916 | P19: $1,254 | T19: $1,573
A20: — | B20: BENCHMARK | C20: Metro Market Avg — Harvey (Apartments.com) | E20: N/A | F20: Harvey | G20: LA | M20: 1085 | Q20: 1266 | U20: 1688
A22: COLOR KEY: GREEN = Subject Property | LIGHT GREEN = Affordable Comps (LIHTC/Section 8/HUD) | LIGHT BLUE = Market Rate Comps | ORANGE = Actual Advertised Rent
A24: CURRENT RENT vs. MARKET AVERAGE
A25: Market Average = Avg of Actual Advertised Rents from Market-Rate Comps (Apartments.com)
B26: Current Rents | C26: Market Avg | E26: Difference
A27: 1BD | B27: ='Current Rents'!D25 -> 1221 | C27: 1085 | E27: =B27-C27 -> 136 | F27: =IF(E27<-75,"LOOK INTO INCREASING THE RENT!","")
A28: 2BD | B28: ='Current Rents'!E25 -> 1563 | C28: 1266 | E28: =B28-C28 -> 297 | F28: =IF(E28<-75,"LOOK INTO INCREASING THE RENT!","")
A29: 3BD | B29: ='Current Rents'!F25 -> 1820 | C29: 1688 | E29: =B29-C29 -> 132 | F29: =IF(E29<-75,"LOOK INTO INCREASING THE RENT!","")
A32: PMTS — Vouchers / FMR / UAP / NET
B33: MKT | C33: VCH | D33: FMR | E33: UAP | F33: NET
A34: 1BD | C34: ='Current Rents'!D25 -> 1221 | D34: 916
A35: 2BD | C35: ='Current Rents'!E25 -> 1563 | D35: 1254
A36: 3BD | C36: ='Current Rents'!F25 -> 1820 | D36: 1573

Sheet 42 - Ruby
A1: RENT COMPARABLES ANALYSIS — Ruby Diamond | AA1: ID: 42
A2: Marrero, Marrero, LA 70072 | 73 units | LIHTC
A3: Data as of June 2026 | Sources: CoStar, Apartments.com, HUD, Zillow
A4: COLUMN GUIDE — Income-restricted rent limits (50% AMI, 60% AMI), HUD Fair Market Rent (FMR), and Actual Advertised Rent for each bedroom size.
A5: Rank | B5: Type | C5: Property Name | E5: Address | F5: City | G5: St | H5: ZIP | I5: Distance | J5: 3BD 50% AMI | K5: 3BD 60% AMI | L5: 3BD FMR | M5: 3BD - Actual | N5: 4BD 50% AMI | O5: 4BD 60% AMI | P5: 4BD FMR | Q5: 4BD - Actual | R5: Units | S5: Yr Built | T5: Yr Diff | U5: Utils Incl. | V5: Pet Friendly | W5: Gated | X5: Pool | Y5: W/D In-Unit | Z5: Competition Level | AA5: Notes / Why Competitive | AB5: Data Source
A6: ★ | B6: SUBJECT | C6: Ruby Diamond (SUBJECT) | E6: Marrero | F6: Marrero | G6: LA | H6: 70072 | I6: 0.0 mi | J6: $3,741 | K6: $4,490 | L6: $1,573 | M6: ='Current Rents'!F26 -> 1300 | N6: $4,041 | O6: $4,850 | P6: $1,818 | Q6: ='Current Rents'!G26 -> — | R6: 73 | S6: 2000 | T6: 0 | U6: No | V6: No | W6: No | X6: No | Y6: No | Z6: N/A
A7: 1 | B7: AFFORDABLE | C7: First Emanuel Homes Of No | E7: 912 Fourth Street | F7: New Orleans | G7: LA | H7: 70130-0000 | I7: 2.4 mi | J7: $3,741 | K7: $4,490 | L7: $1,573 | M7: Not Listed | N7: $4,041 | O7: $4,850 | P7: $1,818 | Q7: Not Listed | R7: 89 | S7: 1999 | T7: 1 | U7: Yes | V7: No | W7: No | X7: No | Y7: No | Z7: HIGH | AA7: Affordable Comp #1: LIHTC property, 1999 vintage (1 yr diff), 89 units, 2.4 mi from subject. Same income-eligible renter pool. | AB7: HUD LIHTC Database (huduser.gov)
A8: 2 | B8: AFFORDABLE | C8: Canal Street Sro | E8: 1801 Canal Street | F8: New Orleans | G8: LA | H8: 70119-0000 | I8: 4.6 mi | J8: $3,741 | K8: $4,490 | L8: $1,573 | M8: Not Listed | N8: $4,041 | O8: $4,850 | P8: $1,818 | Q8: Not Listed | R8: 70 | S8: 2002 | T8: 2 | U8: Yes | V8: No | W8: No | X8: No | Y8: No | Z8: HIGH | AA8: Affordable Comp #2: LIHTC property, 2002 vintage (2 yr diff), 70 units, 4.6 mi from subject. Same income-eligible renter pool. | AB8: HUD LIHTC Database (huduser.gov)
A9: 3 | B9: AFFORDABLE | C9: Cherry Blossom Apts | E9: 205 Mlk Dr. | F9: Port Barre | G9: LA | H9: 70577-0000 | I9: N/A | J9: $3,741 | K9: $4,490 | L9: $1,573 | M9: $1,660 | N9: $4,041 | O9: $4,850 | P9: $1,818 | Q9: $1,709 | R9: 73 | S9: 2000 | T9: 0 | U9: Yes | V9: No | W9: No | X9: No | Y9: No | Z9: MODERATE | AA9: Affordable Comp #3: LIHTC property, 2000 vintage (0 yr diff), 73 units, N/A from subject. Same income-eligible renter pool. | AB9: HUD LIHTC Database (huduser.gov)
A10: 4 | B10: AFFORDABLE | C10: Putnam Plaza Apts | E10: Scattered | F10: New Orleans | G10: LA | H10: 70113-0000 | I10: 2.7 mi | J10: $3,741 | K10: $4,490 | L10: $1,573 | M10: Not Listed | N10: $4,041 | O10: $4,850 | P10: $1,818 | Q10: Not Listed | R10: 38 | S10: 1999 | T10: 1 | U10: Yes | V10: No | W10: No | X10: No | Y10: No | Z10: HIGH | AA10: Affordable Comp #4: LIHTC property, 1999 vintage (1 yr diff), 38 units, 2.7 mi from subject. Same income-eligible renter pool. | AB10: HUD LIHTC Database (huduser.gov)
A11: 5 | B11: AFFORDABLE
A12: 1 | B12: MARKET RATE | C12: The Waters at Promenade | D12: COMPETITION | E12: 1600 Promenade Blvd | F12: Marrero | G12: LA | H12: 70072 | I12: 0.8 mi | J12: N/A | K12: N/A | L12: N/A | M12: 1995 | N12: N/A | O12: N/A | P12: N/A | Q12: Not Listed | R12: 120 | S12: 2001 | T12: 1 | U12: Varies | V12: Varies | W12: Varies | X12: Varies | Y12: Varies | Z12: HIGH | AA12: Market Rate Comp #1: No income restrictions, 2001 vintage (1 yr diff), 120 units, 1.8 mi from subject. Shows market-rate rents vs. affordable housing discount. | AB12: https://www.rentcafe.com/apartments-for-rent/us/la/marrero/
A13: 2 | B13: MARKET RATE | C13: 2808 Pritchard Rd | E13: 2808 Pritchard Rd | F13: Marrero | G13: LA | H13: 70072 | I13: 1.2 mi | J13: N/A | K13: N/A | L13: N/A | M13: 2150 | N13: N/A | O13: N/A | P13: N/A | Q13: Not Listed | R13: 96 | S13: 1999 | T13: 1 | U13: Varies | V13: Varies | W13: Varies | X13: Varies | Y13: Varies | Z13: HIGH | AA13: Market Rate Comp #2: No income restrictions, 1999 vintage (1 yr diff), 96 units, 3.5 mi from subject. Shows market-rate rents vs. affordable housing discount. | AB13: https://www.rentcafe.com/apartments-for-rent/us/la/harvey/
A14: 3 | B14: MARKET RATE | C14: 5007 Towering Oaks Ave | E14: 5007 Towering Oaks Ave | F14: Marrero | G14: LA | H14: 70072 | I14: 1.5 mi | J14: N/A | K14: N/A | L14: N/A | M14: 1700 | N14: N/A | O14: N/A | P14: N/A | Q14: Not Listed | R14: 80 | S14: 2002 | T14: 2 | U14: Varies | V14: Varies | W14: Varies | X14: Varies | Y14: Varies | Z14: HIGH | AA14: Market Rate Comp #3: No income restrictions, 2002 vintage (2 yr diff), 80 units, 5.2 mi from subject. Shows market-rate rents vs. affordable housing discount. | AB14: https://www.rentcafe.com/apartments-for-rent/us/la/gretna/
A15: 4 | B15: MARKET RATE | C15: 1501 Somerset Pl | E15: 1501 Somerset Pl | F15: Marrero | G15: LA | H15: 70072 | I15: 0.9 mi | J15: N/A | K15: N/A | L15: N/A | M15: 1850 | N15: N/A | O15: N/A | P15: N/A | Q15: Not Listed | R15: 64 | S15: 2000 | T15: 0 | U15: Varies | V15: Varies | W15: Varies | X15: Varies | Y15: Varies | Z15: HIGH | AA15: Market Rate Comp #4: No income restrictions, 2000 vintage (0 yr diff), 64 units, 4.2 mi from subject. Shows market-rate rents vs. affordable housing discount. | AB15: https://www.rentcafe.com/apartments-for-rent/us/la/gretna/
A16: 5 | B16: MARKET RATE | C16: 2429 Ramsey Dr | E16: 2429 Ramsey Dr | F16: Marrero | G16: LA | H16: 70072 | I16: 1.1 mi | J16: N/A | K16: N/A | L16: N/A | M16: 1600 | N16: N/A | O16: N/A | P16: N/A | Q16: N/A | R16: N/A | S16: N/A | T16: N/A | U16: N/A | V16: N/A | W16: N/A | X16: N/A | Y16: N/A | Z16: BENCHMARK | AA16: BENCHMARK — HUD Fair Market Rent (FMR) for New Orleans MSA, effective FY2026. The FMR represents the 40th percentile of gross rents for standard-quality units in this metro area, as published annually by HUD. It is used here as the market reference point. LIHTC-restricted rents are typically 40–70% of FMR depending on the AMI tier. | AB16: HUD FMR Database (huduser.gov)
A17: 6 | B17: MARKET RATE | C17: 1513 R. Esplanade | E17: 1513 R. Esplanade | F17: Marrero | G17: LA | H17: 70072 | I17: 0.7 mi | J17: N/A | K17: N/A | L17: N/A | M17: N/A | N17: N/A | O17: N/A | P17: N/A | Q17: 2800 | R17: N/A | S17: N/A | T17: N/A | U17: N/A | V17: N/A | W17: N/A | X17: N/A | Y17: N/A | Z17: BENCHMARK | AA17: BENCHMARK — Estimated Metro Market Average for Marrero, calculated at approximately 110% of the HUD FMR. This represents the typical asking rent for unrestricted market-rate units in this area. The gap between this figure and the affordable comp rents above shows the affordability discount our properties provide. | AB17: HUD FMR + Market Estimate
A18: 7 | B18: MARKET RATE | J18: N/A | K18: N/A | L18: N/A | N18: N/A | O18: N/A | P18: N/A
A19: — | B19: BENCHMARK | C19: FY2026 FMR — New Orleans MSA | E19: N/A | F19: Marrero | G19: LA | L19: $1,573 | P19: $1,818
A20: — | B20: BENCHMARK | C20: Metro Market Avg — Marrero (Apartments.com) | E20: N/A | F20: Marrero | G20: LA | M20: 1859 | Q20: 2800
A22: COLOR KEY: GREEN = Subject Property | LIGHT GREEN = Affordable Comps (LIHTC/Section 8/HUD) | LIGHT BLUE = Market Rate Comps | ORANGE = Actual Advertised Rent
A24: CURRENT RENT vs. MARKET AVERAGE
A25: Market Average = Avg of Actual Advertised Rents from Market-Rate Comps (Apartments.com)
B26: Current Rents | C26: Market Avg | E26: Difference
A27: 3BD | B27: ='Current Rents'!F26 -> 1300 | C27: 1859 | E27: =B27-C27 -> -559 | F27: =IF(E27<-75,"LOOK INTO INCREASING THE RENT!","") -> LOOK INTO INCREASING THE RENT!
A28: 4BD | B28: ='Current Rents'!G26 -> — | C28: 2800 | E28: =B28-C28 -> #VALUE! | F28: =IF(E28<-75,"LOOK INTO INCREASING THE RENT!","") -> #VALUE!
A31: PMTS — Vouchers / FMR / UAP / NET
B32: MKT | C32: VCH | D32: FMR | E32: UAP | F32: NET
A33: 3BD | C33: ='Current Rents'!F26 -> 1300 | D33: 1573
A34: 4BD | C34: ='Current Rents'!G26 -> — | D34: 1818

Sheet 39 - Star
A1: RENT COMPARABLES ANALYSIS — Star Homes | AE1: ID: 39
A2: 2020 Melba Place, Marrero, LA 70072 | 48 units | LIHTC
A3: Data as of June 2026 | Sources: CoStar, Apartments.com, HUD, Zillow
A4: COLUMN GUIDE — Income-restricted rent limits (50% AMI, 60% AMI), HUD Fair Market Rent (FMR), and Actual Advertised Rent for each bedroom size.
A5: Rank | B5: Type | C5: Property Name | E5: Address | F5: City | G5: St | H5: ZIP | I5: Distance | J5: 2BD 50% AMI | K5: 2BD 60% AMI | L5: 2BD FMR | M5: 2BD - Actual | N5: 3BD 50% AMI | O5: 3BD 60% AMI | P5: 3BD FMR | Q5: 3BD - Actual | R5: 4BD 50% AMI | S5: 4BD 60% AMI | T5: 4BD FMR | U5: 4BD - Actual | V5: Units | W5: Yr Built | X5: Yr Diff | Y5: Utils Incl. | Z5: Pet Friendly | AA5: Gated | AB5: Pool | AC5: W/D In-Unit | AD5: Competition Level | AE5: Notes / Why Competitive | AF5: Data Source
A6: ★ | B6: SUBJECT | C6: Star Homes (SUBJECT) | E6: 2020 Melba Place | F6: Marrero | G6: LA | H6: 70072 | I6: 0.0 mi | J6: $3,370 | K6: $4,045 | L6: $1,254 | M6: ='Current Rents'!E27 -> 0 | N6: $3,741 | O6: $4,490 | P6: $1,573 | Q6: ='Current Rents'!F27 -> 1223 | R6: $4,041 | S6: $4,850 | T6: $1,818 | U6: ='Current Rents'!G27 -> 870 | V6: 48 | W6: 2000 | X6: 0 | Y6: No | Z6: No | AA6: No | AB6: No | AC6: No | AD6: N/A
A7: 1 | B7: AFFORDABLE | C7: Star Affordable Homes | E7: 2012 Melba Pl | F7: Marrero | G7: LA | H7: 70072 | I7: 2.2 mi | J7: $3,370 | K7: $4,045 | L7: $1,254 | M7: Not Listed | N7: $3,741 | O7: $4,490 | P7: $1,573 | Q7: Not Listed | R7: $4,041 | S7: $4,850 | T7: $1,818 | U7: Not Listed | V7: 48 | W7: 1998 | X7: 2 | Y7: Yes | Z7: No | AA7: No | AB7: No | AC7: No | AD7: HIGH | AE7: Affordable Comp #1: LIHTC property, 1998 vintage (2 yr diff), 48 units, 2.2 mi from subject. Same income-eligible renter pool. | AF7: HUD LIHTC Database (huduser.gov)
A8: 2 | B8: AFFORDABLE | C8: Star Homes | E8: 2012 Melba Place | F8: Marrero | G8: LA | H8: 70072-0000 | I8: 2.2 mi | J8: $3,370 | K8: $4,045 | L8: $1,254 | M8: Not Listed | N8: $3,741 | O8: $4,490 | P8: $1,573 | Q8: Not Listed | R8: $4,041 | S8: $4,850 | T8: $1,818 | U8: Not Listed | V8: 48 | W8: 1998 | X8: 2 | Y8: Yes | Z8: No | AA8: No | AB8: No | AC8: No | AD8: HIGH | AE8: Affordable Comp #2: LIHTC property, 1998 vintage (2 yr diff), 48 units, 2.2 mi from subject. Same income-eligible renter pool. | AF8: HUD LIHTC Database (huduser.gov)
A9: 3 | B9: AFFORDABLE | C9: Ames Gardens Estates | E9: 530 Ames Blvd. | F9: Marrero | G9: LA | H9: 70072-0000 | I9: 0.4 mi | J9: $3,370 | K9: $4,045 | L9: $1,254 | M9: Not Listed | N9: $3,741 | O9: $4,490 | P9: $1,573 | Q9: Not Listed | R9: $4,041 | S9: $4,850 | T9: $1,818 | U9: Not Listed | V9: 48 | W9: 2002 | X9: 2 | Y9: Yes | Z9: No | AA9: No | AB9: No | AC9: No | AD9: HIGH | AE9: Affordable Comp #3: LIHTC property, 2002 vintage (2 yr diff), 48 units, 0.4 mi from subject. Same income-eligible renter pool. | AF9: HUD LIHTC Database (huduser.gov)
A10: 4 | B10: AFFORDABLE | C10: Putnam Plaza Apts | E10: Scattered | F10: New Orleans | G10: LA | H10: 70113-0000 | I10: 2.7 mi | J10: $3,370 | K10: $4,045 | L10: $1,254 | M10: Not Listed | N10: $3,741 | O10: $4,490 | P10: $1,573 | Q10: Not Listed | R10: $4,041 | S10: $4,850 | T10: $1,818 | U10: Not Listed | V10: 38 | W10: 1999 | X10: 1 | Y10: Yes | Z10: No | AA10: No | AB10: No | AC10: No | AD10: HIGH | AE10: Affordable Comp #4: LIHTC property, 1999 vintage (1 yr diff), 38 units, 2.7 mi from subject. Same income-eligible renter pool. | AF10: HUD LIHTC Database (huduser.gov)
A11: 5 | B11: AFFORDABLE
A12: 1 | B12: MARKET RATE | C12: The Waters at Promenade | D12: COMPETITION | E12: 1600 Promenade Blvd | F12: Marrero | G12: LA | H12: 70072 | I12: 0.8 mi | J12: N/A | K12: N/A | L12: N/A | M12: 1673 | N12: N/A | O12: N/A | P12: N/A | Q12: 1995 | R12: N/A | S12: N/A | T12: N/A | U12: Not Listed | V12: 120 | W12: 2001 | X12: 1 | Y12: Varies | Z12: Varies | AA12: Varies | AB12: Varies | AC12: Varies | AD12: HIGH | AE12: Market Rate Comp #1: No income restrictions, 2001 vintage (1 yr diff), 120 units, 1.2 mi from subject. Shows market-rate rents vs. affordable housing discount. | AF12: https://www.rentcafe.com/apartments-for-rent/us/la/marrero/
A13: 2 | B13: MARKET RATE | C13: 2808 Pritchard Rd | E13: 2808 Pritchard Rd | F13: Marrero | G13: LA | H13: 70072 | I13: 1.2 mi | J13: N/A | K13: N/A | L13: N/A | M13: 1250 | N13: N/A | O13: N/A | P13: N/A | Q13: 2150 | R13: N/A | S13: N/A | T13: N/A | U13: Not Listed | V13: 96 | W13: 1999 | X13: 1 | Y13: Varies | Z13: Varies | AA13: Varies | AB13: Varies | AC13: Varies | AD13: HIGH | AE13: Market Rate Comp #2: No income restrictions, 1999 vintage (1 yr diff), 96 units, 4.0 mi from subject. Shows market-rate rents vs. affordable housing discount. | AF13: https://www.rentcafe.com/apartments-for-rent/us/la/harvey/
A14: 3 | B14: MARKET RATE | C14: 5007 Towering Oaks Ave | E14: 5007 Towering Oaks Ave | F14: Marrero | G14: LA | H14: 70072 | I14: 1.5 mi | J14: N/A | K14: N/A | L14: N/A | M14: 1300 | N14: N/A | O14: N/A | P14: N/A | Q14: 1700 | R14: N/A | S14: N/A | T14: N/A | U14: Not Listed | V14: 80 | W14: 2002 | X14: 2 | Y14: Varies | Z14: Varies | AA14: Varies | AB14: Varies | AC14: Varies | AD14: HIGH | AE14: Market Rate Comp #3: No income restrictions, 2002 vintage (2 yr diff), 80 units, 6.0 mi from subject. Shows market-rate rents vs. affordable housing discount. | AF14: https://www.rentcafe.com/apartments-for-rent/us/la/gretna/
A15: 4 | B15: MARKET RATE | C15: 437 Robinson Ave | E15: 437 Robinson Ave | F15: Marrero | G15: LA | H15: 70072 | I15: 0.6 mi | J15: N/A | K15: N/A | L15: N/A | M15: 1050 | N15: N/A | O15: N/A | P15: N/A | Q15: 1625 | R15: N/A | S15: N/A | T15: N/A | U15: Not Listed | V15: 64 | W15: 2000 | X15: 0 | Y15: Varies | Z15: Varies | AA15: Varies | AB15: Varies | AC15: Varies | AD15: HIGH | AE15: Market Rate Comp #4: No income restrictions, 2000 vintage (0 yr diff), 64 units, 5.5 mi from subject. Shows market-rate rents vs. affordable housing discount. | AF15: https://www.rentcafe.com/apartments-for-rent/us/la/gretna/
A16: 5 | B16: MARKET RATE | C16: 1501 Somerset Pl | E16: 1501 Somerset Pl | F16: Marrero | G16: LA | H16: 70072 | I16: 0.9 mi | J16: N/A | K16: N/A | L16: N/A | M16: N/A | N16: N/A | O16: N/A | P16: N/A | Q16: 1850 | R16: N/A | S16: N/A | T16: N/A | U16: N/A | V16: N/A | W16: N/A | X16: N/A | Y16: N/A | Z16: N/A | AA16: N/A | AB16: N/A | AC16: N/A | AD16: BENCHMARK | AE16: BENCHMARK — HUD Fair Market Rent (FMR) for New Orleans MSA, effective FY2026. The FMR represents the 40th percentile of gross rents for standard-quality units in this metro area, as published annually by HUD. It is used here as the market reference point. LIHTC-restricted rents are typically 40–70% of FMR depending on the AMI tier. | AF16: HUD FMR Database (huduser.gov)
A17: 6 | B17: MARKET RATE | C17: 1513 R. Esplanade | E17: 1513 R. Esplanade | F17: Marrero | G17: LA | H17: 70072 | I17: 0.7 mi | J17: N/A | K17: N/A | L17: N/A | M17: N/A | N17: N/A | O17: N/A | P17: N/A | Q17: N/A | R17: N/A | S17: N/A | T17: N/A | U17: 2800 | V17: N/A | W17: N/A | X17: N/A | Y17: N/A | Z17: N/A | AA17: N/A | AB17: N/A | AC17: N/A | AD17: BENCHMARK | AE17: BENCHMARK — Estimated Metro Market Average for Marrero, calculated at approximately 110% of the HUD FMR. This represents the typical asking rent for unrestricted market-rate units in this area. The gap between this figure and the affordable comp rents above shows the affordability discount our properties provide. | AF17: HUD FMR + Market Estimate
A18: 7 | B18: MARKET RATE | J18: N/A | K18: N/A | L18: N/A | N18: N/A | O18: N/A | P18: N/A | R18: N/A | S18: N/A | T18: N/A
A19: — | B19: BENCHMARK | C19: FY2026 FMR — New Orleans MSA | E19: N/A | F19: Marrero | G19: LA | L19: $1,254 | P19: $1,573 | T19: $1,818
A20: — | B20: BENCHMARK | C20: Metro Market Avg — Marrero (Apartments.com) | E20: N/A | F20: Marrero | G20: LA | M20: 1318 | Q20: 1864 | U20: 2800
A22: COLOR KEY: GREEN = Subject Property | LIGHT GREEN = Affordable Comps (LIHTC/Section 8/HUD) | LIGHT BLUE = Market Rate Comps | ORANGE = Actual Advertised Rent
A24: CURRENT RENT vs. MARKET AVERAGE
A25: Market Average = Avg of Actual Advertised Rents from Market-Rate Comps (Apartments.com)
B26: Current Rents | C26: Market Avg | E26: Difference
A27: 2BD | B27: ='Current Rents'!E27 -> 0 | C27: 1318 | E27: =B27-C27 -> -1318 | F27: =IF(E27<-75,"LOOK INTO INCREASING THE RENT!","") -> LOOK INTO INCREASING THE RENT!
A28: 3BD | B28: ='Current Rents'!F27 -> 1223 | C28: 1864 | E28: =B28-C28 -> -641 | F28: =IF(E28<-75,"LOOK INTO INCREASING THE RENT!","") -> LOOK INTO INCREASING THE RENT!
A29: 4BD | B29: ='Current Rents'!G27 -> 870 | C29: 2800 | E29: =B29-C29 -> -1930 | F29: =IF(E29<-75,"LOOK INTO INCREASING THE RENT!","") -> LOOK INTO INCREASING THE RENT!
A32: PMTS — Vouchers / FMR / UAP / NET
B33: MKT | C33: VCH | D33: FMR | E33: UAP | F33: NET
A34: 2BD | C34: ='Current Rents'!E27 -> 0 | D34: 1254
A35: 3BD | C35: ='Current Rents'!F27 -> 1223 | D35: 1573
A36: 4BD | C36: ='Current Rents'!G27 -> 870 | D36: 1818

Sheet 20 - Thibodaux
A1: RENT COMPARABLES ANALYSIS — Colonial Estates | AE1: ID: 20
A2: 1300 Ridgefield Ave, Thibodaux, LA 70301 | 107 units | Section 8/HUD
A3: Data as of June 2026 | Sources: CoStar, Apartments.com, HUD, Zillow
A4: COLUMN GUIDE — Income-restricted rent limits (50% AMI, 60% AMI), HUD Fair Market Rent (FMR), and Actual Advertised Rent for each bedroom size.
A5: Rank | B5: Type | C5: Property Name | E5: Address | F5: City | G5: St | H5: ZIP | I5: Distance | J5: 1BD 50% AMI | K5: 1BD 60% AMI | L5: 1BD FMR | M5: 1BD - Actual | N5: 2BD 50% AMI | O5: 2BD 60% AMI | P5: 2BD FMR | Q5: 2BD - Actual | R5: 3BD 50% AMI | S5: 3BD 60% AMI | T5: 3BD FMR | U5: 3BD - Actual | V5: Units | W5: Yr Built | X5: Yr Diff | Y5: Utils Incl. | Z5: Pet Friendly | AA5: Gated | AB5: Pool | AC5: W/D In-Unit | AD5: Competition Level | AE5: Notes / Why Competitive | AF5: Data Source
A6: ★ | B6: SUBJECT | C6: Colonial Estates (SUBJECT) | E6: 1300 Ridgefield Ave | F6: Thibodaux | G6: LA | H6: 70301 | I6: 0.0 mi | J6: $2,368 | K6: $2,842 | L6: $739 | M6: ='Current Rents'!D28 -> — | N6: $2,841 | O6: $3,410 | P6: $1,012 | Q6: ='Current Rents'!E28 -> 894 | R6: $3,154 | S6: $3,785 | T6: $1,264 | U6: ='Current Rents'!F28 -> 982 | V6: 107 | W6: 1975 | X6: 0 | Y6: Yes | Z6: No | AA6: No | AB6: No | AC6: No | AD6: N/A
A7: 1 | B7: AFFORDABLE | C7: Bayou Terrace Apartments | E7: 600 Canal Blvd | F7: Thibodaux | G7: LA | H7: 70301 | I7: 1.5 mi | J7: $2,368 | K7: $2,842 | L7: $739 | M7: Not Listed | N7: $2,841 | O7: $3,410 | P7: $1,012 | Q7: Not Listed | R7: $3,154 | S7: $3,785 | T7: $1,264 | U7: Not Listed | V7: 100 | W7: 1976 | X7: 1 | Y7: Yes | Z7: No | AA7: No | AB7: No | AC7: No | AD7: HIGH | AE7: Affordable Comp #1: Section 8/HUD property, 1976 vintage (1 yr diff), 100 units, 1.5 mi from subject. Same income-eligible renter pool. | AF7: HUD Multifamily Assisted Housing
A8: 2 | B8: AFFORDABLE | C8: Houma Gardens | E8: 1200 Grand Caillou Rd | F8: Houma | G8: LA | H8: 70363 | I8: 18.0 mi | J8: $2,368 | K8: $2,842 | L8: $739 | M8: Not Listed | N8: $2,841 | O8: $3,410 | P8: $1,012 | Q8: Not Listed | R8: $3,154 | S8: $3,785 | T8: $1,264 | U8: Not Listed | V8: 120 | W8: 1975 | X8: 0 | Y8: Yes | Z8: No | AA8: No | AB8: No | AC8: No | AD8: MODERATE-HIGH | AE8: Affordable Comp #2: Section 8/HUD property, 1975 vintage (0 yr diff), 120 units, 18.0 mi from subject. Same income-eligible renter pool. | AF8: HUD Multifamily Assisted Housing
A9: 3 | B9: AFFORDABLE | C9: Morgan City Manor | E9: 700 Brashear Ave | F9: Morgan City | G9: LA | H9: 70380 | I9: 42.0 mi | J9: $2,368 | K9: $2,842 | L9: $739 | M9: $670 | N9: $2,841 | O9: $3,410 | P9: $1,012 | Q9: $924 | R9: $3,154 | S9: $3,785 | T9: $1,264 | U9: Not Listed | V9: 96 | W9: 1977 | X9: 2 | Y9: Yes | Z9: No | AA9: No | AB9: No | AC9: No | AD9: MODERATE | AE9: Affordable Comp #3: Section 8/HUD property, 1977 vintage (2 yr diff), 96 units, 42.0 mi from subject. Same income-eligible renter pool. | AF9: HUD Multifamily Assisted Housing
A10: 4 | B10: AFFORDABLE | C10: Lafourche Parish Housing Authority - Lockport Homes | E10: 200 Main St | F10: Lockport | G10: LA | H10: 70374 | I10: 12.0 mi | J10: $2,368 | K10: $2,842 | L10: $739 | M10: Not Listed | N10: $2,841 | O10: $3,410 | P10: $1,012 | Q10: Not Listed | R10: $3,154 | S10: $3,785 | T10: $1,264 | U10: Not Listed | V10: 88 | W10: 1976 | X10: 1 | Y10: Yes | Z10: No | AA10: No | AB10: No | AC10: No | AD10: HIGH | AE10: Affordable Comp #4: Public Housing/HUD property, 1976 vintage (1 yr diff), 88 units, 12.0 mi from subject. Same income-eligible renter pool. | AF10: Lafourche Parish Housing Authority
A11: 5 | B11: AFFORDABLE
A12: 1 | B12: MARKET RATE | C12: Chateau Audubon Apartments | D12: COMPETITION | E12: 106 Beham Ct | F12: Thibodaux | G12: LA | H12: 70301 | I12: 0.5 mi | J12: N/A | K12: N/A | L12: N/A | M12: 850 | N12: N/A | O12: N/A | P12: N/A | Q12: 1050 | R12: N/A | S12: N/A | T12: N/A | U12: 1295 | V12: N/A | W12: 1975 | X12: 0 | Y12: Varies | Z12: Varies | AA12: Varies | AB12: Varies | AC12: Varies | AD12: HIGH | AE12: Market Rate Comp #1: No income restrictions, 1975 vintage (0 yr diff), N/A units, N/A from subject. Shows market-rate rents vs. affordable housing discount. | AF12: HUD FY2026 FMR - Lafourche Parish, LA (limited market rate listings for 1965-1985 vintage)
A13: 2 | B13: MARKET RATE | C13: Bayou Reserve | E13: 2464 Talbot Ave | F13: Thibodaux | G13: LA | H13: 70301 | I13: 1.2 mi | J13: N/A | K13: N/A | L13: N/A | M13: 939 | N13: N/A | O13: N/A | P13: N/A | Q13: 1089 | R13: N/A | S13: N/A | T13: N/A | U13: 1325 | V13: N/A | W13: 1978 | X13: 3 | Y13: Varies | Z13: Varies | AA13: Varies | AB13: Varies | AC13: Varies | AD13: MODERATE-HIGH | AE13: Market Rate Comp #2: No income restrictions, 1978 vintage (3 yr diff), N/A units, 20.0 mi from subject. Shows market-rate rents vs. affordable housing discount. | AF13: HUD FY2026 FMR - Terrebonne Parish, LA
A14: 3 | B14: MARKET RATE | C14: Colonial Estates | E14: 1300 Ridgefield Ave | F14: Thibodaux | G14: LA | H14: 70301 | I14: 0.8 mi | J14: N/A | K14: N/A | L14: N/A | M14: 800 | N14: N/A | O14: N/A | P14: N/A | Q14: 900 | R14: N/A | S14: N/A | T14: N/A | U14: 1000 | V14: N/A | W14: 1972 | X14: 3 | Y14: Varies | Z14: Varies | AA14: Varies | AB14: Varies | AC14: Varies | AD14: MODERATE-HIGH | AE14: Market Rate Comp #3: No income restrictions, 1972 vintage (3 yr diff), N/A units, 22.0 mi from subject. Shows market-rate rents vs. affordable housing discount. | AF14: HUD FY2026 FMR - Terrebonne Parish, LA
A15: 4 | B15: MARKET RATE | C15: Turnberry Townhomes | E15: 130 Leighton Dr | F15: Thibodaux | G15: LA | H15: 70301 | I15: 1.5 mi | J15: N/A | K15: N/A | L15: N/A | M15: 850 | N15: N/A | O15: N/A | P15: N/A | Q15: 1275 | R15: N/A | S15: N/A | T15: N/A | U15: 1300 | V15: N/A | W15: 1978 | X15: 3 | Y15: Varies | Z15: Varies | AA15: Varies | AB15: Varies | AC15: Varies | AD15: HIGH | AE15: Market Rate Comp #4: No income restrictions, 1978 vintage (3 yr diff), N/A units, N/A from subject. Shows market-rate rents vs. affordable housing discount. | AF15: HUD FY2026 FMR - Lafourche Parish, LA
A16: 5 | B16: MARKET RATE | C16: Acadia Villas Apartment Homes | E16: 624 Percy Rd | F16: Thibodaux | G16: LA | H16: 70301 | I16: 1.1 mi | J16: N/A | K16: N/A | L16: N/A | M16: 1325 | N16: N/A | O16: N/A | P16: N/A | Q16: 1575 | R16: N/A | S16: N/A | T16: N/A | U16: 1735 | V16: N/A | W16: N/A | X16: N/A | Y16: N/A | Z16: N/A | AA16: N/A | AB16: N/A | AC16: N/A | AD16: BENCHMARK | AE16: BENCHMARK — HUD Fair Market Rent (FMR) for Lafourche Parish, LA, effective FY2026. The FMR represents the 40th percentile of gross rents for standard-quality units in this metro area, as published annually by HUD. It is used here as the market reference point. LIHTC-restricted rents are typically 40–70% of FMR depending on the AMI tier. | AF16: HUD FMR Database (huduser.gov)
A17: 6 | B17: MARKET RATE | C17: 1359 LA-20 | E17: 1359 LA-20 | F17: Thibodaux | G17: LA | H17: 70301 | I17: 2.0 mi | J17: N/A | K17: N/A | L17: N/A | M17: N/A | N17: N/A | O17: N/A | P17: N/A | Q17: 1250 | R17: N/A | S17: N/A | T17: N/A | U17: N/A | V17: N/A | W17: N/A | X17: N/A | Y17: N/A | Z17: N/A | AA17: N/A | AB17: N/A | AC17: N/A | AD17: BENCHMARK | AE17: BENCHMARK — Estimated Metro Market Average for Thibodaux, calculated at approximately 110% of the HUD FMR. This represents the typical asking rent for unrestricted market-rate units in this area. The gap between this figure and the affordable comp rents above shows the affordability discount our properties provide. | AF17: HUD FMR + Market Estimate
A18: 7 | B18: MARKET RATE | J18: N/A | K18: N/A | L18: N/A | N18: N/A | O18: N/A | P18: N/A | R18: N/A | S18: N/A | T18: N/A
A19: — | B19: BENCHMARK | C19: FY2026 FMR — Lafourche Parish, LA | E19: N/A | F19: Thibodaux | G19: LA | L19: $739 | P19: $1,012 | T19: $1,264
A20: — | B20: BENCHMARK | C20: Metro Market Avg — Thibodaux (Apartments.com) | E20: N/A | F20: Thibodaux | G20: LA | M20: 953 | Q20: 1190 | U20: 1331
A22: COLOR KEY: GREEN = Subject Property | LIGHT GREEN = Affordable Comps (LIHTC/Section 8/HUD) | LIGHT BLUE = Market Rate Comps | ORANGE = Actual Advertised Rent
A24: CURRENT RENT vs. MARKET AVERAGE
A25: Market Average = Avg of Actual Advertised Rents from Market-Rate Comps (Apartments.com)
B26: Current Rents | C26: Market Avg | E26: Difference
A27: 1BD | B27: ='Current Rents'!D28 -> — | C27: 953 | E27: =B27-C27 -> #VALUE! | F27: =IF(E27<-75,"LOOK INTO INCREASING THE RENT!","") -> #VALUE!
A28: 2BD | B28: ='Current Rents'!E28 -> 894 | C28: 1190 | E28: =B28-C28 -> -296 | F28: =IF(E28<-75,"LOOK INTO INCREASING THE RENT!","") -> LOOK INTO INCREASING THE RENT!
A29: 3BD | B29: ='Current Rents'!F28 -> 982 | C29: 1331 | E29: =B29-C29 -> -349 | F29: =IF(E29<-75,"LOOK INTO INCREASING THE RENT!","") -> LOOK INTO INCREASING THE RENT!
A32: PMTS — Vouchers / FMR / UAP / NET
B33: MKT | C33: VCH | D33: FMR | E33: UAP | F33: NET
A34: 1BD | C34: ='Current Rents'!D28 -> — | D34: 739
A35: 2BD | C35: ='Current Rents'!E28 -> 894 | D35: 1012
A36: 3BD | C36: ='Current Rents'!F28 -> 982 | D36: 1264

Sheet 40 - Marrero
A1: RENT COMPARABLES ANALYSIS — Marrero 3 | AA1: ID: 40
A2: 1050 Manhattan Blvd, Harvey, LA 70058 | 173 units | Section 8/HUD
A3: Data as of June 2026 | Sources: CoStar, Apartments.com, HUD, Zillow
A4: COLUMN GUIDE — Income-restricted rent limits (50% AMI, 60% AMI), HUD Fair Market Rent (FMR), and Actual Advertised Rent for each bedroom size.
A5: Rank | B5: Type | C5: Property Name | E5: Address | F5: City | G5: St | H5: ZIP | I5: Distance | J5: 3BD 50% AMI | K5: 3BD 60% AMI | L5: 3BD FMR | M5: 3BD - Actual | N5: 4BD 50% AMI | O5: 4BD 60% AMI | P5: 4BD FMR | Q5: 4BD - Actual | R5: Units | S5: Yr Built | T5: Yr Diff | U5: Utils Incl. | V5: Pet Friendly | W5: Gated | X5: Pool | Y5: W/D In-Unit | Z5: Competition Level | AA5: Notes / Why Competitive | AB5: Data Source
A6: ★ | B6: SUBJECT | C6: Marrero 3 (SUBJECT) | E6: 1050 Manhattan Blvd | F6: Harvey | G6: LA | H6: 70058 | I6: 0.0 mi | J6: $3,741 | K6: $4,490 | L6: $1,573 | M6: ='Current Rents'!F29 -> 0 | N6: $4,041 | O6: $4,850 | P6: $1,818 | Q6: ='Current Rents'!G29 -> 0 | R6: 173 | S6: 1968 | T6: 0 | U6: Yes | V6: No | W6: No | X6: No | Y6: No | Z6: N/A
A7: 1 | B7: AFFORDABLE | C7: Westchase Apartments | E7: 1013 Manhattan Blvd | F7: Harvey | G7: LA | H7: 70058 | I7: 0.3 mi | J7: $3,741 | K7: $4,490 | L7: $1,573 | M7: Not Listed | N7: $4,041 | O7: $4,850 | P7: $1,818 | Q7: Not Listed | R7: 200 | S7: 1970 | T7: 2 | U7: Yes | V7: No | W7: No | X7: No | Y7: No | Z7: HIGH | AA7: Affordable Comp #1: Section 8/HUD property, 1970 vintage (2 yr diff), 200 units, 0.3 mi from subject. Same income-eligible renter pool. | AB7: AffordableHousingOnline.com
A8: 2 | B8: AFFORDABLE | C8: Gretna Manor Apartments | E8: 400 Huey P Long Ave | F8: Gretna | G8: LA | H8: 70053 | I8: 3.5 mi | J8: $3,741 | K8: $4,490 | L8: $1,573 | M8: Not Listed | N8: $4,041 | O8: $4,850 | P8: $1,818 | Q8: Not Listed | R8: 180 | S8: 1972 | T8: 4 | U8: Yes | V8: No | W8: No | X8: No | Y8: No | Z8: HIGH | AA8: Affordable Comp #2: Section 8/HUD property, 1972 vintage (4 yr diff), 180 units, 3.5 mi from subject. Same income-eligible renter pool. | AB8: HUD Multifamily Assisted Housing
A9: 3 | B9: AFFORDABLE | C9: New Orleans East Apartments | E9: 6000 Read Blvd | F9: New Orleans | G9: LA | H9: 70127 | I9: 12.0 mi | J9: $3,741 | K9: $4,490 | L9: $1,573 | M9: Not Listed | N9: $4,041 | O9: $4,850 | P9: $1,818 | Q9: Not Listed | R9: 160 | S9: 1970 | T9: 2 | U9: Yes | V9: No | W9: No | X9: No | Y9: No | Z9: HIGH | AA9: Affordable Comp #3: Section 8/HUD property, 1970 vintage (2 yr diff), 160 units, 12.0 mi from subject. Same income-eligible renter pool. | AB9: HUD Multifamily Assisted Housing
A10: 4 | B10: AFFORDABLE | C10: Jefferson Parish Housing Authority - Woodmere Homes | E10: 1200 Woodmere Blvd | F10: Harvey | G10: LA | H10: 70058 | I10: 2.1 mi | J10: $3,741 | K10: $4,490 | L10: $1,573 | M10: Not Listed | N10: $4,041 | O10: $4,850 | P10: $1,818 | Q10: Not Listed | R10: 180 | S10: 1969 | T10: 1 | U10: Yes | V10: No | W10: No | X10: No | Y10: No | Z10: HIGH | AA10: Affordable Comp #4: Public Housing/HUD property, 1969 vintage (1 yr diff), 180 units, 2.1 mi from subject. Same income-eligible renter pool. | AB10: Jefferson Parish Housing Authority
A11: 5 | B11: AFFORDABLE
A12: 1 | B12: MARKET RATE | C12: Windsor at Manhattan | D12: COMPETITION | E12: 1499 Central Park Blvd | F12: Harvey | G12: LA | H12: 70058 | I12: 0.4 mi | J12: N/A | K12: N/A | L12: N/A | M12: 2100 | N12: N/A | O12: N/A | P12: N/A | Q12: Not Listed | R12: N/A | S12: 1968 | T12: 0 | U12: Varies | V12: Varies | W12: Varies | X12: Varies | Y12: Varies | Z12: HIGH | AA12: Market Rate Comp #1: No income restrictions, 1968 vintage (0 yr diff), N/A units, N/A from subject. Shows market-rate rents vs. affordable housing discount. | AB12: HUD FY2026 FMR - Jefferson Parish, LA (limited market rate listings for 1958-1978 vintage)
A13: 2 | B13: MARKET RATE | C13: 2713 Cerritas Via | E13: 2713 Cerritas Via | F13: Harvey | G13: LA | H13: 70058 | I13: 1.0 mi | J13: N/A | K13: N/A | L13: N/A | M13: 2000 | N13: N/A | O13: N/A | P13: N/A | Q13: Not Listed | R13: N/A | S13: 1965 | T13: 3 | U13: Varies | V13: Varies | W13: Varies | X13: Varies | Y13: Varies | Z13: HIGH | AA13: Market Rate Comp #2: No income restrictions, 1965 vintage (3 yr diff), N/A units, 3.0 mi from subject. Shows market-rate rents vs. affordable housing discount. | AB13: HUD FY2026 FMR - Jefferson Parish, LA
A14: 3 | B14: MARKET RATE | C14: 1148 Lochlomand Dr | E14: 1148 Lochlomand Dr | F14: Harvey | G14: LA | H14: 70058 | I14: 1.2 mi | J14: N/A | K14: N/A | L14: N/A | M14: 1800 | N14: N/A | O14: N/A | P14: N/A | Q14: Not Listed | R14: N/A | S14: 1970 | T14: 2 | U14: Varies | V14: Varies | W14: Varies | X14: Varies | Y14: Varies | Z14: HIGH | AA14: Market Rate Comp #3: No income restrictions, 1970 vintage (2 yr diff), N/A units, 5.0 mi from subject. Shows market-rate rents vs. affordable housing discount. | AB14: HUD FY2026 FMR - Jefferson Parish, LA
A15: 4 | B15: MARKET RATE | C15: 1549 Spanish Oaks Dr | E15: 1549 Spanish Oaks Dr | F15: Harvey | G15: LA | H15: 70058 | I15: 0.8 mi | J15: N/A | K15: N/A | L15: N/A | M15: 1550 | N15: N/A | O15: N/A | P15: N/A | Q15: 1900 | R15: N/A | S15: 1966 | T15: 2 | U15: Varies | V15: Varies | W15: Varies | X15: Varies | Y15: Varies | Z15: HIGH | AA15: Market Rate Comp #4: No income restrictions, 1966 vintage (2 yr diff), N/A units, 7.0 mi from subject. Shows market-rate rents vs. affordable housing discount. | AB15: HUD FY2026 FMR - Jefferson Parish, LA
A16: 5 | B16: MARKET RATE | C16: 1522 Maplewood Dr | E16: 1522 Maplewood Dr | F16: Harvey | G16: LA | H16: 70058 | I16: 0.6 mi | J16: N/A | K16: N/A | L16: N/A | M16: 1700 | N16: N/A | O16: N/A | P16: N/A | Q16: N/A | R16: N/A | S16: N/A | T16: N/A | U16: N/A | V16: N/A | W16: N/A | X16: N/A | Y16: N/A | Z16: BENCHMARK | AA16: BENCHMARK — HUD Fair Market Rent (FMR) for New Orleans MSA, effective FY2026. The FMR represents the 40th percentile of gross rents for standard-quality units in this metro area, as published annually by HUD. It is used here as the market reference point. LIHTC-restricted rents are typically 40–70% of FMR depending on the AMI tier. | AB16: HUD FMR Database (huduser.gov)
A17: 6 | B17: MARKET RATE | C17: 1720 Huey P Long Ave | E17: 1720 Huey P Long Ave | F17: Harvey | G17: LA | H17: 70058 | I17: 1.5 mi | J17: N/A | K17: N/A | L17: N/A | M17: 1650 | N17: N/A | O17: N/A | P17: N/A | Q17: N/A | R17: N/A | S17: N/A | T17: N/A | U17: N/A | V17: N/A | W17: N/A | X17: N/A | Y17: N/A | Z17: BENCHMARK | AA17: BENCHMARK — Estimated Metro Market Average for Harvey, calculated at approximately 110% of the HUD FMR. This represents the typical asking rent for unrestricted market-rate units in this area. The gap between this figure and the affordable comp rents above shows the affordability discount our properties provide. | AB17: HUD FMR + Market Estimate
A18: 7 | B18: MARKET RATE | J18: N/A | K18: N/A | L18: N/A | N18: N/A | O18: N/A | P18: N/A
A19: — | B19: BENCHMARK | C19: FY2026 FMR — New Orleans MSA | E19: N/A | F19: Harvey | G19: LA | L19: $1,573 | P19: $1,818
A20: — | B20: BENCHMARK | C20: Metro Market Avg — Harvey (Apartments.com) | E20: N/A | F20: Harvey | G20: LA | M20: 1800 | Q20: 1900
A22: COLOR KEY: GREEN = Subject Property | LIGHT GREEN = Affordable Comps (LIHTC/Section 8/HUD) | LIGHT BLUE = Market Rate Comps | ORANGE = Actual Advertised Rent
A24: CURRENT RENT vs. MARKET AVERAGE
A25: Market Average = Avg of Actual Advertised Rents from Market-Rate Comps (Apartments.com)
B26: Current Rents | C26: Market Avg | E26: Difference
A27: 3BD | B27: ='Current Rents'!F29 -> 0 | C27: 1800 | E27: =B27-C27 -> -1800 | F27: =IF(E27<-75,"LOOK INTO INCREASING THE RENT!","") -> LOOK INTO INCREASING THE RENT!
A28: 4BD | B28: ='Current Rents'!G29 -> 0 | C28: 1900 | E28: =B28-C28 -> -1900 | F28: =IF(E28<-75,"LOOK INTO INCREASING THE RENT!","") -> LOOK INTO INCREASING THE RENT!
A31: PMTS — Vouchers / FMR / UAP / NET
B32: MKT | C32: VCH | D32: FMR | E32: UAP | F32: NET
A33: 3BD | C33: ='Current Rents'!F29 -> 0 | D33: 1573
A34: 4BD | C34: ='Current Rents'!G29 -> 0 | D34: 1818

Sheet 37 - Arbor Crest
A1: RENT COMPARABLES ANALYSIS — Arbor Crest | AE1: ID: 37
A2: 64 N Cleveland Street, Quincy, FL 32351 | 120 units | LIHTC
A3: Data as of June 2026 | Sources: CoStar, Apartments.com, HUD, Zillow
A4: COLUMN GUIDE — Income-restricted rent limits (50% AMI, 60% AMI), HUD Fair Market Rent (FMR), and Actual Advertised Rent for each bedroom size.
A5: Rank | B5: Type | C5: Property Name | E5: Address | F5: City | G5: St | H5: ZIP | I5: Distance | J5: 1BD 50% AMI | K5: 1BD 60% AMI | L5: 1BD FMR | M5: 1BD - Actual | N5: 2BD 50% AMI | O5: 2BD 60% AMI | P5: 2BD FMR | Q5: 2BD - Actual | R5: 3BD 50% AMI | S5: 3BD 60% AMI | T5: 3BD FMR | U5: 3BD - Actual | V5: Units | W5: Yr Built | X5: Yr Diff | Y5: Utils Incl. | Z5: Pet Friendly | AA5: Gated | AB5: Pool | AC5: W/D In-Unit | AD5: Competition Level | AE5: Notes / Why Competitive | AF5: Data Source
A6: ★ | B6: SUBJECT | C6: Arbor Crest (SUBJECT) | E6: 64 N Cleveland Street | F6: Quincy | G6: FL | H6: 32351 | I6: 0.0 mi | J6: $2,887 | K6: $3,465 | L6: $800 | M6: ='Current Rents'!D30 -> — | N6: $3,462 | O6: $4,155 | P6: $1,095 | Q6: ='Current Rents'!E30 -> 0 | R6: $3,845 | S6: $4,615 | T6: $1,372 | U6: ='Current Rents'!F30 -> 1401 | V6: 120 | W6: 1995 | X6: 0 | Y6: No | Z6: No | AA6: No | AB6: Yes | AC6: No | AD6: N/A
A7: 1 | B7: AFFORDABLE | C7: Springwood - Tallahassee | E7: 2660 Old Bainbridge Rd | F7: Tallahassee | G7: FL | H7: 32303 | I7: 17.4 mi | J7: $2,887 | K7: $3,465 | L7: $800 | M7: Not Listed | N7: $3,462 | O7: $4,155 | P7: $1,095 | Q7: Not Listed | R7: $3,845 | S7: $4,615 | T7: $1,372 | U7: $1,325 | V7: 113 | W7: 1995 | X7: 0 | Y7: Yes | Z7: No | AA7: No | AB7: No | AC7: No | AD7: MODERATE-HIGH | AE7: Affordable Comp #1: LIHTC property, 1995 vintage (0 yr diff), 113 units, 17.4 mi from subject. Same income-eligible renter pool. | AF7: HUD LIHTC Database (huduser.gov)
A8: 2 | B8: AFFORDABLE | C8: Savannah Sound | E8: 1950 N Point Blvd | F8: Tallahassee | G8: FL | H8: 32308 | I8: 21.5 mi | J8: $2,887 | K8: $3,465 | L8: $800 | M8: Not Listed | N8: $3,462 | O8: $4,155 | P8: $1,095 | Q8: Not Listed | R8: $3,845 | S8: $4,615 | T8: $1,372 | U8: Not Listed | V8: 160 | W8: 1995 | X8: 0 | Y8: Yes | Z8: No | AA8: No | AB8: No | AC8: No | AD8: MODERATE-HIGH | AE8: Affordable Comp #2: LIHTC property, 1995 vintage (0 yr diff), 160 units, 21.5 mi from subject. Same income-eligible renter pool. | AF8: HUD LIHTC Database (huduser.gov)
A9: 3 | B9: AFFORDABLE | C9: Biscayne Woods Apts | F9: Homestead | G9: FL | I9: N/A | J9: $2,887 | K9: $3,465 | L9: $800 | M9: Not Listed | N9: $3,462 | O9: $4,155 | P9: $1,095 | Q9: Not Listed | R9: $3,845 | S9: $4,615 | T9: $1,372 | U9: Not Listed | V9: 114 | W9: 1994 | X9: 1 | Y9: Yes | Z9: No | AA9: No | AB9: No | AC9: No | AD9: MODERATE | AE9: Affordable Comp #3: LIHTC property, 1994 vintage (1 yr diff), 114 units, N/A from subject. Same income-eligible renter pool. | AF9: HUD LIHTC Database (huduser.gov)
A10: 4 | B10: AFFORDABLE | C10: Oak Pointe | E10: 1747 Capital Cir Ne | F10: Tallahassee | G10: FL | H10: 32308 | I10: 22.8 mi | J10: $2,887 | K10: $3,465 | L10: $800 | M10: Not Listed | N10: $3,462 | O10: $4,155 | P10: $1,095 | Q10: Not Listed | R10: $3,845 | S10: $4,615 | T10: $1,372 | U10: Not Listed | V10: 184 | W10: 1993 | X10: 2 | Y10: Yes | Z10: No | AA10: No | AB10: No | AC10: No | AD10: MODERATE-HIGH | AE10: Affordable Comp #4: LIHTC property, 1993 vintage (2 yr diff), 184 units, 22.8 mi from subject. Same income-eligible renter pool. | AF10: HUD LIHTC Database (huduser.gov)
A11: 5 | B11: AFFORDABLE
A12: 1 | B12: MARKET RATE | C12: Arbours at Quincy | D12: COMPETITION | E12: 1880 Pat Thomas Pky | F12: Quincy | G12: FL | H12: 32351 | I12: 1.5 mi | J12: N/A | K12: N/A | L12: N/A | M12: 880 | N12: N/A | O12: N/A | P12: N/A | Q12: 1295 | R12: N/A | S12: N/A | T12: N/A | U12: 1625 | V12: N/A | W12: 1995 | X12: 0 | Y12: Varies | Z12: Varies | AA12: Varies | AB12: Varies | AC12: Varies | AD12: HIGH | AE12: Market Rate Comp #1: No income restrictions, 1995 vintage (0 yr diff), N/A units, N/A from subject. Shows market-rate rents vs. affordable housing discount. | AF12: HUD FY2026 FMR - Gadsden County, FL (limited market rate listings in Quincy)
A13: 2 | B13: MARKET RATE | C13: Ochlockonee Pointe Apartments | E13: 33870 Blue Star Hwy | F13: Midway | G13: FL | H13: 32343 | I13: 5.0 mi | J13: N/A | K13: N/A | L13: N/A | M13: 850 | N13: N/A | O13: N/A | P13: N/A | Q13: 970 | R13: N/A | S13: N/A | T13: N/A | U13: 1150 | V13: N/A | W13: 1998 | X13: 3 | Y13: No | Z13: Yes | AA13: Yes | AB13: Yes | AC13: Yes | AD13: HIGH | AE13: Market Rate Comp #2: No income restrictions, 1998 vintage (3 yr diff), N/A units, 8.5 mi from subject. Midway FL market-rate complex — closest unrestricted rental to Arbor Crest. Shows market-rate rents vs. affordable housing discount. | AF13: https://www.apartments.com/ochlockonee-pointe-apartments-midway-fl/
A14: 3 | B14: MARKET RATE | C14: 723 W Washington St | E14: 723 W Washington St | F14: Quincy | G14: FL | H14: 32351 | I14: 0.8 mi | J14: N/A | K14: N/A | L14: N/A | M14: 559 | N14: N/A | O14: N/A | P14: N/A | Q14: 1095 | R14: N/A | S14: N/A | T14: N/A | U14: Not Listed | V14: 48 | W14: 1997 | X14: 2 | Y14: No | Z14: Yes | AA14: Yes | AB14: No | AC14: Yes | AD14: HIGH | AE14: Market Rate Comp #3: No income restrictions, 1997 vintage (2 yr diff), 48 units, 0.5 mi from subject. Same city as Arbor Crest — direct local market rate benchmark. Shows market-rate rents vs. affordable housing discount. | AF14: https://www.apartments.com/omega-villas-quincy-fl/d7w38lk/
A15: 4 | B15: MARKET RATE | C15: 526 N Adams St | E15: 526 N Adams St | F15: Quincy | G15: FL | H15: 32351 | I15: 0.6 mi | J15: N/A | K15: N/A | L15: N/A | M15: 475 | N15: N/A | O15: N/A | P15: N/A | Q15: 1175 | R15: N/A | S15: N/A | T15: N/A | U15: Not Listed | V15: 81 | W15: 1993 | X15: 2 | Y15: No | Z15: Yes | AA15: Yes | AB15: No | AC15: Yes | AD15: HIGH | AE15: Market Rate Comp #4: No income restrictions, 1993 vintage (2 yr diff), 81 units, 0.7 mi from subject. Same city as Arbor Crest — direct local market rate benchmark. Shows market-rate rents vs. affordable housing discount. | AF15: https://www.apartments.com/triple-oaks-apartments-quincy-fl/3ey417e/
A16: 5 | B16: MARKET RATE | C16: 116 Milton St | E16: 116 Milton St | F16: Quincy | G16: FL | H16: 32351 | I16: 0.5 mi | J16: N/A | K16: N/A | L16: N/A | M16: N/A | N16: N/A | O16: N/A | P16: N/A | Q16: N/A | R16: N/A | S16: N/A | T16: N/A | U16: 1500 | V16: N/A | W16: N/A | X16: N/A | Y16: N/A | Z16: N/A | AA16: N/A | AB16: N/A | AC16: N/A | AD16: BENCHMARK | AE16: BENCHMARK — HUD Fair Market Rent (FMR) for Gadsden County, FL, effective FY2026. The FMR represents the 40th percentile of gross rents for standard-quality units in this metro area, as published annually by HUD. It is used here as the market reference point. LIHTC-restricted rents are typically 40–70% of FMR depending on the AMI tier. | AF16: HUD FMR Database (huduser.gov)
A17: 6 | B17: MARKET RATE | C17: Arbour Crest Apartments | E17: 64 N Cleveland St | F17: Quincy | G17: FL | H17: 32351 | I17: 0.1 mi | J17: N/A | K17: N/A | L17: N/A | M17: 920 | N17: N/A | O17: N/A | P17: N/A | Q17: 1098 | R17: N/A | S17: N/A | T17: N/A | U17: 1260 | V17: N/A | W17: N/A | X17: N/A | Y17: N/A | Z17: N/A | AA17: N/A | AB17: N/A | AC17: N/A | AD17: BENCHMARK | AE17: BENCHMARK — Estimated Metro Market Average for Quincy, calculated at approximately 110% of the HUD FMR. This represents the typical asking rent for unrestricted market-rate units in this area. The gap between this figure and the affordable comp rents above shows the affordability discount our properties provide. | AF17: HUD FMR + Market Estimate
A18: 7 | B18: MARKET RATE | J18: N/A | K18: N/A | L18: N/A | N18: N/A | O18: N/A | P18: N/A | R18: N/A | S18: N/A | T18: N/A
A19: — | B19: BENCHMARK | C19: FY2026 FMR — Gadsden County, FL | E19: N/A | F19: Quincy | G19: FL | L19: $800 | P19: $1,095 | T19: $1,372
A20: — | B20: BENCHMARK | C20: Metro Market Avg — Quincy (Apartments.com) | E20: N/A | F20: Quincy | G20: FL | M20: 737 | Q20: 1127 | U20: 1384
A22: COLOR KEY: GREEN = Subject Property | LIGHT GREEN = Affordable Comps (LIHTC/Section 8/HUD) | LIGHT BLUE = Market Rate Comps | ORANGE = Actual Advertised Rent
A24: CURRENT RENT vs. MARKET AVERAGE
A25: Market Average = Avg of Actual Advertised Rents from Market-Rate Comps (Apartments.com)
B26: Current Rents | C26: Market Avg | E26: Difference
A27: 1BD | B27: ='Current Rents'!D30 -> — | C27: 737 | E27: =B27-C27 -> #VALUE! | F27: =IF(E27<-75,"LOOK INTO INCREASING THE RENT!","") -> #VALUE!
A28: 2BD | B28: ='Current Rents'!E30 -> 0 | C28: 1127 | E28: =B28-C28 -> -1127 | F28: =IF(E28<-75,"LOOK INTO INCREASING THE RENT!","") -> LOOK INTO INCREASING THE RENT!
A29: 3BD | B29: ='Current Rents'!F30 -> 1401 | C29: 1384 | E29: =B29-C29 -> 17 | F29: =IF(E29<-75,"LOOK INTO INCREASING THE RENT!","")
A32: PMTS — Vouchers / FMR / UAP / NET
B33: MKT | C33: VCH | D33: FMR | E33: UAP | F33: NET
A34: 1BD | C34: ='Current Rents'!D30 -> — | D34: 800
A35: 2BD | C35: ='Current Rents'!E30 -> 0 | D35: 1095
A36: 3BD | C36: ='Current Rents'!F30 -> 1401 | D36: 1372

Sheet 33 - Windsor-Yorkshire
A1: RENT COMPARABLES ANALYSIS — Windsor/Yorkshire | AE1: ID: 33
A2: 2020 N. Hearne Avenue, Shreveport, LA 71107 | 134 units | LIHTC
A3: Data as of June 2026 | Sources: CoStar, Apartments.com, HUD, Zillow
A4: COLUMN GUIDE — Income-restricted rent limits (50% AMI, 60% AMI), HUD Fair Market Rent (FMR), and Actual Advertised Rent for each bedroom size.
A5: Rank | B5: Type | C5: Property Name | E5: Address | F5: City | G5: St | H5: ZIP | I5: Distance | J5: 1BD 50% AMI | K5: 1BD 60% AMI | L5: 1BD FMR | M5: 1BD - Actual | N5: 2BD 50% AMI | O5: 2BD 60% AMI | P5: 2BD FMR | Q5: 2BD - Actual | R5: 4BD 50% AMI | S5: 4BD 60% AMI | T5: 4BD FMR | U5: 4BD - Actual | V5: Units | W5: Yr Built | X5: Yr Diff | Y5: Utils Incl. | Z5: Pet Friendly | AA5: Gated | AB5: Pool | AC5: W/D In-Unit | AD5: Competition Level | AE5: Notes / Why Competitive | AF5: Data Source
A6: ★ | B6: SUBJECT | C6: Windsor/Yorkshire (SUBJECT) | E6: 2020 N. Hearne Avenue | F6: Shreveport | G6: LA | H6: 71107 | I6: 0.0 mi | J6: $2,554 | K6: $3,065 | L6: $736 | M6: ='Current Rents'!D31 -> 914 | N6: $3,066 | O6: $3,680 | P6: $1,008 | Q6: ='Current Rents'!E31 -> 1058 | R6: $3,679 | S6: $4,415 | T6: $1,457 | U6: ='Current Rents'!G31 -> — | V6: 134 | W6: 1998 | X6: 0 | Y6: No | Z6: No | AA6: No | AB6: Yes | AC6: No | AD6: N/A
